Workbook
Name ChartofAccountsTable: '[1]Chart of Accounts'!$B$7:$C$115

Sheet CF
B2: SEVEN-TRENT MACHINERIES INDUSTRIAL EQUIPMENT TRADING
B3: Summary of Cash Flows
B4: For the month ended January 2026
H5: Amounts in pesos
B6: CASH FLOWS ARISING FROM OPERATING ACTIVITIES
B7: Collections from Distribution and Hauling of Petroleum (+) [ Net of inter-account transfer] | H7: ='JAN 01-05 2026'!P17+'JAN 06-12 2026'!P17+'JAN 13-19 2026'!P17+'JAN 20-26 2026'!P17+'JAN 27-31 2026'!P17 -> 42043027
B8: Other Cash Collections relating to operating activities (+) | H8: ='JAN 01-05 2026'!O18+'JAN 06-12 2026'!O18+'JAN 13-19 2026'!O18+'JAN 20-26 2026'!O18+'JAN 27-31 2026'!O18 -> 673859.57 | K8: =H6+H8 -> 673859.57
B9: Payments to Supplier of Petroleum Products (-) | H9: =-('JAN 01-05 2026'!O20+'JAN 06-12 2026'!O20+'JAN 13-19 2026'!O20+'JAN 20-26 2026'!O20+'JAN 27-31 2026'!O20) -> -40872400 | K9: =H7+H9 -> 1170627
B10: RFP of Accounts Payable [ i.e other suppliers, 3rd parties] (-) | H10: =-('JAN 01-05 2026'!O21+'JAN 06-12 2026'!O21+'JAN 13-19 2026'!O21+'JAN 20-26 2026'!O21+'JAN 27-31 2026'!O21) -> -1425020.4 | K10: =H10 -> -1425020.4
B11: Cash Withdrawn for PCF Replenishment (-) | H11: =-('JAN 01-05 2026'!O22+'JAN 06-12 2026'!O22+'JAN 13-19 2026'!O22+'JAN 20-26 2026'!O23+'JAN 27-31 2026'!O23) -> -66223.25 | K11: =H11 -> -66223.25
B12: Other Cash payments relating to operating activities(-) | H12: =-('JAN 01-05 2026'!O25+'JAN 06-12 2026'!O25+'JAN 13-19 2026'!O25+'JAN 20-26 2026'!O26+'JAN 27-31 2026'!O26) -> -461000.1 | K12: =H12 -> -461000.1
B13: Net cash flows provided by operating activities (+/-) | H13: =H7+H8+H9+H10+H11+H12 -> -107757.23 | K13: =K9+K10+K11+K12+K8 -> -107757.23 | L13: =H13-K13 -> 3.4924597e-10
B14: CASH FLOWS FROM INVESTING ACTIVITIES
B15: Purchase of Property, Plant & Equipment ( CAPEX ) | H15: =-('JAN 20-26 2026'!O22) -> -3040
H16: 0
B17: Net cash flows used in investing activities | H17: =H15+H16 -> -3040
B18: CASH FLOWS ARISING FROM FINANCING ACTIVITIES
B19: Funds Borrowed from other account (+) | H19: ='JAN 01-05 2026'!O19+'JAN 06-12 2026'!O19+'JAN 13-19 2026'!O19+'JAN 20-26 2026'!O19+'JAN 27-31 2026'!O19 -> 3517300
B20: Checks Cleared for Loan / Fund Repayments (-) | H20: =-('JAN 01-05 2026'!O26+'JAN 06-12 2026'!O26+'JAN 13-19 2026'!O26+'JAN 20-26 2026'!O27+'JAN 27-31 2026'!O27) -> -4348194.7
B21: Net cash flows used in financing activities (+/-) | H21: =H20+H19 -> -830894.73 | N21: 6D
B22: NET INCREASE / (DECREASE) IN CASH | H22: =H21+H17+H13 -> -941691.96 | N22: PO 6D 837- GAMPIS | O22: 1 | V22: 53650
B23: Add: CASH AT THE BEGINNING OF THE CYCLE | H23: ='JAN 01-05 2026'!O3 -> 2412842.5 | U23: -
B24: Less: ADB, Maintaining Balance | H24: =-'JAN 01-05 2026'!O4 -> -155000
B25: CASH AVAILABLE AT THE END OF THE MONTH | H25: =H22+H23+H24 -> 1316150.6 | J25: ='JAN 27-31 2026'!O8 -> 1316150.6 | K25: =H25-J25 -> 0 | U25: -
J26: =H25-H24 -> 1471150.6 | U26: -
J27: =J25-J26 -> -155000

Sheet COLLECTIBLES
C1: DISTRIBUTION AND HAULING DEPARTMENT | F1: FINANCE AND ACCOUNTING DEPARTMENT
C2: PERIOD: AUG 19-AUG 25, 2025 | D2: AMOUNT | F2: PERIOD: AUG 19-AUG 25, 2025 | G2: AMOUNT
C3: PARTICULARS | F3: PARTICULARS | L3: CASHIER:
C4: TOTAL NET AMOUNT CLIENT PAID CURRENT | D4: =D9 -> 6615525 | F4: TOTAL AMOUNT CLIENT PAID | G4: ='JAN 01-05 2026'!O17+'JAN 01-05 2026'!O18-'JAN 01-05 2026'!O24 -> 7004321.2 | I4: =D12-G4 -> -491396.17 | M4: RECONCILIATION
C5: TOTAL DEPOT AMOUNT PAID | D5: 6315100 | F5: BORROWINGS FROM OTHER ACCOUNT (EW) | G5: 0 | M5: PASSBOOKS | N5: =G4 -> 7004321.2
C6: GROSS MARK - UP | D6: =D4-D5 -> 300425 | F6: TOTAL DEPOT AMOUNT PAID | G6: ='JAN 01-05 2026'!O20 -> 7641900 | I6: =D5-G6 -> -1326800 | M6: GCASH | N6: 5050
F7: EXCESS CASH REMAINING FROM COLLECTIONS | G7: =G4-G6 -> -637578.83 | M7: OTHER BANK CREDITS | N7: -292.55 | P7: =N5+N6+N7+N8+N9+N10+N11 -> 6965278.6
F8: Add: Ending, Available Balance Aug 12, 2025 | G8: =CF!H23+CF!H24 -> 2257842.5 | M8: COLLECTED LAST CYCLE | N8: =-43800 -> -43800
C9: TOTAL AMOUNT CLIENT PAID | D9: 6615525 | F9: TOTAL EXCESS CASH AFTER PAYMENTS TO DEPOT | G9: =SUM(G7:G8) -> 1620263.7
C10: LESS: TUBIL-OFFICE | D10: 0 | F10: LESS: OTHER PAYMENTS / OUTFLOW ( AUG 05 - AUG 11, 2025) | G10: =SUM(G11:G14) -> -635973.95
C11: LESS : PREVIOUS ORDERS | D11: 102600 | F11: RFP of Accounts Payable [ i.e other suppliers, 3rd parties] (-) | G11: =-'JAN 01-05 2026'!$O$21 -> -48757.35 | P11: =N12-P7 -> 720201.38
C12: TOTAL NET AMOUNT CLIENT PAID CURRENT | D12: =D9-D10-D11 -> 6512925 | F12: Cash Withdrawn for PCF Replenishment (-) | G12: =-'JAN 01-05 2026'!$O$22 -> -7216.6 | M12: CASHIER | N12: 7685480
F13: Checks Cleared for Loan / Fund Repayments (-) | G13: =-'JAN 01-05 2026'!$O$26 -> -580000
F14: Other Cash payments / transfer relating to operating activities to EW (-) | G14: =-'JAN 01-05 2026'!$O$25 -> 0
F15: ENDING BALANCE, CASH AVAILABLE AUG 11, 2025 | G15: =G9+G10 -> 984289.76 | I15: =CF!H25 -> 1316150.6 | J15: 0
F16: LESS: ADVANCE PAYMENTS FOR NEXT CYCLE* | G16: =-349405 -> -349405 | I16: *Cashier
F17: ="ACTUAL CASH "&IF(G17<0,"DEFICIT",IF(G17>0,"EXCESS","BREAKEVEN"))&" FOR THE CYCLE" -> ACTUAL CASH EXCESS FOR THE CYCLE | G17: =G15+G16 -> 634884.76
F19: TOTAL AMOUNT CLIENT PAID | G19: =G4 -> 7004321.2
F20: LESS: PAYMENTS FROM NON-DHPP / PREVIOUS CYCLES / ADVANCES / ETC | G20: =SUM(G21:G24) -> -597827.55
F21: PAYMENTS COLLECTED FOR NEXT CYCLE (ADVANCES) [ Data from Cashier] | G21: =G16 -> -349405 | H21: OK
B22: 7c1334 | C22: 700000 | F22: PAYMENTS COLLECTED FROM PREVIOUS CYCLES [Data from Cashier] | G22: =-232750 -> -232750
C23: 300000 | F23: PAYMENTS COLLECTED FROM (DMIE / OPS) [ Data from Cashier ] | G23: =-15380 -> -15380
C24: =C23/C22 -> 0.42857143 | F24: OTHER COLLECTIONS [ Bank data ] | G24: =-292.55 -> -292.55 | I24: 8574420
C25: 0.25 | F25: EQUALS: NET AMOUNT PAID FOR FUEL CURRENT CYCLE (ACCOUNTING) | G25: =G19+G20 -> 6406493.6 | I25: 8670950 | J25: cashier
F26: LESS: TOTAL AMOUNT CLIENT PAID CURRENT CYCLE (HAULING) | G26: =D12 -> 6512925 | I26: 96530 | J26: COH
F27: ADD: ADVANCE PAYMENTS LAST CYCLE ( AUG 5-11, 2025 ) | G27: 968125 | I27: 5000 | J27: EW
F28: VARIANCE: REMAINING COLLECTIBLES FOR THE CURRENT CYCLE | G28: =G25-G26+G27 -> 861693.62 | I28: 15000 | J28: CALICAN | K28: 78900
I29: 51500 | J29: ILAYA | K29: 17630
I30: 7400 | J30: GCASH

Sheet CASH SHORT
C1: DISTRIBUTION AND HAULING DEPARTMENT | F1: FINANCE AND ACCOUNTING DEPARTMENT
C2: PERIOD: NOV 11-NOV 17, 2025 | D2: AMOUNT | F2: PERIOD: NOV 11 - NOV 17, 2025 | G2: AMOUNT
C3: PARTICULARS | F3: PARTICULARS | L3: CASHIER:
C4: TOTAL NET AMOUNT CLIENT PAID CURRENT | D4: =D12 -> 9398277 | F4: TOTAL AMOUNT DEPOSITED ( From Nov 11- Nov 17, 2025) | G4: ='JAN 01-05 2026'!O17+'JAN 01-05 2026'!O18-'JAN 01-05 2026'!O24 -> 7004321.2 | I4: =D12-G4 -> 2393955.8 | M4: RECONCILIATION
C5: TOTAL PAYABLE TO DEPOT | D5: 9068800 | F5: BORROWINGS FROM OTHER ACCOUNT (EW) | G5: ='JAN 01-05 2026'!$O$19 -> 0 | M5: PASSBOOKS | N5: =G4 -> 7004321.2
C6: GROSS MARK - UP | D6: =D4-D5 -> 329477 | F6: TOTAL PAYABLES TO DEPOT ( Cycle Nov 11 - Nov 17, 2025) | G6: ='JAN 01-05 2026'!O20 -> 7641900 | I6: =D5-G6 -> 1426900 | M6: GCASH | N6: 17450
F7: TOTAL CASH EXCESS FROM COLLECTIONS | G7: =G4+G5-G6 -> -637578.83 | M7: OTHER BANK CREDITS | N7: =-105.19 -> -105.19 | P7: =N5+N6+N7+N8+N9+N10+N11 -> 7021666
F8: Add: Ending, Available Balance Nov 10, 2025 | G8: =CF!H23+CF!H24 -> 2257842.5 | M8: COLLECTED LAST CYCLE | N8: 0
C9: TOTAL AMOUNT CLIENT PAID | D9: 9424327 | F9: NET CASH EXCESS AFTER PAYMENTS TO DEPOT | G9: =SUM(G7:G8) -> 1620263.7 | M9: EW | N9: 0
C10: LESS: TUBIL-OFFICE | D10: 26050 | F10: LESS: OTHER PAYMENTS / OUTFLOW ( NOV 11 - NOV 17, 2025) | G10: =SUM(G11:G14) -> -635973.95
C11: LESS : PREVIOUS ORDERS | D11: 0 | F11: RFP of Accounts Payable [ i.e other suppliers, 3rd parties] (-) | G11: =-'JAN 01-05 2026'!$O$21 -> -48757.35 | M11: PCF | P11: =N12-P7 -> 52079.02
C12: TOTAL NET AMOUNT CLIENT PAID CURRENT | D12: =D9-D10-D11 -> 9398277 | F12: Cash Withdrawn for PCF Replenishment (-) | G12: =-'JAN 01-05 2026'!$O$22 -> -7216.6 | M12: CASHIER | N12: 7073745
F13: Checks Cleared for Loan / Fund Repayments (-) | G13: =-'JAN 01-05 2026'!$O$26 -> -580000
F14: Other Cash payments / transfer relating to operating activities to EW (-) | G14: =-'JAN 01-05 2026'!$O$25 -> 0
C15: NET MARK-UP | D15: =D6 -> 329477 | F15: TOTAL CASH AVAILABLE, AS OF NOV 17, 2025 | G15: =G9+G10 -> 984289.76 | I15: =CF!H25 -> 1316150.6 | J15: 0
C16: CASH OUTFLOW | D16: =G11+G12+G14 -> -55973.95 | F16: LESS: ADVANCE PAYMENTS COLLECTED FOR THE CYCLE | G16: =-53100 -> -53100 | I16: *Cashier
C17: EXCESS FUNDS / NET PROFIT | D17: =D15+D16 -> 273503.05 | F17: ="ACTUAL CASH "&IF(G17<0,"DEFICIT",IF(G17>0,"EXCESS","BREAKEVEN"))&" AS OF THE END THE CYCLE"&J17 -> ACTUAL CASH EXCESS AS OF THE END THE CYCLE NOV. 17, 2025 | G17: =G15+G16 -> 931189.76 | J17: NOV. 17, 2025
G18: 0
F19: CASH SHORT ACTUAL | G19: =G18-G17 -> -931189.76
F24: 150000
F25: 4
D26: 150 | F26: =F24*F25 -> 600000
D27: 150 | F27: 300000
F28: =F27/F26 -> 0.5

Sheet JAN 01-05 2026
D1: OK | E1: OK | F1: OK | G1: OK | H1: OK | I1: OK | J1: OK | K1: OK | L1: OK | M1: OK | N1: OK
C2: CASH FOR THE CYCLE | D2: PNB | E2: PSBC-S | F2: PSBC-C | G2: KB | H2: 1VB | I2: BDO | J2: MBTC | K2: RCBC | L2: CHINA BANK | M2: E.TAN/STPC | N2: PCF & COH | O2: GRAND TOTAL
C3: Beginning Balances, Jan. 01 , 2026 | D3: 733035.46 | E3: 14281.36 | F3: 314297.74 | G3: 9030.43 | H3: 891913.88 | I3: 201183.08 | J3: 213003.48 | K3: 11097.11 | L3: 5000 | N3: 20000 | O3: =SUM(D3:N3) -> 2412842.5
C4: Less: ADB /Maintaining Balance / PCF | D4: 50000 | E4: 5000 | F4: 5000 | G4: 5000 | H4: 5000 | I4: 5000 | J4: 50000 | K4: 5000 | L4: 5000 | M4: 0 | N4: 20000 | O4: =SUM(D4:N4) -> 155000
C5: Available Cash in Bank | D5: =D3-D4 -> 683035.46 | E5: =E3-E4 -> 9281.36 | F5: =F3-F4 -> 309297.74 | G5: =G3-G4 -> 4030.43 | H5: =H3-H4 -> 886913.88 | I5: =I3-I4 -> 196183.08 | J5: =J3-J4 -> 163003.48 | K5: =K3-K4 -> 6097.11 | ... N5: =N3-N4 -> 0 | O5: =SUM(D5:N5) -> 2257842.5
C6: Add: Deposits | D6: 1716926.2 | E6: 4700 | F6: 715145 | G6: 50000 | H6: 2057625 | I6: 461850 | J6: 1296000 | M6: 530000 | N6: 172075 | O6: =SUM(D6:N6) -> 7004321.2 | P6: =O17+O18+O19 -> 7004321.2 | Q6: =O6-P6 -> 0
C7: Less: Checks Issued/ Withdrawals | D7: 2281174.6 | F7: 901700 | H7: 2940700 | I7: 254300 | J7: 1369999.3 | M7: 530000 | O7: =SUM(D7:N7) -> 8277874 | P7: =O20+O21+O22+O24+O25+O26+O23 -> 8277874 | Q7: =O7-P7 -> 0
C8: Available Cash, End. Jan. 05, 2026 | D8: =D5+D6-D7 -> 118787.02 | E8: =E5+E6-E7 -> 13981.36 | F8: =F5+F6-F7 -> 122742.74 | G8: =G5+G6-G7 -> 54030.43 | H8: =H5+H6-H7 -> 3838.88 | I8: =I5+I6-I7 -> 403733.08 | J8: =J5+J6-J7 -> 89004.14 | K8: =K5+K6-K7 -> 6097.11 | ... N8: =N5+N6-N7 -> 172075 | O8: =SUM(D8:N8) -> 984289.76 | Q8: =O3-O4+O6-O7 -> 984289.76 | R8: =O8-Q8 -> -1.9790605e-09
C9: Add: ADB/Maintaining Balance/ PCF | D9: =D4 -> 50000 | E9: =E4 -> 5000 | F9: =F4 -> 5000 | G9: =G4 -> 5000 | H9: =H4 -> 5000 | I9: =I4 -> 5000 | J9: =J4 -> 50000 | K9: =K4 -> 5000 | ... N9: =N4 -> 20000 | O9: =SUM(D9:N9) -> 155000
C10: TOTAL CASH | D10: =D8+D9 -> 168787.02 | E10: =E8+E9 -> 18981.36 | F10: =F8+F9 -> 127742.74 | G10: =G8+G9 -> 59030.43 | H10: =H8+H9 -> 8838.88 | I10: =I8+I9 -> 408733.08 | J10: =J8+J9 -> 139004.14 | K10: =K8+K9 -> 11097.11 | ... N10: =N8+N9 -> 192075 | O10: =SUM(D10:N10) -> 1139289.8 | P10: =O8+O9 -> 1139289.8 | Q10: =O10-P10 -> 0
D11: =D8/$O$8 -> 0.12068298 | E11: =E8/$O$8 -> 0.014204516 | F11: =F8/$O$8 -> 0.12470184 | G11: =G8/$O$8 -> 0.054892809 | H11: =H8/$O$8 -> 0.0039001523 | I11: =I8/$O$8 -> 0.41017706 | J11: =J8/$O$8 -> 0.090424734 | K11: =K8/$O$8 -> 0.0061944259 | L11: =L8/$O$8 -> 0
G12: =G5+G4 -> 9030.43 | H12: =H5+H4 -> 891913.88 | I12: =I5+I4 -> 201183.08 | J12: =J5+J4 -> 213003.48
C13: T-ENDING | D13: 168787.02 | E13: 18981.36 | F13: 127742.74 | G13: 59030.43 | H13: 8838.88 | I13: 408733.08 | J13: 139004.14 | K13: 11097.11 | L13: 5000 | N13: 192075 | O13: =SUM(D13:N13) -> 1139289.8
C14: variance | D14: =D10-D13 -> 0 | E14: =E10-E13 -> 0 | F14: =F10-F13 -> 0 | G14: =G10-G13 -> 0 | H14: =H10-H13 -> -1.1095835e-10 | I14: =I10-I13 -> 0 | J14: =J10-J13 -> 0 | K14: =K10-K13 -> 0 | ... O14: =O10-O13 -> 0
C17: Collections from Distribution and Hauling of Petroleum (+) | D17: =1716926.17-76.17 -> 1716850 | F17: 715145 | G17: 50000 | H17: 2057625 | I17: 461850 | J17: 1296000 | M17: 530000 | N17: 172075 | O17: =SUM(D17:N17) -> 6999545 | P17: =O17-O24-O23 -> 6999545 | Q17: =O17+O18+O19-O20-O21-O22-O23-O24-O25-O26 -> -1273552.8
C18: Other Cash Collections relating to operating activities (+) | D18: 76.17 | E18: 4700 | O18: =SUM(D18:N18) -> 4776.17 | Q18: =O17+O18-O23-O24 -> 7004321.2
C19: Funds Borrowed from other account (+) | O19: =SUM(D19:N19) -> 0
C20: Payments to Supplier of Petroleum Products (-) | D20: 2246300 | F20: 901700 | H20: =584400+1078200+785000 -> 2447600 | I20: 254300 | J20: 1262000 | M20: 530000 | O20: =SUM(D20:N20) -> 7641900
C21: RFP of Accounts Payables [ i.e other suppliers, 3rd parties] (-) | D21: =15.23+5938+2500+4013.16+6981.62+8210 -> 27658.01 | H21: 13100 | J21: 7999.34 | O21: =SUM(D21:N21) -> 48757.35
C22: Cash Withdrawn for PCF Replenishment (-) | D22: 7216.6 | O22: =SUM(D22:N22) -> 7216.6
C23: Inter-account fund transfer / EW (-) | O23: =SUM(D23:N23) -> 0
C24: Inter-account fund transfer / SA to CA (-) | O24: =SUM(D24:N24) -> 0
C25: Other Cash payments / transfer relating to operating activities (-) | O25: =SUM(D25:N25) -> 0
C26: Checks Cleared for Loan / Funds Repayments(-) | H26: 480000 | J26: 100000 | O26: =SUM(D26:N26) -> 580000 | P26: =O17+O18-O20-O21-O22-O25-O26 -> -1273552.8
C27: TOTAL | D27: =D17+D18+D19-D20-D21-D22-D23-D24-D25-D26 -> -564248.44 | E27: =E17+E18+E19-E20-E21-E22-E23-E24-E25-E26 -> 4700 | F27: =F17+F18+F19-F20-F21-F22-F23-F24-F25-F26 -> -186555 | G27: =G17+G18+G19-G20-G21-G22-G23-G24-G25-G26 -> 50000 | H27: =H17+H18+H19-H20-H21-H22-H23-H24-H25-H26 -> -883075 | I27: =I17+I18+I19-I20-I21-I22-I23-I24-I25-I26 -> 207550 | J27: =J17+J18+J19-J20-J21-J22-J23-J24-J25-J26 -> -73999.34 | K27: =K17+K18+K19-K20-K21-K22-K23-K24-K25-K26 -> 0 | ... N27: =N17+N18+N19-N20-N21-N22-N23-N24-N25-N26 -> 172075 | O27: =O17+O18-O20-O21-O22-O24-O25-O26+O19 -> -1273552.8
C28: BEGINNING | D28: =D3 -> 733035.46 | E28: =E3 -> 14281.36 | F28: =F3 -> 314297.74 | G28: =G3 -> 9030.43 | H28: =H3 -> 891913.88 | I28: =I3 -> 201183.08 | J28: =J3 -> 213003.48 | K28: =K3 -> 11097.11 | ... O28: =O3 -> 2412842.5
C29: ENDING | D29: =D10 -> 168787.02 | E29: =E10 -> 18981.36 | F29: =F10 -> 127742.74 | G29: =G10 -> 59030.43 | H29: =H10 -> 8838.88 | I29: =I10 -> 408733.08 | J29: =J10 -> 139004.14 | K29: =K10 -> 11097.11 | ... O29: =O10 -> 1139289.8
C30: VARIANCE | D30: =D27+D28-D29 -> 0 | E30: =E27+E28-E29 -> 0 | F30: =F27+F28-F29 -> 0 | G30: =G27+G28-G29 -> 0 | H30: =H27+H28-H29 -> 1.1641532e-10 | I30: =I27+I28-I29 -> 0 | J30: =J27+J28-J29 -> 0 | K30: =K27+K28-K29 -> 0 | ... O30: =O27+O28-O29 -> 0
D32: =D6-SUM(D17:D19) -> 0 | E32: =E6-SUM(E17:E19) -> 0 | F32: =F6-SUM(F17:F19) -> 0 | G32: =G6-SUM(G17:G19) -> 0 | H32: =H6-SUM(H17:H19) -> 0 | I32: =I6-SUM(I17:I19) -> 0 | J32: =J6-SUM(J17:J19) -> 0 | K32: =K6-SUM(K17:K19) -> 0 | ... O32: =O6-SUM(O17:O19) -> 0
D33: =D7-SUM(D20:D26) -> 0 | E33: =E7-SUM(E20:E26) -> 0 | F33: =F7-SUM(F20:F26) -> 0 | G33: =G7-SUM(G20:G26) -> 0 | H33: =H7-SUM(H20:H26) -> 0 | I33: =I7-SUM(I20:I26) -> 0 | J33: =J7-SUM(J20:J26) -> 0 | K33: =K7-SUM(K20:K26) -> 0 | ... O33: =O7-SUM(O20:O26) -> 0

Sheet JAN 06-12 2026
D1: OK | E1: OK | F1: OK | G1: OK | H1: OK | I1: OK | J1: OK | K1: OK | L1: OK | M1: OK | N1: OK
C2: CASH FOR THE CYCLE | D2: PNB | E2: PSBC-S | F2: PSBC-C | G2: KB | H2: 1VB | I2: BDO | J2: MBTC | K2: RCBC | L2: CHINA BANK | M2: E.TAN/STPC | N2: PCF & COH | O2: GRAND TOTAL
C3: Beg. Balances, Jan 06, 2026 | D3: 168787.02 | E3: 18981.36 | F3: 127742.74 | G3: 59030.43 | H3: 8838.88 | I3: 408733.08 | J3: 139004.14 | K3: 11097.11 | L3: 5000 | M3: 0 | N3: 192075 | O3: =SUM(D3:N3) -> 1139289.8
C4: Less: ADB /Maintaining Balance / PCF | D4: 50000 | E4: 5000 | F4: 5000 | G4: 5000 | H4: 5000 | I4: 5000 | J4: 50000 | K4: 5000 | L4: 5000 | M4: 0 | N4: 20000 | O4: =SUM(D4:N4) -> 155000
C5: Available Cash in Bank | D5: =D3-D4 -> 118787.02 | E5: =E3-E4 -> 13981.36 | F5: =F3-F4 -> 122742.74 | G5: =G3-G4 -> 54030.43 | H5: =H3-H4 -> 3838.88 | I5: =I3-I4 -> 403733.08 | J5: =J3-J4 -> 89004.14 | K5: =K3-K4 -> 6097.11 | ... N5: =N3-N4 -> 172075 | O5: =SUM(D5:N5) -> 984289.76
C6: Add: Deposits | D6: 3487525 | E6: 6850 | F6: 432650 | G6: 476400 | H6: 3209050 | I6: 156006.27 | J6: 2204550 | K6: 14470 | L6: 0 | M6: 150000 | N6: =108350+471600 -> 579950 | O6: =SUM(D6:N6) -> 10717451 | P6: =O17+O18+O19 -> 10717451 | Q6: =O6-P6 -> 0 | W6: 49000
C7: Less: Checks Issued/ Withdrawals | D7: 3410382.6 | E7: 17435 | F7: 552575.75 | G7: 526400 | H7: 3209350 | I7: 558001.25 | J7: 2171164 | K7: 0 | L7: 0 | M7: 150000 | N7: =172075+471600 -> 643675 | O7: =SUM(D7:N7) -> 11238984 | P7: =O20+O21+O22+O24+O25+O26+O23 -> 11238984 | Q7: =O7-P7 -> 0 | W7: 51900
C8: Available Cash, End. Jan. 12, 2026 | D8: =D5+D6-D7 -> 195929.41 | E8: =E5+E6-E7 -> 3396.36 | F8: =F5+F6-F7 -> 2816.99 | G8: =G5+G6-G7 -> 4030.43 | H8: =H5+H6-H7 -> 3538.88 | I8: =I5+I6-I7 -> 1738.1 | J8: =J5+J6-J7 -> 122390.19 | K8: =K5+K6-K7 -> 20567.11 | ... N8: =N5+N6-N7 -> 108350 | O8: =SUM(D8:N8) -> 462757.47 | Q8: =O3-O4+O6-O7 -> 462757.47 | R8: =O8-Q8 -> -6.9849193e-10 | W8: 1300
C9: Add: ADB/Maintaining Balance/ PCF | D9: =D4 -> 50000 | E9: =E4 -> 5000 | F9: =F4 -> 5000 | G9: =G4 -> 5000 | H9: =H4 -> 5000 | I9: =I4 -> 5000 | J9: =J4 -> 50000 | K9: =K4 -> 5000 | ... N9: =N4 -> 20000 | O9: =SUM(D9:N9) -> 155000
C10: TOTAL CASH | D10: =D8+D9 -> 245929.41 | E10: =E8+E9 -> 8396.36 | F10: =F8+F9 -> 7816.99 | G10: =G8+G9 -> 9030.43 | H10: =H8+H9 -> 8538.88 | I10: =I8+I9 -> 6738.1 | J10: =J8+J9 -> 172390.19 | K10: =K8+K9 -> 25567.11 | ... N10: =N8+N9 -> 128350 | O10: =SUM(D10:N10) -> 617757.47 | P10: =O8+O9 -> 617757.47 | Q10: =O10-P10 -> 0
D11: =D8/$O$8 -> 0.42339546 | E11: =E8/$O$8 -> 0.0073393953 | F11: =F8/$O$8 -> 0.0060874004 | G11: =G8/$O$8 -> 0.0087095947 | H11: =H8/$O$8 -> 0.0076473752 | I11: =I8/$O$8 -> 0.0037559631 | J11: =J8/$O$8 -> 0.2644802 | K11: =K8/$O$8 -> 0.044444685 | L11: =L8/$O$8 -> 0
G12: =G5+G4 -> 59030.43 | H12: =H5+H4 -> 8838.88 | I12: =I5+I4 -> 408733.08 | J12: =J5+J4 -> 139004.14
C13: T-ENDING | D13: 245929.41 | E13: 8396.36 | F13: 7816.99 | G13: 9030.43 | H13: 8538.88 | I13: 6738.1 | J13: 172390.19 | K13: 25567.11 | L13: 5000 | M13: 0 | N13: =108350+20000 -> 128350 | O13: =SUM(D13:N13) -> 617757.47
C14: variance | D14: =D10-D13 -> 0 | E14: =E10-E13 -> 0 | F14: =F10-F13 -> -9.094947e-12 | G14: =G10-G13 -> 5.0931703e-11 | H14: =H10-H13 -> -1.1095835e-10 | I14: =I10-I13 -> -2.3646862e-11 | J14: =J10-J13 -> 0 | K14: =K10-K13 -> 0 | ... O14: =O10-O13 -> 0
C17: Collections from Distribution and Hauling of Petroleum (+) | D17: 3437525 | F17: 422650 | G17: 476400 | H17: 3209050 | I17: 156000 | J17: 1840030 | M17: 150000 | N17: 108350 | O17: =SUM(D17:N17) -> 9800005 | P17: =O17-O24-O23 -> 9041530 | Q17: =O17+O18+O19-O20-O21-O22-O23-O24-O25-O26 -> -521532.29
C18: Other Cash Collections relating to operating activities (+) | D18: 50000 | E18: 6850 | F18: 10000 | I18: 6.27 | J18: 364520 | K18: 14470 | O18: =SUM(D18:N18) -> 445846.27 | Q18: =O17+O18-O23-O24 -> 9487376.3
C19: Funds Borrowed from other account (+) | N19: 471600 | O19: =SUM(D19:N19) -> 471600
C20: Payments to Supplier of Petroleum Products (-) | D20: 2926700 | F20: 412300 | H20: =135900+83600+500000+680000+381050+356000+530000+336800+106000 -> 3109350 | I20: =155000+103000 -> 258000 | J20: 1676750 | M20: 150000 | N20: 471600 | O20: =SUM(D20:N20) -> 9004700 | S20: =M17+K18+J18+J17+I17+H17+G17+F17+F18+E18+D18+D17+I18 -> 10137501 | V20: =P17+O18 -> 9487376.3
C21: RFP of Accounts Payable [ i.e other suppliers, 3rd parties] (-) | D21: =93740.13+57242.28+2100+25576.74+45000+5923.46+100 -> 229682.61 | F21: 11772 | H21: 100000 | I21: 1.25 | J21: =12725+80000+63227.78+63225.87+42695.07+115712 -> 377585.72 | O21: =SUM(D21:N21) -> 719041.58 | S21: =-(D24+E24+G24) -> -586400 | T21: INTERBRANCH | V21: =S22 -> -6.27
C22: Cash Withdrawn for PCF Replenishment (-) | E22: 7435 | F22: 8503.75 | J22: =8987.6+7840.63 -> 16828.23 | O22: =SUM(D22:N22) -> 32766.98 | S22: =-6.27 -> -6.27 | T22: CREDIT MEMO
C23: Inter-account fund transfer / EW (-) | O23: =SUM(D23:N23) -> 0
C24: Inter-account fund transfer / SA to CA (-) | D24: =50000 -> 50000 | E24: 10000 | G24: =51450+15000+320200+53750+36000+50000 -> 526400 | N24: 172075 | O24: =SUM(D24:N24) -> 758475 | S24: 16600 | T24: GCASH | V24: =S24 -> 16600
C25: Other Cash payments / transfer relating to operating activities (-) | D25: =29000+175000 -> 204000 | O25: =SUM(D25:N25) -> 204000
C26: Checks Cleared for Loan / Funds Repayments(-) | F26: 120000 | I26: 300000 | J26: =100000 -> 100000 | O26: =SUM(D26:N26) -> 520000 | P26: =O17+O18-O20-O21-O22-O25-O26 -> -234657.29 | S26: =108350 -> 108350 | T26: CASH COLLECTIONS | V26: =SUM(V20:V24) -> 9503970
C27: TOTAL | D27: =D17+D18+D19-D20-D21-D22-D23-D24-D25-D26 -> 77142.39 | E27: =E17+E18+E19-E20-E21-E22-E23-E24-E25-E26 -> -10585 | F27: =F17+F18+F19-F20-F21-F22-F23-F24-F25-F26 -> -119925.75 | G27: =G17+G18+G19-G20-G21-G22-G23-G24-G25-G26 -> -50000 | H27: =H17+H18+H19-H20-H21-H22-H23-H24-H25-H26 -> -300 | I27: =I17+I18+I19-I20-I21-I22-I23-I24-I25-I26 -> -401994.98 | J27: =J17+J18+J19-J20-J21-J22-J23-J24-J25-J26 -> 33386.05 | K27: =K17+K18+K19-K20-K21-K22-K23-K24-K25-K26 -> 14470 | ... O27: =O17+O18+O19-O20-O21-O22-O23-O24-O25-O26 -> -521532.29 | S27: =-172075 -> -172075 | T27: CASH DEPOSIT
C28: BEGINNING | D28: =D3 -> 168787.02 | E28: =E3 -> 18981.36 | F28: =F3 -> 127742.74 | G28: =G3 -> 59030.43 | H28: =H3 -> 8838.88 | I28: =I3 -> 408733.08 | J28: =J3 -> 139004.14 | K28: =K3 -> 11097.11 | ... O28: =O3 -> 1139289.8 | T28: PCF
C29: ENDING | D29: =D10 -> 245929.41 | E29: =E10 -> 8396.36 | F29: =F10 -> 7816.99 | G29: =G10 -> 9030.43 | H29: =H10 -> 8538.88 | I29: =I10 -> 6738.1 | J29: =J10 -> 172390.19 | K29: =K10 -> 25567.11 | ... O29: =O10 -> 617757.47
C30: VARIANCE | D30: =D27+D28-D29 -> 0 | E30: =E27+E28-E29 -> 0 | F30: =F27+F28-F29 -> 1.4551915e-11 | G30: =G27+G28-G29 -> -5.0931703e-11 | H30: =H27+H28-H29 -> 1.1095835e-10 | I30: =I27+I28-I29 -> 5.8207661e-11 | J30: =J27+J28-J29 -> 0 | K30: =K27+K28-K29 -> 0 | ... O30: =O27+O28-O29 -> 0 | S30: =SUM(S20:S28) -> 9503970
U31: =S30-S32 -> 0
D32: =D6-SUM(D17:D19) -> 0 | E32: =E6-SUM(E17:E19) -> 0 | F32: =F6-SUM(F17:F19) -> 0 | G32: =G6-SUM(G17:G19) -> 0 | H32: =H6-SUM(H17:H19) -> 0 | I32: =I6-SUM(I17:I19) -> 0 | J32: =J6-SUM(J17:J19) -> 0 | K32: =K6-SUM(K17:K19) -> 0 | ... O32: =O6-SUM(O17:O19) -> 0 | S32: 9503970
D33: =D7-SUM(D20:D26) -> 0 | E33: =E7-SUM(E20:E26) -> 0 | F33: =F7-SUM(F20:F26) -> 0 | G33: =G7-SUM(G20:G26) -> 0 | H33: =H7-SUM(H20:H26) -> 0 | I33: =I7-SUM(I20:I26) -> 0 | J33: =J7-SUM(J20:J26) -> 0 | K33: =K7-SUM(K20:K26) -> 0 | ... O33: =O7-SUM(O20:O26) -> 0
S34: =V24+V21 -> 16593.73
S36: =S32-S34 -> 9487376.3

Sheet JAN 13-19 2026
D1: OK | E1: OK | F1: OK | G1: OK | H1: OK | I1: OK | J1: OK | K1: OK | L1: OK | M1: OK | N1: OK
C2: CASH FOR THE CYCLE | D2: PNB | E2: PSBC-S | F2: PSBC-C | G2: KB | H2: 1VB | I2: BDO | J2: MBTC | K2: RCBC | L2: CHINA BANK | M2: E.TAN/STPC | N2: PCF & COH | O2: GRAND TOTAL
C3: Beg. Balances, Jan 13, 2026 | D3: 245929.41 | E3: 8396.36 | F3: 7816.99 | G3: 9030.43 | H3: 8538.88 | I3: 6738.1 | J3: 172390.19 | K3: 25567.11 | L3: 5000 | M3: 0 | N3: 128350 | O3: =D3+E3+F3+G3+H3+I3+J3+K3+L3+M3+N3 -> 617757.47
C4: Less: ADB /Maintaining Balance / PCF | D4: 50000 | E4: 5000 | F4: 5000 | G4: 5000 | H4: 5000 | I4: 5000 | J4: 50000 | K4: 5000 | L4: 5000 | M4: 0 | N4: 20000 | O4: =SUM(D4:N4) -> 155000
C5: Available Cash in Bank | D5: =D3-D4 -> 195929.41 | E5: =E3-E4 -> 3396.36 | F5: =F3-F4 -> 2816.99 | G5: =G3-G4 -> 4030.43 | H5: =H3-H4 -> 3538.88 | I5: =I3-I4 -> 1738.1 | J5: =J3-J4 -> 122390.19 | K5: =K3-K4 -> 20567.11 | ... N5: =N3-N4 -> 108350 | O5: =SUM(D5:N5) -> 462757.47
C6: Add: Deposits | D6: 2417095 | E6: 4000 | F6: 500169 | H6: 3387615 | I6: 359750 | J6: 1706631 | K6: 1000 | M6: 440000 | N6: 697550 | O6: =SUM(D6:N6) -> 9513810 | P6: =O17+O18+O19 -> 9513810 | Q6: =O6-P6 -> 0 | W6: 49000
C7: Less: Checks Issued/ Withdrawals | D7: 2583718.6 | F7: 500191 | H7: 3051625 | I7: 359750 | J7: 1799376.2 | K7: 0 | M7: 440000 | N7: 754050 | O7: =SUM(D7:N7) -> 9488710.9 | P7: =O20+O21+O22+O24+O25+O26+O23 -> 9488710.9 | Q7: =O7-P7 -> 0 | W7: 51900
C8: Available Cash, End. Jan. 19, 2026 | D8: =D5+D6-D7 -> 29305.76 | E8: =E5+E6-E7 -> 7396.36 | F8: =F5+F6-F7 -> 2794.99 | G8: =G5+G6-G7 -> 4030.43 | H8: =H5+H6-H7 -> 339528.88 | I8: =I5+I6-I7 -> 1738.1 | J8: =J5+J6-J7 -> 29644.97 | K8: =K5+K6-K7 -> 21567.11 | ... N8: =N5+N6-N7 -> 51850 | O8: =SUM(D8:N8) -> 487856.6 | Q8: =O3-O4+O6-O7 -> 487856.6 | R8: =O8-Q8 -> 0 | W8: 1300
C9: Add: ADB/Maintaining Balance/ PCF | D9: =D4 -> 50000 | E9: =E4 -> 5000 | F9: =F4 -> 5000 | G9: =G4 -> 5000 | H9: =H4 -> 5000 | I9: =I4 -> 5000 | J9: =J4 -> 50000 | K9: =K4 -> 5000 | ... N9: =N4 -> 20000 | O9: =SUM(D9:N9) -> 155000
C10: TOTAL CASH | D10: =D8+D9 -> 79305.76 | E10: =E8+E9 -> 12396.36 | F10: =F8+F9 -> 7794.99 | G10: =G8+G9 -> 9030.43 | H10: =H8+H9 -> 344528.88 | I10: =I8+I9 -> 6738.1 | J10: =J8+J9 -> 79644.97 | K10: =K8+K9 -> 26567.11 | ... N10: =N8+N9 -> 71850 | O10: =SUM(D10:N10) -> 642856.6 | P10: =O8+O9 -> 642856.6 | Q10: =O10-P10 -> 0
D11: =D8/$O$8 -> 0.060070439 | E11: =E8/$O$8 -> 0.01516093 | F11: =F8/$O$8 -> 0.005729122 | G11: =G8/$O$8 -> 0.0082615055 | H11: =H8/$O$8 -> 0.69596041 | I11: =I8/$O$8 -> 0.0035627272 | J11: =J8/$O$8 -> 0.060765746 | K11: =K8/$O$8 -> 0.044207888 | L11: =L8/$O$8 -> 0
G12: =G5+G4 -> 9030.43 | H12: =H5+H4 -> 8538.88 | I12: =I5+I4 -> 6738.1 | J12: =J5+J4 -> 172390.19
C13: T-ENDING | D13: 79305.76 | E13: 12396.36 | F13: 7794.99 | G13: 9030.43 | H13: 344528.88 | I13: 6738.1 | J13: 79644.97 | K13: 26567.11 | L13: 5000 | N13: 71850 | O13: =SUM(D13:N13) -> 642856.6
C14: variance | D14: =D10-D13 -> 2.4738256e-10 | E14: =E10-E13 -> 0 | F14: =F10-F13 -> -9.094947e-12 | G14: =G10-G13 -> 0 | H14: =H10-H13 -> 0 | I14: =I10-I13 -> -2.3646862e-11 | J14: =J10-J13 -> 0 | K14: =K10-K13 -> 0 | ... O14: =O10-O13 -> 0
C17: Collections from Distribution and Hauling of Petroleum (+) | D17: =2307095-6870 -> 2300225 | F17: 498650 | H17: 3387615 | I17: 359750 | J17: 1701650 | M17: 440000 | N17: 51850 | O17: =SUM(D17:N17) -> 8739740 | P17: =O17-O24-O23 -> 8431390 | Q17: =O17+O18+O19-O20-O21-O22-O23-O24-O25-O26 -> 25099.13
C18: Other Cash Collections relating to operating activities (+) | D18: =6870+110000 -> 116870 | E18: 4000 | F18: 1519 | J18: 4981 | K18: 1000 | O18: =SUM(D18:N18) -> 128370 | Q18: =O17+O18-O23-O24 -> 8559760
C19: Funds Borrowed from other account (+) | N19: 645700 | O19: =SUM(D19:N19) -> 645700 | V19: RECONCILIATION DATA | W19: REMARKS
C20: Payments to Supplier of Petroleum Products (-) | D20: 1924450 | F20: 468100 | H20: 2573800 | I20: 359750 | J20: 1707400 | M20: 440000 | N20: 645700 | O20: =SUM(D20:N20) -> 8119200 | S20: =M17+K18+J18+J17+I17+H17+G17+F17+F18+E18+D18+D17+I18 -> 8816260 | V20: =P17 -> 8431390 | W20: COLLECTIONS NET OF INTER-ACCOUNT
C21: RFP of Accounts Payable [ i.e other suppliers, 3rd parties] (-) | D21: =43812.38+1116.27+15+8625 -> 53568.65 | F21: 32091 | H21: 6225 | J21: 82907.3 | O21: =SUM(D21:N21) -> 174791.95 | S21: =-O24+N24 -> -200000 | T21: INTERBRANCH | V21: 128370 | W21: =C18 -> Other Cash Collections relating to operating activities (+)
C22: Cash Withdrawn for PCF Replenishment (-) | J22: 9068.92 | O22: =SUM(D22:N22) -> 9068.92 | S22: =0 -> 0 | T22: CREDIT MEMO
C23: Inter-account fund transfer / EW (-) | O23: =SUM(D23:N23) -> 0 | V23: 12647 | W23: EW- MICH
C24: Inter-account fund transfer / SA to CA (-) | D24: 200000 | N24: 108350 | O24: =SUM(D24:N24) -> 308350 | S24: 3366 | T24: GCASH | V24: 3366 | W24: GCASH-MICH
C25: Other Cash payments / transfer relating to operating activities (-) | D25: 110000 | O25: =SUM(D25:N25) -> 110000 | V25: =V20+V21+V23+V24 -> 8575773 | W25: TOTAL AMOUNT
C26: Checks Cleared for Loan / Funds Repayments(-) | D26: 295700 | H26: 471600 | O26: =SUM(D26:N26) -> 767300 | P26: =O17+O18-O20-O21-O22-O25-O26 -> -312250.87 | S26: =N17 -> 51850 | T26: CASH COLLECTIONS | V26: 8575773 | W26: COLLECTIONS MICH
C27: TOTAL | D27: =D17+D18+D19-D20-D21-D22-D23-D24-D25-D26 -> -166623.65 | E27: =E17+E18+E19-E20-E21-E22-E23-E24-E25-E26 -> 4000 | F27: =F17+F18+F19-F20-F21-F22-F23-F24-F25-F26 -> -22 | G27: =G17+G18+G19-G20-G21-G22-G23-G24-G25-G26 -> 0 | H27: =H17+H18+H19-H20-H21-H22-H23-H24-H25-H26 -> 335990 | I27: =I17+I18+I19-I20-I21-I22-I23-I24-I25-I26 -> 0 | J27: =J17+J18+J19-J20-J21-J22-J23-J24-J25-J26 -> -92745.22 | K27: =K17+K18+K19-K20-K21-K22-K23-K24-K25-K26 -> 1000 | ... O27: =O17+O18+O19-O20-O21-O22-O23-O24-O25-O26 -> 25099.13 | S27: =-N24 -> -108350 | T27: CASH DEPOSIT
C28: BEGINNING | D28: =D3 -> 245929.41 | E28: =E3 -> 8396.36 | F28: =F3 -> 7816.99 | G28: =G3 -> 9030.43 | H28: =H3 -> 8538.88 | I28: =I3 -> 6738.1 | J28: =J3 -> 172390.19 | K28: =K3 -> 25567.11 | ... O28: =O3 -> 617757.47 | S28: 20000 | T28: PCF | V28: =V25-V26 -> 0 | W28: VARIANCE
C29: ENDING | D29: =D10 -> 79305.76 | E29: =E10 -> 12396.36 | F29: =F10 -> 7794.99 | G29: =G10 -> 9030.43 | H29: =H10 -> 344528.88 | I29: =I10 -> 6738.1 | J29: =J10 -> 79644.97 | K29: =K10 -> 26567.11 | ... O29: =O10 -> 642856.6
C30: VARIANCE | D30: =D27+D28-D29 -> -2.6193447e-10 | E30: =E27+E28-E29 -> 0 | F30: =F27+F28-F29 -> 9.094947e-12 | G30: =G27+G28-G29 -> 0 | H30: =H27+H28-H29 -> 0 | I30: =I27+I28-I29 -> 2.3646862e-11 | J30: =J27+J28-J29 -> 0 | K30: =K27+K28-K29 -> 0 | ... O30: =O27+O28-O29 -> 0 | S30: =SUM(S20:S28) -> 8583126
U31: =S30-S32 -> -920844
D32: =D6-SUM(D17:D19) -> 0 | E32: =E6-SUM(E17:E19) -> 0 | F32: =F6-SUM(F17:F19) -> 0 | G32: =G6-SUM(G17:G19) -> 0 | H32: =H6-SUM(H17:H19) -> 0 | I32: =I6-SUM(I17:I19) -> 0 | J32: =J6-SUM(J17:J19) -> 0 | K32: =K6-SUM(K17:K19) -> 0 | ... O32: =O6-SUM(O17:O19) -> 0 | S32: 9503970
D33: =D7-SUM(D20:D26) -> 0 | E33: =E7-SUM(E20:E26) -> 0 | F33: =F7-SUM(F20:F26) -> 0 | G33: =G7-SUM(G20:G26) -> 0 | H33: =H7-SUM(H20:H26) -> 0 | I33: =I7-SUM(I20:I26) -> 0 | J33: =J7-SUM(J20:J26) -> 0 | K33: =K7-SUM(K20:K26) -> 0 | ... O33: =O7-SUM(O20:O26) -> 0
S34: =V24+V21 -> 131736
S36: =S32-S34 -> 9372234

Sheet JAN 20-26 2026
D1: OK | E1: OK | F1: OK | G1: OK | H1: OK | I1: OK | J1: OK | K1: OK | L1: OK | M1: OK | N1: OK
C2: CASH FOR THE CYCLE | D2: PNB | E2: PSBC-S | F2: PSBC-C | G2: KB | H2: 1VB | I2: BDO | J2: MBTC | K2: RCBC | L2: CHINA BANK | M2: E.TAN/STPC | N2: PCF & COH | O2: GRAND TOTAL
C3: Beg. Balances, Jan 20, 2026 | D3: 79305.76 | E3: 12396.36 | F3: 7794.99 | G3: 9030.43 | H3: 344528.88 | I3: 6738.1 | J3: 79644.97 | K3: 26567.11 | L3: 5000 | N3: 71850 | O3: =SUM(D3:N3) -> 642856.6
C4: Less: ADB /Maintaining Balance / PCF | D4: 50000 | E4: 5000 | F4: 5000 | G4: 5000 | H4: 5000 | I4: 5000 | J4: 50000 | K4: 5000 | L4: 5000 | M4: 0 | N4: 20000 | O4: =SUM(D4:N4) -> 155000
C5: Available Cash in Bank | D5: =D3-D4 -> 29305.76 | E5: =E3-E4 -> 7396.36 | F5: =F3-F4 -> 2794.99 | G5: =G3-G4 -> 4030.43 | H5: =H3-H4 -> 339528.88 | I5: =I3-I4 -> 1738.1 | J5: =J3-J4 -> 29644.97 | K5: =K3-K4 -> 21567.11 | ... N5: =N3-N4 -> 51850 | O5: =SUM(D5:N5) -> 487856.6
C6: Add: Deposits | D6: 2698215.9 | E6: 9707 | F6: 340456 | G6: 133350 | H6: 3729556 | I6: 274944 | J6: 2660350 | M6: 440000 | N6: 2203900 | O6: =SUM(D6:N6) -> 12490479 | P6: =O17+O18+O19 -> 12490479 | Q6: =O6-P6 -> 0
C7: Less: Checks Issued/ Withdrawals | D7: 2588219 | F7: 340425 | G7: 92350 | H7: 3662550 | I7: 274875 | J7: 2536718.6 | M7: 440000 | N7: 2151800 | O7: =SUM(D7:N7) -> 12086938 | P7: =O20+O21+O23+O25+O26+O27+O24 -> 12083898 | Q7: =O7-P7 -> 3040
C8: Available Cash, End. Jan. 26, 2026 | D8: =D5+D6-D7 -> 139302.69 | E8: =E5+E6-E7 -> 17103.36 | F8: =F5+F6-F7 -> 2825.99 | G8: =G5+G6-G7 -> 45030.43 | H8: =H5+H6-H7 -> 406534.88 | I8: =I5+I6-I7 -> 1807.1 | J8: =J5+J6-J7 -> 153276.37 | K8: =K5+K6-K7 -> 21567.11 | ... N8: =N5+N6-N7 -> 103950 | O8: =SUM(D8:N8) -> 891397.93 | Q8: =O3-O4+O6-O7 -> 891397.93 | R8: =O8-Q8 -> 1.6298145e-09
C9: Add: ADB/Maintaining Balance/ PCF | D9: =D4 -> 50000 | E9: =E4 -> 5000 | F9: =F4 -> 5000 | G9: =G4 -> 5000 | H9: =H4 -> 5000 | I9: =I4 -> 5000 | J9: =J4 -> 50000 | K9: =K4 -> 5000 | ... N9: =N4 -> 20000 | O9: =SUM(D9:N9) -> 155000
C10: TOTAL CASH | D10: =D8+D9 -> 189302.69 | E10: =E8+E9 -> 22103.36 | F10: =F8+F9 -> 7825.99 | G10: =G8+G9 -> 50030.43 | H10: =H8+H9 -> 411534.88 | I10: =I8+I9 -> 6807.1 | J10: =J8+J9 -> 203276.37 | K10: =K8+K9 -> 26567.11 | ... N10: =N8+N9 -> 123950 | O10: =SUM(D10:N10) -> 1046397.9 | P10: =O8+O9 -> 1046397.9 | Q10: =O10-P10 -> 0
D11: =D8/$O$8 -> 0.15627441 | E11: =E8/$O$8 -> 0.019187121 | F11: =F8/$O$8 -> 0.0031702901 | G11: =G8/$O$8 -> 0.050516642 | H11: =H8/$O$8 -> 0.45606442 | I11: =I8/$O$8 -> 0.0020272652 | J11: =J8/$O$8 -> 0.17195056 | K11: =K8/$O$8 -> 0.024194705 | L11: =L8/$O$8 -> 0
G12: =G5+G4 -> 9030.43 | H12: =H5+H4 -> 344528.88 | I12: =I5+I4 -> 6738.1 | J12: =J5+J4 -> 79644.97
C13: T-ENDING | D13: 189302.69 | E13: 22103.36 | F13: 7825.99 | G13: 50030.43 | H13: 411534.88 | I13: 6807.1 | J13: 203276.37 | K13: 26567.11 | L13: 5000 | N13: 123950 | O13: 1046397.9
C14: variance | D14: =D10-D13 -> -5.2386895e-10 | E14: =E10-E13 -> 0 | F14: =F10-F13 -> -9.094947e-12 | G14: =G10-G13 -> 0 | H14: =H10-H13 -> 0 | I14: =I10-I13 -> -2.3646862e-11 | J14: =J10-J13 -> 0 | K14: =K10-K13 -> 0 | ... O14: =O10-O13 -> 0
C17: Collections from Distribution and Hauling of Petroleum (+) | D17: =2698215.88-17865.88 -> 2680350 | F17: =299456+41000-1031 -> 339425 | G17: 133350 | H17: =3709556-2350+20000 -> 3727206 | I17: 274944 | J17: =1921750+51750+51350+85000+500000+20000 -> 2629850 | M17: 440000 | N17: 103900 | O17: =SUM(D17:N17) -> 10329025 | P17: =O17-O25-O24 -> 9528125 | Q17: =O17+O18+O19-O20-O21-O23-O24-O25-O26-O27 -> 406581.33
C18: Other Cash Collections relating to operating activities (+) | D18: 17865.88 | E18: 9707 | F18: 1031 | H18: 2350 | J18: 30500 | O18: =SUM(D18:N18) -> 61453.88 | Q18: =O17+O18-O24-O25 -> 9589578.9
C19: Funds Borrowed from other account (+) | N19: 2100000 | O19: =SUM(D19:N19) -> 2100000
C20: Payments to Supplier of Petroleum Products (-) | D20: 1502700 | F20: 312450 | H20: 2860800 | I20: 274875 | J20: 2089775 | M20: 440000 | N20: 2100000 | O20: =SUM(D20:N20) -> 9580600 | V20: =P17 -> 9528125 | X20: COLLECTIONS NET OF INTER-ACCOUNT
C21: RFP of Accounts Payable [ i.e other suppliers, 3rd parties] (-) | D21: =7000+4500+8425+8625+60927.4+14707.65+95439.17 -> 199624.22 | F21: =15000+12975 -> 27975 | J21: =8959.25+2500+3000+3150+6600+2441.25+12000 -> 38650.5 | O21: =SUM(D21:N21) -> 266249.72 | V21: 61453.88 | X21: OTHER COLLECTIONS
C22: Disbursement for CAPEX / Purchase of PPE (-) | J22: 3040 | O22: =SUM(D22:N22) -> 3040
C23: Cash Withdrawn for PCF Replenishment (-) | J23: 8253 | O23: =SUM(D23:N23) -> 8253 | V23: 50000 | X23: EW MITCH
C24: Inter-account fund transfer / EW (-) | O24: =SUM(D24:N24) -> 0 | V24: =-20000 -> -20000 | X24: FVB
C25: Inter-account fund transfer / SA to CA (-) | D25: =85000+20000 -> 105000 | G25: 92350 | H25: =500000+51750 -> 551750 | N25: 51800 | O25: =SUM(D25:N25) -> 800900
C26: Other Cash payments / transfer relating to operating activities (-) | J26: =10029.65+70628+42930.64+23411.81 -> 147000.1 | O26: =SUM(D26:N26) -> 147000.1 | V26: =SUM(V20:V25) -> 9619578.9 | X26: TOTAL
C27: Checks Cleared for Loan / Funds Repayments(-) | D27: =30894.73+350000+250000+150000 -> 780894.73 | H27: =200000+50000 -> 250000 | J27: 250000 | O27: =SUM(D27:N27) -> 1280894.7 | P27: =O17+O18-O20-O21-O23-O26-O27 -> -892518.67 | V27: 9619528.9 | X27: COLLECTIONS OF MICH
C28: TOTAL | D28: =D17+D18+D19-D20-D21-D23-D24-D25-D26-D27 -> 109996.93 | E28: =E17+E18+E19-E20-E21-E23-E24-E25-E26-E27 -> 9707 | F28: =F17+F18+F19-F20-F21-F23-F24-F25-F26-F27 -> 31 | G28: =G17+G18+G19-G20-G21-G23-G24-G25-G26-G27 -> 41000 | H28: =H17+H18+H19-H20-H21-H23-H24-H25-H26-H27 -> 67006 | I28: =I17+I18+I19-I20-I21-I23-I24-I25-I26-I27 -> 69 | J28: =J17+J18+J19-J20-J21-J22-J23-J24-J25-J26-J27 -> 123631.4 | K28: =K17+K18+K19-K20-K21-K23-K24-K25-K26-K27 -> 0 | L28: =L17+L18+L19-L20-L21-L23-L24-L25-L26-L27 -> 0 | M28: =M17+M18+M19-M20-M21-M23-M24-M25-M26-M27 -> 0 | N28: =N17+N18+N19-N20-N21-N23-N24-N25-N26-N27 -> 52100 | O28: =O17+O18+O19-O20-O21-O22-O23-O24-O25-O26-O27 -> 403541.33
C29: BEGINNING | D29: =D3 -> 79305.76 | E29: =E3 -> 12396.36 | F29: =F3 -> 7794.99 | G29: =G3 -> 9030.43 | H29: =H3 -> 344528.88 | I29: =I3 -> 6738.1 | J29: =J3 -> 79644.97 | K29: =K3 -> 26567.11 | ... O29: =O3 -> 642856.6
C30: ENDING | D30: =D10 -> 189302.69 | E30: =E10 -> 22103.36 | F30: =F10 -> 7825.99 | G30: =G10 -> 50030.43 | H30: =H10 -> 411534.88 | I30: =I10 -> 6807.1 | J30: =J10 -> 203276.37 | K30: =K10 -> 26567.11 | ... O30: =O10 -> 1046397.9 | V30: 50 | X30: VARIANCE
C31: VARIANCE | D31: =D28+D29-D30 -> 4.6566129e-10 | E31: =E28+E29-E30 -> 0 | F31: =F28+F29-F30 -> 9.094947e-12 | G31: =G28+G29-G30 -> 0 | H31: =H28+H29-H30 -> 0 | I31: =I28+I29-I30 -> 2.3646862e-11 | J31: =J28+J29-J30 -> 0 | K31: =K28+K29-K30 -> 0 | ... O31: =O28+O29-O30 -> 1.5133992e-09
D33: =D6-SUM(D17:D19) -> 0 | E33: =E6-SUM(E17:E19) -> 0 | F33: =F6-SUM(F17:F19) -> 0 | G33: =G6-SUM(G17:G19) -> 0 | H33: =H6-SUM(H17:H19) -> 0 | I33: =I6-SUM(I17:I19) -> 0 | J33: =J6-SUM(J17:J19) -> 0 | K33: =K6-SUM(K17:K19) -> 0 | ... O33: =O6-SUM(O17:O19) -> 0
D34: =D7-SUM(D20:D27) -> 0 | E34: =E7-SUM(E20:E27) -> 0 | F34: =F7-SUM(F20:F27) -> 0 | G34: =G7-SUM(G20:G27) -> 0 | H34: =H7-SUM(H20:H27) -> 0 | I34: =I7-SUM(I20:I27) -> 0 | J34: =J7-SUM(J20:J27) -> 0 | K34: =K7-SUM(K20:K27) -> 0 | ... O34: =O7-SUM(O20:O27) -> 0
D37: XX

Sheet JAN 27-31 2026
D1: OK | E1: OK | F1: OK | G1: OK | H1: OK | I1: OK | J1: OK | K1: OK | L1: OK | M1: OK | N1: OK
C2: CASH FOR THE CYCLE | D2: PNB | E2: PSBC-S | F2: PSBC-C | G2: KB | H2: 1VB | I2: BDO | J2: MBTC | K2: RCBC | L2: CHINA BANK | M2: E.TAN/STPC | N2: PCF & COH | O2: GRAND TOTAL
C3: Beg. Balances, Jan 27, 2026 | D3: 189302.69 | E3: 22103.36 | F3: 7825.99 | G3: 50030.43 | H3: 411534.88 | I3: 6807.1 | J3: 203276.37 | K3: 26567.11 | L3: 5000 | N3: 123950 | O3: =SUM(D3:N3) -> 1046397.9
C4: Less: ADB /Maintaining Balance / PCF | D4: 50000 | E4: 5000 | F4: 5000 | G4: 5000 | H4: 5000 | I4: 5000 | J4: 50000 | K4: 5000 | L4: 5000 | M4: 0 | N4: 20000 | O4: =SUM(D4:N4) -> 155000
C5: Available Cash in Bank | D5: =D3-D4 -> 139302.69 | E5: =E3-E4 -> 17103.36 | F5: =F3-F4 -> 2825.99 | G5: =G3-G4 -> 45030.43 | H5: =H3-H4 -> 406534.88 | I5: =I3-I4 -> 1807.1 | J5: =J3-J4 -> 153276.37 | K5: =K3-K4 -> 21567.11 | ... N5: =N3-N4 -> 103950 | O5: =SUM(D5:N5) -> 891397.93
C6: Add: Deposits | D6: 2188583.3 | E6: 22040 | F6: 586775 | G6: 526685.56 | H6: 2671374.4 | I6: 451842 | J6: 3013065 | K6: 1000 | M6: 300000 | N6: 300000 | O6: =SUM(D6:N6) -> 10061365 | P6: =O17+O18+O19 -> 10061365 | Q6: =O6-P6 -> 0
C7: Less: Checks Issued/ Withdrawals | D7: 2152088.6 | F7: 367131 | G7: 567877.11 | H7: 2486505.9 | I7: 333500 | J7: 3025460 | M7: 300000 | N7: 404050 | O7: =SUM(D7:N7) -> 9636612.6 | P7: =O20+O21+O23+O25+O26+O27+O24 -> 9636612.6 | Q7: =O7-P7 -> 0
C8: Available Cash, End. Jan 31, 2026 | D8: =D5+D6-D7 -> 175797.41 | E8: =E5+E6-E7 -> 39143.36 | F8: =F5+F6-F7 -> 222469.99 | G8: =G5+G6-G7 -> 3838.88 | H8: =H5+H6-H7 -> 591403.36 | I8: =I5+I6-I7 -> 120149.1 | J8: =J5+J6-J7 -> 140881.37 | K8: =K5+K6-K7 -> 22567.11 | ... N8: =N5+N6-N7 -> -100 | O8: =SUM(D8:N8) -> 1316150.6 | Q8: =O3-O4+O6-O7 -> 1316150.6 | R8: =O8-Q8 -> 0
C9: Add: ADB/Maintaining Balance/ PCF | D9: =D4 -> 50000 | E9: =E4 -> 5000 | F9: =F4 -> 5000 | G9: =G4 -> 5000 | H9: =H4 -> 5000 | I9: =I4 -> 5000 | J9: =J4 -> 50000 | K9: =K4 -> 5000 | ... N9: =N4 -> 20000 | O9: =SUM(D9:N9) -> 155000
C10: TOTAL CASH | D10: =D8+D9 -> 225797.41 | E10: =E8+E9 -> 44143.36 | F10: =F8+F9 -> 227469.99 | G10: =G8+G9 -> 8838.88 | H10: =H8+H9 -> 596403.36 | I10: =I8+I9 -> 125149.1 | J10: =J8+J9 -> 190881.37 | K10: =K8+K9 -> 27567.11 | ... N10: =N8+N9 -> 19900 | O10: =SUM(D10:N10) -> 1471150.6 | P10: =O8+O9 -> 1471150.6 | Q10: =O10-P10 -> 0
D11: =D8/$O$8 -> 0.13356937 | E11: =E8/$O$8 -> 0.029740792 | F11: =F8/$O$8 -> 0.1690308 | G11: =G8/$O$8 -> 0.0029167483 | H11: =H8/$O$8 -> 0.44934324 | I11: =I8/$O$8 -> 0.091288263 | J11: =J8/$O$8 -> 0.10704046 | K11: =K8/$O$8 -> 0.017146298 | L11: =L8/$O$8 -> 0
G12: =G5+G4 -> 50030.43 | H12: =H5+H4 -> 411534.88 | I12: =I5+I4 -> 6807.1 | J12: =J5+J4 -> 203276.37
C13: T-ENDING | D13: 225797.41 | E13: 44143.36 | F13: 227469.99 | G13: 8838.88 | H13: 596403.36 | I13: 125149.1 | J13: 190881.37 | K13: 27567.11 | L13: 5000 | N13: 19900 | O13: =SUM(D13:N13) -> 1471150.6
C14: variance | D14: =D10-D13 -> -3.2014214e-10 | E14: =E10-E13 -> 0 | F14: =F10-F13 -> 0 | G14: =G10-G13 -> 1.2187229e-10 | H14: =H10-H13 -> 0 | I14: =I10-I13 -> 0 | J14: =J10-J13 -> 0 | K14: =K10-K13 -> 0 | ... O14: =O10-O13 -> 0
C17: Collections from Distribution and Hauling of Petroleum (+) | D17: =2188583.34-10333.34 -> 2178250 | F17: 586775 | G17: 526675 | H17: =2671374.35-29.35 -> 2671345 | I17: 451842 | J17: 3013065 | M17: 300000 | O17: =SUM(D17:N17) -> 9727952 | P17: =O17-O25-O24 -> 8042437 | Q17: =O17+O18+O19-O20-O21-O23-O24-O25-O26-O27 -> 424752.65
C18: Other Cash Collections relating to operating activities (+) | D18: 10333.34 | E18: =1300+150+20590 -> 22040 | G18: 10.56 | H18: =29.35 -> 29.35 | K18: 1000 | O18: =SUM(D18:N18) -> 33413.25 | Q18: =O17+O18-O24-O25 -> 8075850.2
C19: Funds Borrowed from other account (+) | N19: 300000 | O19: =SUM(D19:N19) -> 300000 | V19: RECONCILIATION DATA | W19: REMARKS
C20: Payments to Supplier of Petroleum Products (-) | D20: =382700+554900 -> 937600 | F20: =256200 -> 256200 | H20: =2229500-750000 -> 1479500 | I20: =102000+231500 -> 333500 | J20: =1796000+245000+878200 -> 2919200 | M20: 300000 | N20: 300000 | O20: =SUM(D20:N20) -> 6526000 | V20: =P17 -> 8042437 | W20: COLLECTIONS NET OF INTER-ACCOUNT
C21: RFP of Accounts Payable [ i.e other suppliers, 3rd parties] (-) | D21: =30626+4646.67+79139.14+32295+5923.46+17350.6+25000 -> 194980.87 | F21: =7131 -> 7131 | G21: 2.11 | H21: =5300+2500+5.87 -> 7805.87 | J21: =3360+2900 -> 6260 | O21: =SUM(D21:N21) -> 216179.85 | V21: =O18 -> 33413.25 | W21: OTHER COLLECTIONS
C22: Disbursement for CAPEX / Purchase of PPE (-) | O22: =SUM(D22:N22) -> 0 | V22: 23300 | W22: GCASH
C23: Cash Withdrawn for PCF Replenishment (-) | D23: =8917.75 -> 8917.75 | O23: =SUM(D23:N23) -> 8917.75 | V23: =-10.56 -> -10.56 | W23: KB INTEREST
C24: Inter-account fund transfer / EW (-) | O24: =SUM(D24:N24) -> 0 | U24: VARIANCE | W24: METROBANK
C25: Inter-account fund transfer / SA to CA (-) | D25: =50000+50000+490000+20590 -> 610590 | G25: =41000+101975+102700+322200 -> 567875 | H25: 403000 | N25: 104050 | O25: =SUM(D25:N25) -> 1685515 | U25: VARIANCE | V25: =-29.35 -> -29.35 | W25: FVB INTEREST
C26: Other Cash payments / transfer relating to operating activities (-) | O26: =SUM(D26:N26) -> 0 | V26: =SUM(V20:V25) -> 8099110.3 | W26: TOTAL
C27: Checks Cleared for Loan / Funds Repayments(-) | D27: 400000 | F27: 103800 | H27: =400000+196200 -> 596200 | J27: 100000 | O27: =SUM(D27:N27) -> 1200000 | P27: =O17+O18-O20-O21-O23-O26-O27 -> 1810267.6 | V27: 9797703.3 | W27: COLLECTIONS OF MICH
C28: TOTAL | D28: =D17+D18+D19-D20-D21-D23-D24-D25-D26-D27 -> 36494.72 | E28: =E17+E18+E19-E20-E21-E23-E24-E25-E26-E27 -> 22040 | F28: =F17+F18+F19-F20-F21-F23-F24-F25-F26-F27 -> 219644 | G28: =G17+G18+G19-G20-G21-G23-G24-G25-G26-G27 -> -41191.55 | H28: =H17+H18+H19-H20-H21-H23-H24-H25-H26-H27 -> 184868.48 | I28: =I17+I18+I19-I20-I21-I23-I24-I25-I26-I27 -> 118342 | J28: =J17+J18+J19-J20-J21-J23-J24-J25-J26-J27 -> -12395 | K28: =K17+K18+K19-K20-K21-K23-K24-K25-K26-K27 -> 1000 | ... O28: =O17+O18+O19-O20-O21-O23-O24-O25-O26-O27 -> 424752.65
C29: BEGINNING | D29: =D3 -> 189302.69 | E29: =E3 -> 22103.36 | F29: =F3 -> 7825.99 | G29: =G3 -> 50030.43 | H29: =H3 -> 411534.88 | I29: =I3 -> 6807.1 | J29: =J3 -> 203276.37 | K29: =K3 -> 26567.11 | ... O29: =O3 -> 1046397.9
C30: ENDING | D30: =D10 -> 225797.41 | E30: =E10 -> 44143.36 | F30: =F10 -> 227469.99 | G30: =G10 -> 8838.88 | H30: =H10 -> 596403.36 | I30: =I10 -> 125149.1 | J30: =J10 -> 190881.37 | K30: =K10 -> 27567.11 | ... O30: =O10 -> 1471150.6 | V30: =V26-V27 -> -1698593 | W30: VARIANCE
C31: VARIANCE | D31: =D28+D29-D30 -> 0 | E31: =E28+E29-E30 -> 0 | F31: =F28+F29-F30 -> 0 | G31: =G28+G29-G30 -> -5.0931703e-11 | H31: =H28+H29-H30 -> 0 | I31: =I28+I29-I30 -> 0 | J31: =J28+J29-J30 -> 0 | K31: =K28+K29-K30 -> 0 | ... O31: =O28+O29-O30 -> 0
D33: =D6-SUM(D17:D19) -> 0 | E33: =E6-SUM(E17:E19) -> 0 | F33: =F6-SUM(F17:F19) -> 0 | G33: =G6-SUM(G17:G19) -> 0 | H33: =H6-SUM(H17:H19) -> 0 | I33: =I6-SUM(I17:I19) -> 0 | J33: =J6-SUM(J17:J19) -> 0 | K33: =K6-SUM(K17:K19) -> 0 | ... O33: =O6-SUM(O17:O19) -> 0
D34: =D7-SUM(D20:D27) -> 0 | E34: =E7-SUM(E20:E27) -> 0 | F34: =F7-SUM(F20:F27) -> 0 | G34: =G7-SUM(G20:G27) -> 0 | H34: =H7-SUM(H20:H27) -> 0 | I34: =I7-SUM(I20:I27) -> 0 | J34: =J7-SUM(J20:J27) -> 0 | K34: =K7-SUM(K20:K27) -> 0 | ... O34: =O7-SUM(O20:O27) -> 0
