Workbook

Sheet MONITORING
A1: MONITORING SHEET FOR MACHINERIES, INDUSTRIAL EQUIPMENT, OTHER SERVICES
A2: Seven-Trent Machineries Industrial Equipment Trading
A3: Starting March 10, 2026
D5: =SUM(D8:D1048576) -> 5478579.9
A6: DATE OF PAYMENT | B6: TR NO: | C6: AR No: | D6: AMOUNT COLLECTED | E6: JOURNAL ENTRY SECTION | I6: CUSTOMER DETAILS | M6: PRODUCT / SERVICES DETAIL | R6: SEGMENT | S6: DR NO. / SOA REF. | T6: DR DATE / SOA DATE | U6: DATE OF REVERSAL OF ENTRY / RECOGNITION OF INCOME
E7: CODE | F7: GENERAL LEDGER (Dr.) | G7: COA | H7: GENERAL LEDGER COA (Cr.) | I7: CODE | J7: CUSTOMER | K7: CONTACT PERSON | L7: ADDRESS | M7: CODE | N7: PRODUCTS / SERVICES | O7: QTY | P7: BRAND / TYPE | Q7: OTHER DESCRIPTION ( ELABORATE DETAILS )
A8: 46091 | B8: 632 | C8: 2026-921 | D8: 2850 | E8: RCS | F8: =IF(E8<>"",VLOOKUP(E8,CODE!$B$2:$C$11,2,0),"") -> RCBC -SAVINGS | G8: 43016 | H8: =IF(G8<>"",VLOOKUP(G8,COA!$A$3:$G$1048576,2,0),"") -> Job Orders | I8: Basagan | J8: =IF(I8<>"",VLOOKUP(I8,'CUSTOMER LISTS'!$B$3:$E$1048576,2,0),"") -> RJM GASOLINAHAN PETROCHEMICAL PRODUCTS TRADING | K8: =IF(I8<>"",VLOOKUP(I8,'CUSTOMER LISTS'!$B$3:$E$1048576,3,0),"") -> FELICISIMA PANTORILLA ORILLAN | L8: =IF(I8<>"",VLOOKUP(I8,'CUSTOMER LISTS'!$B$3:$E$1048576,4,0),"") -> BRGY. BASAGAN, KATIPUNAN, ZAMBOANGA DEL NORTE | M8: 721 | N8: =IF(M8<>"",VLOOKUP(M8,'PRODUCT & SERVICES'!$O:$P,2,0),"") -> Job Order | Q8: REPLACEMENT OF RELAY & CHECK-UP | R8: OPS | S8: NA | T8: NA
A9: 46091 | B9: 632 | C9: 2026-921 | D9: 500 | E9: PSS | F9: =IF(E9<>"",VLOOKUP(E9,CODE!$B$2:$C$11,2,0),"") -> PSBC- SAVINGS | G9: 21016 | H9: =IF(G9<>"",VLOOKUP(G9,COA!$A$3:$G$1048576,2,0),"") -> Unearned Revenue - OPS | I9: Basagan | J9: =IF(I9<>"",VLOOKUP(I9,'CUSTOMER LISTS'!$B$3:$E$1048576,2,0),"") -> RJM GASOLINAHAN PETROCHEMICAL PRODUCTS TRADING | K9: =IF(I9<>"",VLOOKUP(I9,'CUSTOMER LISTS'!$B$3:$E$1048576,3,0),"") -> FELICISIMA PANTORILLA ORILLAN | L9: =IF(I9<>"",VLOOKUP(I9,'CUSTOMER LISTS'!$B$3:$E$1048576,4,0),"") -> BRGY. BASAGAN, KATIPUNAN, ZAMBOANGA DEL NORTE | M9: 731 | N9: =IF(M9<>"",VLOOKUP(M9,'PRODUCT & SERVICES'!$O:$P,2,0),"") -> Other OPS ( Pls. Specify ) | Q9: PAYMENT FOR LEAKED BUCKET
A10: 46091 | B10: 633 | C10: 2026-922 | D10: 1300 | E10: PSS | F10: =IF(E10<>"",VLOOKUP(E10,CODE!$B$2:$C$11,2,0),"") -> PSBC- SAVINGS | G10: 21016 | H10: =IF(G10<>"",VLOOKUP(G10,COA!$A$3:$G$1048576,2,0),"") -> Unearned Revenue - OPS | I10: Singaran | J10: =IF(I10<>"",VLOOKUP(I10,'CUSTOMER LISTS'!$B$3:$E$1048576,2,0),"") -> ED-ZEL FUEL REFILLING STATION | K10: =IF(I10<>"",VLOOKUP(I10,'CUSTOMER LISTS'!$B$3:$E$1048576,3,0),"") -> HAZEL NAMIT CABOVERDE | L10: =IF(I10<>"",VLOOKUP(I10,'CUSTOMER LISTS'!$B$3:$E$1048576,4,0),"") -> BRGY. SINGARAN, LA LIBERTAD, ZAMBOANGA DEL NORTE | M10: 731 | N10: =IF(M10<>"",VLOOKUP(M10,'PRODUCT & SERVICES'!$O:$P,2,0),"") -> Other OPS ( Pls. Specify ) | Q10: RECALIBRATION | R10: OPS | S10: 2026-00108
A11: 46092 | B11: 634 | C11: 2026-923 | D11: 2350 | E11: PSS | F11: =IF(E11<>"",VLOOKUP(E11,CODE!$B$2:$C$11,2,0),"") -> PSBC- SAVINGS | G11: 21016 | H11: =IF(G11<>"",VLOOKUP(G11,COA!$A$3:$G$1048576,2,0),"") -> Unearned Revenue - OPS | I11: Lingasad | J11: =IF(I11<>"",VLOOKUP(I11,'CUSTOMER LISTS'!$B$3:$E$1048576,2,0),"") -> ARQUIZA FUEL REFILLING STATION | K11: =IF(I11<>"",VLOOKUP(I11,'CUSTOMER LISTS'!$B$3:$E$1048576,3,0),"") -> ANTONIO MANINGO ARQUIZA | L11: =IF(I11<>"",VLOOKUP(I11,'CUSTOMER LISTS'!$B$3:$E$1048576,4,0),"") -> BRGY. LINGASAD, POLANCO, ZAMBOANGA DEL NORTE | M11: 711 | N11: =IF(M11<>"",VLOOKUP(M11,'PRODUCT & SERVICES'!$O:$P,2,0),"") -> National | O11: 1 BOX | P11: 2T 200ML X 60 | Q11: FULL PAYMENT ON PURCHASED ITEM | R11: OPS | S11: 2026-031 | T11: 46093
A12: 46093 | B12: 635 | C12: 2026-924 | D12: 20050 | E12: PNC | F12: =IF(E12<>"",VLOOKUP(E12,CODE!$B$2:$C$11,2,0),"") -> PNB - CHECKING | G12: 65000 | H12: =IF(G12<>"",VLOOKUP(G12,COA!$A$3:$G$1048576,2,0),"") -> Miscellaneous Expenses_DHPP | I12: OTHER CUSTOMER | J12: =IF(I12<>"",VLOOKUP(I12,'CUSTOMER LISTS'!$B$3:$E$1048576,2,0),"") -> JOHN BILLY CONCHE | K12: =IF(I12<>"",VLOOKUP(I12,'CUSTOMER LISTS'!$B$3:$E$1048576,3,0),"") -> JOHN BILLY CONCHE | L12: =IF(I12<>"",VLOOKUP(I12,'CUSTOMER LISTS'!$B$3:$E$1048576,4,0),"") -> BRGY. STA.ISABEL, DIPOLOG CITY | M12: 761 | N12: =IF(M12<>"",VLOOKUP(M12,'PRODUCT & SERVICES'!$O:$P,2,0),"") -> Others ( Pls. Specify ) | Q12: PAYMENT FOR CASH IN PNB TO GCASH - CHARGED AS MISCELLANEOUS EXPENSE UPON PAYMENT
A13: 46093 | B13: 636 | C13: 2026-925 | D13: 457200 | E13: EWC | F13: =IF(E13<>"",VLOOKUP(E13,CODE!$B$2:$C$11,2,0),"") -> EASTWEST-CHECKING | H13: =IF(G13<>"",VLOOKUP(G13,COA!$A$3:$G$1048576,2,0),"") | J13: =IF(I13<>"",VLOOKUP(I13,'CUSTOMER LISTS'!$B$3:$E$1048576,2,0),"") | K13: =IF(I13<>"",VLOOKUP(I13,'CUSTOMER LISTS'!$B$3:$E$1048576,3,0),"") | L13: =IF(I13<>"",VLOOKUP(I13,'CUSTOMER LISTS'!$B$3:$E$1048576,4,0),"") | M13: 761 | N13: =IF(M13<>"",VLOOKUP(M13,'PRODUCT & SERVICES'!$O:$P,2,0),"") -> Others ( Pls. Specify ) | Q13: CANCELLED TRANSACTION / CANCELLED ACKNOWLEDGMENT RECEIPT- ERROR ISSUANCE
A14: 46094 | B14: 637 | C14: 2026-926 | D14: 8000 | E14: MBC | F14: =IF(E14<>"",VLOOKUP(E14,CODE!$B$2:$C$11,2,0),"") -> METROBANK-CHECKING | G14: 12070 | H14: =IF(G14<>"",VLOOKUP(G14,COA!$A$3:$G$1048576,2,0),"") -> Advances to Employees - DHPP | I14: CNR | J14: =IF(I14<>"",VLOOKUP(I14,'CUSTOMER LISTS'!$B$3:$E$1048576,2,0),"") -> CLYDE N. REBOLLOS | K14: =IF(I14<>"",VLOOKUP(I14,'CUSTOMER LISTS'!$B$3:$E$1048576,3,0),"") -> CLYDE N. REBOLLOS | L14: =IF(I14<>"",VLOOKUP(I14,'CUSTOMER LISTS'!$B$3:$E$1048576,4,0),"") -> BRGY. STA.ISABEL, DIPOLOG CITY | M14: 761 | N14: =IF(M14<>"",VLOOKUP(M14,'PRODUCT & SERVICES'!$O:$P,2,0),"") -> Others ( Pls. Specify ) | Q14: SALARY LOAN
A15: 46094 | B15: 638 | C15: 2026-927 | D15: 425 | E15: MBC | F15: =IF(E15<>"",VLOOKUP(E15,CODE!$B$2:$C$11,2,0),"") -> METROBANK-CHECKING | G15: 20000 | H15: =IF(G15<>"",VLOOKUP(G15,COA!$A$3:$G$1048576,2,0),"") -> A/Payables - Current - DHPP | J15: =IF(I15<>"",VLOOKUP(I15,'CUSTOMER LISTS'!$B$3:$E$1048576,2,0),"") | K15: =IF(I15<>"",VLOOKUP(I15,'CUSTOMER LISTS'!$B$3:$E$1048576,3,0),"") | L15: =IF(I15<>"",VLOOKUP(I15,'CUSTOMER LISTS'!$B$3:$E$1048576,4,0),"") | M15: 761 | N15: =IF(M15<>"",VLOOKUP(M15,'PRODUCT & SERVICES'!$O:$P,2,0),"") -> Others ( Pls. Specify ) | Q15: CANCELLED TRANSACTION / CANCELLED ACKNOWLEDGMENT RECEIPT- ERROR ISSUANCE
A16: 46094 | B16: 639 | C16: 2026-928 | D16: 30378.29 | E16: PNC | F16: =IF(E16<>"",VLOOKUP(E16,CODE!$B$2:$C$11,2,0),"") -> PNB - CHECKING | G16: 15000 | H16: =IF(G16<>"",VLOOKUP(G16,COA!$A$3:$G$1048576,2,0),"") -> Due from STPC - DHPP | I16: STPC-San Pedro | J16: =IF(I16<>"",VLOOKUP(I16,'CUSTOMER LISTS'!$B$3:$E$1048576,2,0),"") -> SEVEN-TRENT PETROLEUM CORP. | K16: =IF(I16<>"",VLOOKUP(I16,'CUSTOMER LISTS'!$B$3:$E$1048576,3,0),"") -> SEVEN-TRENT PETROLEUM CORP. | L16: =IF(I16<>"",VLOOKUP(I16,'CUSTOMER LISTS'!$B$3:$E$1048576,4,0),"") -> BRGY. SAN PEDRO, DAPITAN, ZAMBOANGA DEL NORTE | M16: 761 | N16: =IF(M16<>"",VLOOKUP(M16,'PRODUCT & SERVICES'!$O:$P,2,0),"") -> Others ( Pls. Specify ) | Q16: COLLECTION OF RECEIVABLES - PAYMENT FOR VARIOUS EXPENSES FOR MAY 1-31, 2025
A17: 46094 | B17: 640 | C17: 2026-929 | D17: 500000 | E17: EWC | F17: =IF(E17<>"",VLOOKUP(E17,CODE!$B$2:$C$11,2,0),"") -> EASTWEST-CHECKING | G17: 25500 | H17: =IF(G17<>"",VLOOKUP(G17,COA!$A$3:$G$1048576,2,0),"") -> Other Payables_Current - DHPP | I17: STPC-San Pedro | J17: =IF(I17<>"",VLOOKUP(I17,'CUSTOMER LISTS'!$B$3:$E$1048576,2,0),"") -> SEVEN-TRENT PETROLEUM CORP. | K17: =IF(I17<>"",VLOOKUP(I17,'CUSTOMER LISTS'!$B$3:$E$1048576,3,0),"") -> SEVEN-TRENT PETROLEUM CORP. | L17: =IF(I17<>"",VLOOKUP(I17,'CUSTOMER LISTS'!$B$3:$E$1048576,4,0),"") -> BRGY. SAN PEDRO, DAPITAN, ZAMBOANGA DEL NORTE | M17: 761 | N17: =IF(M17<>"",VLOOKUP(M17,'PRODUCT & SERVICES'!$O:$P,2,0),"") -> Others ( Pls. Specify ) | Q17: RECOGNIZED SHORT TERM LOAN
A18: 46095 | B18: 641 | C18: 2026-930 | D18: 400000 | E18: EWC | F18: =IF(E18<>"",VLOOKUP(E18,CODE!$B$2:$C$11,2,0),"") -> EASTWEST-CHECKING | G18: 21023 | H18: =IF(G18<>"",VLOOKUP(G18,COA!$A$3:$G$1048576,2,0),"") -> Unearned Revenue - DMIE | I18: TM-CALAMBA | J18: =IF(I18<>"",VLOOKUP(I18,'CUSTOMER LISTS'!$B$3:$E$1048576,2,0),"") -> TM'S GAS REFILLING STATION | K18: =IF(I18<>"",VLOOKUP(I18,'CUSTOMER LISTS'!$B$3:$E$1048576,3,0),"") -> ISABELO A. VILLANUEVA III | L18: =IF(I18<>"",VLOOKUP(I18,'CUSTOMER LISTS'!$B$3:$E$1048576,4,0),"") -> BRGY. SOUTHWESTERN POBLACION, CALAMBA, MISAMIS OCCIDENTAL | M18: 2217 | N18: =IF(M18<>"",VLOOKUP(M18,'PRODUCT & SERVICES'!$O:$P,2,0),"") -> 5.0 KL TSRO Standard Machine | Q18: DOWNPAYMENT FOR 5 KL TSRO STP MACHINE
A19: 46097 | B19: 642 | C19: 2026-931 | D19: 250 | E19: PSS | F19: =IF(E19<>"",VLOOKUP(E19,CODE!$B$2:$C$11,2,0),"") -> PSBC- SAVINGS | G19: 21016 | H19: =IF(G19<>"",VLOOKUP(G19,COA!$A$3:$G$1048576,2,0),"") -> Unearned Revenue - OPS | I19: Singaran | J19: =IF(I19<>"",VLOOKUP(I19,'CUSTOMER LISTS'!$B$3:$E$1048576,2,0),"") -> ED-ZEL FUEL REFILLING STATION | K19: =IF(I19<>"",VLOOKUP(I19,'CUSTOMER LISTS'!$B$3:$E$1048576,3,0),"") -> HAZEL NAMIT CABOVERDE | L19: =IF(I19<>"",VLOOKUP(I19,'CUSTOMER LISTS'!$B$3:$E$1048576,4,0),"") -> BRGY. SINGARAN, LA LIBERTAD, ZAMBOANGA DEL NORTE | M19: 731 | N19: =IF(M19<>"",VLOOKUP(M19,'PRODUCT & SERVICES'!$O:$P,2,0),"") -> Other OPS ( Pls. Specify ) | Q19: PAYMENT FOR NOZZLE JACKET
A20: 46097 | B20: 643 | C20: 2026-932 | D20: 12647 | E20: EWC | F20: =IF(E20<>"",VLOOKUP(E20,CODE!$B$2:$C$11,2,0),"") -> EASTWEST-CHECKING | G20: 25506 | H20: =IF(G20<>"",VLOOKUP(G20,COA!$A$3:$G$1048576,2,0),"") -> Other Payables_Current - OPS | I20: STPC-San Pedro | J20: =IF(I20<>"",VLOOKUP(I20,'CUSTOMER LISTS'!$B$3:$E$1048576,2,0),"") -> SEVEN-TRENT PETROLEUM CORP. | K20: =IF(I20<>"",VLOOKUP(I20,'CUSTOMER LISTS'!$B$3:$E$1048576,3,0),"") -> SEVEN-TRENT PETROLEUM CORP. | L20: =IF(I20<>"",VLOOKUP(I20,'CUSTOMER LISTS'!$B$3:$E$1048576,4,0),"") -> BRGY. SAN PEDRO, DAPITAN, ZAMBOANGA DEL NORTE | M20: 761 | N20: =IF(M20<>"",VLOOKUP(M20,'PRODUCT & SERVICES'!$O:$P,2,0),"") -> Others ( Pls. Specify ) | Q20: TAMARAW AMORTIZATION
A21: 46100 | B21: 644 | C21: 2026-933 | D21: 4260 | E21: PSS | F21: =IF(E21<>"",VLOOKUP(E21,CODE!$B$2:$C$11,2,0),"") -> PSBC- SAVINGS | G21: 21016 | H21: =IF(G21<>"",VLOOKUP(G21,COA!$A$3:$G$1048576,2,0),"") -> Unearned Revenue - OPS | I21: Dansulyan-Awa | J21: =IF(I21<>"",VLOOKUP(I21,'CUSTOMER LISTS'!$B$3:$E$1048576,2,0),"") -> MJ FUEL REFILLING STATION | K21: =IF(I21<>"",VLOOKUP(I21,'CUSTOMER LISTS'!$B$3:$E$1048576,3,0),"") -> JERELYN MONTEZA AWA | L21: =IF(I21<>"",VLOOKUP(I21,'CUSTOMER LISTS'!$B$3:$E$1048576,4,0),"") -> BRGY. DANSULLAN, POLANCO, ZAMBOANGA DEL NORTE | M21: 731 | N21: =IF(M21<>"",VLOOKUP(M21,'PRODUCT & SERVICES'!$O:$P,2,0),"") -> Other OPS ( Pls. Specify ) | O21: 1 BOX | P21: DEOMAX 15W-40 OIL | Q21: FULL PAYMENT ON PURCHASED ITEM | R21: OPS | S21: 2026-037 | T21: 46100
A22: 46100 | B22: 645 | C22: 2026-934 | D22: 48653.97 | E22: PNC | F22: =IF(E22<>"",VLOOKUP(E22,CODE!$B$2:$C$11,2,0),"") -> PNB - CHECKING | G22: 15000 | H22: =IF(G22<>"",VLOOKUP(G22,COA!$A$3:$G$1048576,2,0),"") -> Due from STPC - DHPP | I22: STPC-San Pedro | J22: =IF(I22<>"",VLOOKUP(I22,'CUSTOMER LISTS'!$B$3:$E$1048576,2,0),"") -> SEVEN-TRENT PETROLEUM CORP. | K22: =IF(I22<>"",VLOOKUP(I22,'CUSTOMER LISTS'!$B$3:$E$1048576,3,0),"") -> SEVEN-TRENT PETROLEUM CORP. | L22: =IF(I22<>"",VLOOKUP(I22,'CUSTOMER LISTS'!$B$3:$E$1048576,4,0),"") -> BRGY. SAN PEDRO, DAPITAN, ZAMBOANGA DEL NORTE | M22: 761 | N22: =IF(M22<>"",VLOOKUP(M22,'PRODUCT & SERVICES'!$O:$P,2,0),"") -> Others ( Pls. Specify ) | Q22: PAYMENT FOR BIR DOCUMENTATION TAX STAMP
A23: 46100 | B23: 646 | C23: 2026-935 | D23: 18890 | E23: FVC | F23: =IF(E23<>"",VLOOKUP(E23,CODE!$B$2:$C$11,2,0),"") -> FIRST VALLEY -CHECKING | G23: 43026 | H23: =IF(G23<>"",VLOOKUP(G23,COA!$A$3:$G$1048576,2,0),"") -> Service Income | I23: Suertes-Guitran | J23: =IF(I23<>"",VLOOKUP(I23,'CUSTOMER LISTS'!$B$3:$E$1048576,2,0),"") -> SUERTE GAS STATION | K23: =IF(I23<>"",VLOOKUP(I23,'CUSTOMER LISTS'!$B$3:$E$1048576,3,0),"") -> ALJUN LATA SUERTE | L23: =IF(I23<>"",VLOOKUP(I23,'CUSTOMER LISTS'!$B$3:$E$1048576,4,0),"") -> BRGY. GUITRAN, DUMINGAG, ZAMBOANGA DEL SUR | M23: 751 | N23: =IF(M23<>"",VLOOKUP(M23,'PRODUCT & SERVICES'!$O:$P,2,0),"") -> Other Services ( Pls. Specify ) | Q23: COC PROCESSING
A24: 46101 | B24: 647 | C24: 2026-936 | D24: 5300 | E24: PNC | F24: =IF(E24<>"",VLOOKUP(E24,CODE!$B$2:$C$11,2,0),"") -> PNB - CHECKING | G24: 21023 | H24: =IF(G24<>"",VLOOKUP(G24,COA!$A$3:$G$1048576,2,0),"") -> Unearned Revenue - DMIE | I24: MUTIA-OROQUIETA | J24: =IF(I24<>"",VLOOKUP(I24,'CUSTOMER LISTS'!$B$3:$E$1048576,2,0),"") -> MUTIA RANGERS FUEL RETAILING | K24: =IF(I24<>"",VLOOKUP(I24,'CUSTOMER LISTS'!$B$3:$E$1048576,3,0),"") -> JULIE ANN CONING MUTIA | L24: =IF(I24<>"",VLOOKUP(I24,'CUSTOMER LISTS'!$B$3:$E$1048576,4,0),"") -> BRGY. DOLIPOS, BAJO, OROQUIETA CITY | M24: 731 | N24: =IF(M24<>"",VLOOKUP(M24,'PRODUCT & SERVICES'!$O:$P,2,0),"") -> Other OPS ( Pls. Specify ) | Q24: CALIBRATION BUCKET | R24: OPS | S24: 2026-00107 | T24: 46218
A25: 46102 | B25: 648 | C25: 2026-937 | D25: 200000 | E25: MBC | F25: =IF(E25<>"",VLOOKUP(E25,CODE!$B$2:$C$11,2,0),"") -> METROBANK-CHECKING | G25: 21023 | H25: =IF(G25<>"",VLOOKUP(G25,COA!$A$3:$G$1048576,2,0),"") -> Unearned Revenue - DMIE | I25: Villaflor Oroquieta | J25: =IF(I25<>"",VLOOKUP(I25,'CUSTOMER LISTS'!$B$3:$E$1048576,2,0),"") -> AYA G MICRO GAS STATION | K25: =IF(I25<>"",VLOOKUP(I25,'CUSTOMER LISTS'!$B$3:$E$1048576,3,0),"") -> ARTIUS TALADUA GALINDO | L25: =IF(I25<>"",VLOOKUP(I25,'CUSTOMER LISTS'!$B$3:$E$1048576,4,0),"") -> BRGY. VILLAFLOR, OROQUIETA CITY, MISAMIS OCCIDENTAL | M25: 2218 | N25: =IF(M25<>"",VLOOKUP(M25,'PRODUCT & SERVICES'!$O:$P,2,0),"") -> 5.0 KL TSRO Standing Machine | Q25: ADDITIONAL PAYMENT (PROMO PRICE ON MACHINE) | S25: 2026-0009 | T25: 4/7/2026
A26: 46104 | B26: 649 | C26: 2026-938 | D26: 2350 | E26: PNC | F26: =IF(E26<>"",VLOOKUP(E26,CODE!$B$2:$C$11,2,0),"") -> PNB - CHECKING | G26: 21016 | H26: =IF(G26<>"",VLOOKUP(G26,COA!$A$3:$G$1048576,2,0),"") -> Unearned Revenue - OPS | I26: Binoni | J26: =IF(I26<>"",VLOOKUP(I26,'CUSTOMER LISTS'!$B$3:$E$1048576,2,0),"") -> BOY G FUEL REFILLING STATION | K26: =IF(I26<>"",VLOOKUP(I26,'CUSTOMER LISTS'!$B$3:$E$1048576,3,0),"") -> EPIFRAS RUDAS GALLEPOSO | L26: =IF(I26<>"",VLOOKUP(I26,'CUSTOMER LISTS'!$B$3:$E$1048576,4,0),"") -> BRGY. BINONI, SALUG, ZAMBOANGA DEL NORTE | M26: 712 | N26: =IF(M26<>"",VLOOKUP(M26,'PRODUCT & SERVICES'!$O:$P,2,0),"") -> Sea-Oil | O26: 1 BOX | P26: 2T 200ML X 60 | Q26: FULL PAYMENT ON PURCHASED ITEM | S26: 2026-0036 | T26: 3/26/2026
A27: 46104 | B27: 650 | C27: 2026-939 | D27: 173500 | E27: MBC | F27: =IF(E27<>"",VLOOKUP(E27,CODE!$B$2:$C$11,2,0),"") -> METROBANK-CHECKING | G27: 21023 | H27: =IF(G27<>"",VLOOKUP(G27,COA!$A$3:$G$1048576,2,0),"") -> Unearned Revenue - DMIE | I27: Villaflor Oroquieta | J27: =IF(I27<>"",VLOOKUP(I27,'CUSTOMER LISTS'!$B$3:$E$1048576,2,0),"") -> AYA G MICRO GAS STATION | K27: =IF(I27<>"",VLOOKUP(I27,'CUSTOMER LISTS'!$B$3:$E$1048576,3,0),"") -> ARTIUS TALADUA GALINDO | L27: =IF(I27<>"",VLOOKUP(I27,'CUSTOMER LISTS'!$B$3:$E$1048576,4,0),"") -> BRGY. VILLAFLOR, OROQUIETA CITY, MISAMIS OCCIDENTAL | M27: 2218 | N27: =IF(M27<>"",VLOOKUP(M27,'PRODUCT & SERVICES'!$O:$P,2,0),"") -> 5.0 KL TSRO Standing Machine | Q27: FULL PAYMENT ON 5 KL MACHINE (PROMO PRICE) | S27: 2026-0009 | T27: 4/7/2026
A28: 46106 | B28: 651 | C28: 2026-940 | D28: 2400 | E28: PSC | F28: =IF(E28<>"",VLOOKUP(E28,CODE!$B$2:$C$11,2,0),"") -> PSBC - CHECKING | G28: 21016 | H28: =IF(G28<>"",VLOOKUP(G28,COA!$A$3:$G$1048576,2,0),"") -> Unearned Revenue - OPS | I28: Dansulyan-Awa | J28: =IF(I28<>"",VLOOKUP(I28,'CUSTOMER LISTS'!$B$3:$E$1048576,2,0),"") -> MJ FUEL REFILLING STATION | K28: =IF(I28<>"",VLOOKUP(I28,'CUSTOMER LISTS'!$B$3:$E$1048576,3,0),"") -> JERELYN MONTEZA AWA | L28: =IF(I28<>"",VLOOKUP(I28,'CUSTOMER LISTS'!$B$3:$E$1048576,4,0),"") -> BRGY. DANSULLAN, POLANCO, ZAMBOANGA DEL NORTE | M28: 712 | N28: =IF(M28<>"",VLOOKUP(M28,'PRODUCT & SERVICES'!$O:$P,2,0),"") -> Sea-Oil | O28: 1 BOX | P28: 2T 200ML X 60 | Q28: FULL PAYMENT ON PURCHASED ITEM | S28: 2026-049 | T28: 46106
A29: 04/01/2026 | B29: 652 | C29: 2026-941 | D29: 1500 | E29: RCS | F29: =IF(E29<>"",VLOOKUP(E29,CODE!$B$2:$C$11,2,0),"") -> RCBC -SAVINGS | G29: 43016 | H29: =IF(G29<>"",VLOOKUP(G29,COA!$A$3:$G$1048576,2,0),"") -> Job Orders | I29: Bayog buboan | J29: =IF(I29<>"",VLOOKUP(I29,'CUSTOMER LISTS'!$B$3:$E$1048576,2,0),"") -> REDBAR GAS REFILLING STATION | K29: =IF(I29<>"",VLOOKUP(I29,'CUSTOMER LISTS'!$B$3:$E$1048576,3,0),"") -> ARNEL GAJO ENTAG | L29: =IF(I29<>"",VLOOKUP(I29,'CUSTOMER LISTS'!$B$3:$E$1048576,4,0),"") -> BRGY. BOBUAN, BAYOG, ZAMBOANGA DEL SUR | M29: 721 | N29: =IF(M29<>"",VLOOKUP(M29,'PRODUCT & SERVICES'!$O:$P,2,0),"") -> Job Order | Q29: CALIBRATION | U29: 04/01/2026
A30: 04/01/2026 | B30: 653 | C30: 2026-942 | D30: 1500 | E30: RCS | F30: =IF(E30<>"",VLOOKUP(E30,CODE!$B$2:$C$11,2,0),"") -> RCBC -SAVINGS | G30: 43016 | H30: =IF(G30<>"",VLOOKUP(G30,COA!$A$3:$G$1048576,2,0),"") -> Job Orders | I30: Liba Bayog | J30: =IF(I30<>"",VLOOKUP(I30,'CUSTOMER LISTS'!$B$3:$E$1048576,2,0),"") -> KELTEX GAS REFILLING STATION | K30: =IF(I30<>"",VLOOKUP(I30,'CUSTOMER LISTS'!$B$3:$E$1048576,3,0),"") -> LOVELY BERNARDO FABIANTES | L30: =IF(I30<>"",VLOOKUP(I30,'CUSTOMER LISTS'!$B$3:$E$1048576,4,0),"") -> BRGY. LIBA, BAYOG, ZAMBOANGA DEL SUR | M30: 721 | N30: =IF(M30<>"",VLOOKUP(M30,'PRODUCT & SERVICES'!$O:$P,2,0),"") -> Job Order | Q30: CALIBRATION | U30: 04/01/2026
A31: 04/01/2026 | B31: 654 | C31: 2026-943 | D31: 4000 | E31: RCS | F31: =IF(E31<>"",VLOOKUP(E31,CODE!$B$2:$C$11,2,0),"") -> RCBC -SAVINGS | G31: 43016 | H31: =IF(G31<>"",VLOOKUP(G31,COA!$A$3:$G$1048576,2,0),"") -> Job Orders | I31: Bayog Bulilit | J31: =IF(I31<>"",VLOOKUP(I31,'CUSTOMER LISTS'!$B$3:$E$1048576,2,0),"") -> JDM-6 FUEL STATION | K31: =IF(I31<>"",VLOOKUP(I31,'CUSTOMER LISTS'!$B$3:$E$1048576,3,0),"") -> DELIA SAJULGA BACO | L31: =IF(I31<>"",VLOOKUP(I31,'CUSTOMER LISTS'!$B$3:$E$1048576,4,0),"") -> BRGY. KAHAYAGAN, BAYOG, ZAMBOANGA DEL SUR | M31: 721 | N31: =IF(M31<>"",VLOOKUP(M31,'PRODUCT & SERVICES'!$O:$P,2,0),"") -> Job Order | Q31: CALIBRATION | U31: 04/01/2026
A32: 04/01/2026 | B32: 655 | C32: 2026-944 | D32: 1500 | E32: RCS | F32: =IF(E32<>"",VLOOKUP(E32,CODE!$B$2:$C$11,2,0),"") -> RCBC -SAVINGS | G32: 43016 | H32: =IF(G32<>"",VLOOKUP(G32,COA!$A$3:$G$1048576,2,0),"") -> Job Orders | I32: Dipili Bayog | J32: =IF(I32<>"",VLOOKUP(I32,'CUSTOMER LISTS'!$B$3:$E$1048576,2,0),"") -> MG'S FUEL REFILLING STATION | K32: =IF(I32<>"",VLOOKUP(I32,'CUSTOMER LISTS'!$B$3:$E$1048576,3,0),"") -> NORMITA DELA CERNA | L32: =IF(I32<>"",VLOOKUP(I32,'CUSTOMER LISTS'!$B$3:$E$1048576,4,0),"") -> BRGY. DIPILI, BAYOG, ZAMBOANGA DEL SUR | M32: 721 | N32: =IF(M32<>"",VLOOKUP(M32,'PRODUCT & SERVICES'!$O:$P,2,0),"") -> Job Order | Q32: CALIBRATION | U32: 04/01/2026
A33: 04/01/2026 | B33: 656 | C33: 2026-945 | D33: 4800 | E33: PSS | F33: =IF(E33<>"",VLOOKUP(E33,CODE!$B$2:$C$11,2,0),"") -> PSBC- SAVINGS | G33: 21016 | H33: =IF(G33<>"",VLOOKUP(G33,COA!$A$3:$G$1048576,2,0),"") -> Unearned Revenue - OPS | I33: Villahermosa | J33: =IF(I33<>"",VLOOKUP(I33,'CUSTOMER LISTS'!$B$3:$E$1048576,2,0),"") -> CM-POWER FUEL REFILLING STATION | K33: =IF(I33<>"",VLOOKUP(I33,'CUSTOMER LISTS'!$B$3:$E$1048576,3,0),"") -> CHARLENE ESTRADA MANDANTES | L33: =IF(I33<>"",VLOOKUP(I33,'CUSTOMER LISTS'!$B$3:$E$1048576,4,0),"") -> BRGY. VILLAHERMOSA, POLANCO, ZAMBOANGA DEL NORTE | M33: 712 | N33: =IF(M33<>"",VLOOKUP(M33,'PRODUCT & SERVICES'!$O:$P,2,0),"") -> Sea-Oil | O33: 2 BOXES | P33: 2T 200ML X 60 | Q33: FULL PAYMENT ON PURCHASED ITEM | R33: OPS | S33: 2026-045 | T33: 46118
A34: 04/06/2026 | B34: 657 | C34: 2026-946 | D34: 1300 | E34: PSS | F34: =IF(E34<>"",VLOOKUP(E34,CODE!$B$2:$C$11,2,0),"") -> PSBC- SAVINGS | G34: 21016 | H34: =IF(G34<>"",VLOOKUP(G34,COA!$A$3:$G$1048576,2,0),"") -> Unearned Revenue - OPS | I34: Paruk Siay | J34: =IF(I34<>"",VLOOKUP(I34,'CUSTOMER LISTS'!$B$3:$E$1048576,2,0),"") -> CRILOUR FUEL REFILLING STATION | K34: =IF(I34<>"",VLOOKUP(I34,'CUSTOMER LISTS'!$B$3:$E$1048576,3,0),"") -> ELSON ENRIQUEZ BASCO | L34: =IF(I34<>"",VLOOKUP(I34,'CUSTOMER LISTS'!$B$3:$E$1048576,4,0),"") -> BRGY. PARUK, SIAY, ZAMBOANGA SIBUGAY | M34: 731 | N34: =IF(M34<>"",VLOOKUP(M34,'PRODUCT & SERVICES'!$O:$P,2,0),"") -> Other OPS ( Pls. Specify ) | Q34: RECALIBRATION
A35: 04/07/2026 | B35: 658 | C35: 2026-947 | D35: 93900 | E35: MBC | F35: =IF(E35<>"",VLOOKUP(E35,CODE!$B$2:$C$11,2,0),"") -> METROBANK-CHECKING | G35: 25500 | H35: =IF(G35<>"",VLOOKUP(G35,COA!$A$3:$G$1048576,2,0),"") -> Other Payables_Current - DHPP | I35: STPC-San Pedro | J35: =IF(I35<>"",VLOOKUP(I35,'CUSTOMER LISTS'!$B$3:$E$1048576,2,0),"") -> SEVEN-TRENT PETROLEUM CORP. | K35: =IF(I35<>"",VLOOKUP(I35,'CUSTOMER LISTS'!$B$3:$E$1048576,3,0),"") -> SEVEN-TRENT PETROLEUM CORP. | L35: =IF(I35<>"",VLOOKUP(I35,'CUSTOMER LISTS'!$B$3:$E$1048576,4,0),"") -> BRGY. SAN PEDRO, DAPITAN, ZAMBOANGA DEL NORTE | M35: 761 | N35: =IF(M35<>"",VLOOKUP(M35,'PRODUCT & SERVICES'!$O:$P,2,0),"") -> Others ( Pls. Specify ) | Q35: SHORT TERM LOAN
A36: 04/07/2026 | B36: 659 | C36: 2026-948 | D36: 50000 | E36: MBC | F36: =IF(E36<>"",VLOOKUP(E36,CODE!$B$2:$C$11,2,0),"") -> METROBANK-CHECKING | G36: 43060 | H36: =IF(G36<>"",VLOOKUP(G36,COA!$A$3:$G$1048576,2,0),"") -> Miscellaneous Income - DHPP | I36: E.TAN | J36: =IF(I36<>"",VLOOKUP(I36,'CUSTOMER LISTS'!$B$3:$E$1048576,2,0),"") -> MEM TRADING AND HAULING SERVICES INC. | K36: =IF(I36<>"",VLOOKUP(I36,'CUSTOMER LISTS'!$B$3:$E$1048576,3,0),"") -> EMMANUEL TAN | L36: =IF(I36<>"",VLOOKUP(I36,'CUSTOMER LISTS'!$B$3:$E$1048576,4,0),"") -> BRGY. SOUTHWESTERN POBLACION, CALAMBA, MISAMIS OCCIDENTAL | M36: 761 | N36: =IF(M36<>"",VLOOKUP(M36,'PRODUCT & SERVICES'!$O:$P,2,0),"") -> Others ( Pls. Specify ) | Q36: FUEL ASSISTANCE INCOME
A37: 04/08/2026 | B37: 660 | C37: 2026-949 | D37: 35210 | E37: MBC | F37: =IF(E37<>"",VLOOKUP(E37,CODE!$B$2:$C$11,2,0),"") -> METROBANK-CHECKING | G37: 21023 | H37: =IF(G37<>"",VLOOKUP(G37,COA!$A$3:$G$1048576,2,0),"") -> Unearned Revenue - DMIE | I37: Villaflor Oroquieta | J37: =IF(I37<>"",VLOOKUP(I37,'CUSTOMER LISTS'!$B$3:$E$1048576,2,0),"") -> AYA G MICRO GAS STATION | K37: =IF(I37<>"",VLOOKUP(I37,'CUSTOMER LISTS'!$B$3:$E$1048576,3,0),"") -> ARTIUS TALADUA GALINDO | L37: =IF(I37<>"",VLOOKUP(I37,'CUSTOMER LISTS'!$B$3:$E$1048576,4,0),"") -> BRGY. VILLAFLOR, OROQUIETA CITY, MISAMIS OCCIDENTAL | M37: 761 | N37: =IF(M37<>"",VLOOKUP(M37,'PRODUCT & SERVICES'!$O:$P,2,0),"") -> Others ( Pls. Specify ) | Q37: SHIPPING PARTICIPATION
A38: 04/08/2026 | B38: 661 | C38: 2026-950 | D38: 35210 | E38: EWC | F38: =IF(E38<>"",VLOOKUP(E38,CODE!$B$2:$C$11,2,0),"") -> EASTWEST-CHECKING | G38: 21023 | H38: =IF(G38<>"",VLOOKUP(G38,COA!$A$3:$G$1048576,2,0),"") -> Unearned Revenue - DMIE | I38: MUTIA-OROQUIETA | J38: =IF(I38<>"",VLOOKUP(I38,'CUSTOMER LISTS'!$B$3:$E$1048576,2,0),"") -> MUTIA RANGERS FUEL RETAILING | K38: =IF(I38<>"",VLOOKUP(I38,'CUSTOMER LISTS'!$B$3:$E$1048576,3,0),"") -> JULIE ANN CONING MUTIA | L38: =IF(I38<>"",VLOOKUP(I38,'CUSTOMER LISTS'!$B$3:$E$1048576,4,0),"") -> BRGY. DOLIPOS, BAJO, OROQUIETA CITY | M38: 761 | N38: =IF(M38<>"",VLOOKUP(M38,'PRODUCT & SERVICES'!$O:$P,2,0),"") -> Others ( Pls. Specify ) | Q38: SHIPPING PARTICIPATION | R38: DMIE
A39: 04/09/2026 | B39: 662 | C39: 2026-951 | D39: 2200 | E39: PSC | F39: =IF(E39<>"",VLOOKUP(E39,CODE!$B$2:$C$11,2,0),"") -> PSBC - CHECKING | G39: 21016 | H39: =IF(G39<>"",VLOOKUP(G39,COA!$A$3:$G$1048576,2,0),"") -> Unearned Revenue - OPS | I39: CALAMBA | J39: =IF(I39<>"",VLOOKUP(I39,'CUSTOMER LISTS'!$B$3:$E$1048576,2,0),"") -> CALAMBA FUEL REFILLING STATION | K39: =IF(I39<>"",VLOOKUP(I39,'CUSTOMER LISTS'!$B$3:$E$1048576,3,0),"") -> RONAN CASTILLON | L39: =IF(I39<>"",VLOOKUP(I39,'CUSTOMER LISTS'!$B$3:$E$1048576,4,0),"") -> BRGY. MAGCAMIGUING, CALAMBA, ZAMBOANGA DEL NORTE | M39: 711 | N39: =IF(M39<>"",VLOOKUP(M39,'PRODUCT & SERVICES'!$O:$P,2,0),"") -> National | O39: 1/2 BOX | P39: 2T 1L X 24 | Q39: FULL PAYMENT ON PURCHASED ITEM | S39: 2026-046 | T39: 4/10/2026
A40: 04/09/2026 | B40: 662 | C40: 2026-951 | D40: 2125 | E40: PSC | F40: =IF(E40<>"",VLOOKUP(E40,CODE!$B$2:$C$11,2,0),"") -> PSBC - CHECKING | G40: 21016 | H40: =IF(G40<>"",VLOOKUP(G40,COA!$A$3:$G$1048576,2,0),"") -> Unearned Revenue - OPS | I40: CALAMBA | J40: =IF(I40<>"",VLOOKUP(I40,'CUSTOMER LISTS'!$B$3:$E$1048576,2,0),"") -> CALAMBA FUEL REFILLING STATION | K40: =IF(I40<>"",VLOOKUP(I40,'CUSTOMER LISTS'!$B$3:$E$1048576,3,0),"") -> RONAN CASTILLON | L40: =IF(I40<>"",VLOOKUP(I40,'CUSTOMER LISTS'!$B$3:$E$1048576,4,0),"") -> BRGY. MAGCAMIGUING, CALAMBA, ZAMBOANGA DEL NORTE | M40: 712 | N40: =IF(M40<>"",VLOOKUP(M40,'PRODUCT & SERVICES'!$O:$P,2,0),"") -> Sea-Oil | O40: 1/2 BOX | P40: 2T 1L X 24 | Q40: FULL PAYMENT ON PURCHASED ITEM | S40: 2026-046 | T40: 4/10/2026
A41: 04/11/2026 | B41: 663 | C41: 2026-952 | D41: 1400 | E41: PSC | F41: =IF(E41<>"",VLOOKUP(E41,CODE!$B$2:$C$11,2,0),"") -> PSBC - CHECKING | G41: 21016 | H41: =IF(G41<>"",VLOOKUP(G41,COA!$A$3:$G$1048576,2,0),"") -> Unearned Revenue - OPS | I41: New Sicayab | J41: =IF(I41<>"",VLOOKUP(I41,'CUSTOMER LISTS'!$B$3:$E$1048576,2,0),"") -> FAME GAS REFILLING STATION | K41: =IF(I41<>"",VLOOKUP(I41,'CUSTOMER LISTS'!$B$3:$E$1048576,3,0),"") -> FERNANDO DELA ROSA PARAN | L41: =IF(I41<>"",VLOOKUP(I41,'CUSTOMER LISTS'!$B$3:$E$1048576,4,0),"") -> BRGY. NEW SICAYAB, POLANCO, ZAMBOANGA DEL NORTE | M41: 761 | N41: =IF(M41<>"",VLOOKUP(M41,'PRODUCT & SERVICES'!$O:$P,2,0),"") -> Others ( Pls. Specify ) | Q41: RECALIBRATION
A42: 04/13/2026 | B42: 664 | C42: 2026-953 | D42: 3500 | E42: RCS | F42: =IF(E42<>"",VLOOKUP(E42,CODE!$B$2:$C$11,2,0),"") -> RCBC -SAVINGS | G42: 43016 | H42: =IF(G42<>"",VLOOKUP(G42,COA!$A$3:$G$1048576,2,0),"") -> Job Orders | I42: New Sicayab | J42: =IF(I42<>"",VLOOKUP(I42,'CUSTOMER LISTS'!$B$3:$E$1048576,2,0),"") -> FAME GAS REFILLING STATION | K42: =IF(I42<>"",VLOOKUP(I42,'CUSTOMER LISTS'!$B$3:$E$1048576,3,0),"") -> FERNANDO DELA ROSA PARAN | L42: =IF(I42<>"",VLOOKUP(I42,'CUSTOMER LISTS'!$B$3:$E$1048576,4,0),"") -> BRGY. NEW SICAYAB, POLANCO, ZAMBOANGA DEL NORTE | M42: 721 | N42: =IF(M42<>"",VLOOKUP(M42,'PRODUCT & SERVICES'!$O:$P,2,0),"") -> Job Order | Q42: CALIBRATION; DISPENSE RELOCATION | U42: 04/13/2026
A43: 04/13/2026 | B43: 665 | C43: 2026-954 | D43: 10333.34 | E43: PNC | F43: =IF(E43<>"",VLOOKUP(E43,CODE!$B$2:$C$11,2,0),"") -> PNB - CHECKING | G43: 12013 | H43: =IF(G43<>"",VLOOKUP(G43,COA!$A$3:$G$1048576,2,0),"") -> A/Receivables - Installment-DMIE | I43: Balamban Mahayag | J43: =IF(I43<>"",VLOOKUP(I43,'CUSTOMER LISTS'!$B$3:$E$1048576,2,0),"") -> MMN GAS STATION | K43: =IF(I43<>"",VLOOKUP(I43,'CUSTOMER LISTS'!$B$3:$E$1048576,3,0),"") -> MARY JANE RESILOSA PAUSANOS | L43: =IF(I43<>"",VLOOKUP(I43,'CUSTOMER LISTS'!$B$3:$E$1048576,4,0),"") -> BRGY. BAG-ONG BALAMBAN, MAHAYAG, ZAMBOANGA DEL SUR | M43: 761 | N43: =IF(M43<>"",VLOOKUP(M43,'PRODUCT & SERVICES'!$O:$P,2,0),"") -> Others ( Pls. Specify ) | Q43: FULL PAYMENT ON TRANSFER PUMP (INSTALLMENT) | R43: DMIE
A44: 04/13/2026 | B44: 666 | C44: 2026-955 | D44: 2050 | E44: FVC | F44: =IF(E44<>"",VLOOKUP(E44,CODE!$B$2:$C$11,2,0),"") -> FIRST VALLEY -CHECKING | G44: 21016 | H44: =IF(G44<>"",VLOOKUP(G44,COA!$A$3:$G$1048576,2,0),"") -> Unearned Revenue - OPS | I44: Dumingag Bulilit | J44: =IF(I44<>"",VLOOKUP(I44,'CUSTOMER LISTS'!$B$3:$E$1048576,2,0),"") -> K2J2 GAS REFILLING STATION | K44: =IF(I44<>"",VLOOKUP(I44,'CUSTOMER LISTS'!$B$3:$E$1048576,3,0),"") -> JENIE FE BALOGBOG ALINSUG | L44: =IF(I44<>"",VLOOKUP(I44,'CUSTOMER LISTS'!$B$3:$E$1048576,4,0),"") -> BRGY. SAN PEDRO, DUMINGAG, ZAMBOANGA DEL SUR | M44: 712 | N44: =IF(M44<>"",VLOOKUP(M44,'PRODUCT & SERVICES'!$O:$P,2,0),"") -> Sea-Oil | O44: 1 BOX | P44: BRAKE FLUID 300ML | Q44: FULL PAYMENT ON PURCHASED ITEM | R44: OPS | S44: 2026-047 | T44: 46128
A45: 04/13/2026 | B45: 666 | C45: 2026-955 | D45: 8880 | E45: FVC | F45: =IF(E45<>"",VLOOKUP(E45,CODE!$B$2:$C$11,2,0),"") -> FIRST VALLEY -CHECKING | G45: 21016 | H45: =IF(G45<>"",VLOOKUP(G45,COA!$A$3:$G$1048576,2,0),"") -> Unearned Revenue - OPS | I45: Dumingag Bulilit | J45: =IF(I45<>"",VLOOKUP(I45,'CUSTOMER LISTS'!$B$3:$E$1048576,2,0),"") -> K2J2 GAS REFILLING STATION | K45: =IF(I45<>"",VLOOKUP(I45,'CUSTOMER LISTS'!$B$3:$E$1048576,3,0),"") -> JENIE FE BALOGBOG ALINSUG | L45: =IF(I45<>"",VLOOKUP(I45,'CUSTOMER LISTS'!$B$3:$E$1048576,4,0),"") -> BRGY. SAN PEDRO, DUMINGAG, ZAMBOANGA DEL SUR | M45: 712 | N45: =IF(M45<>"",VLOOKUP(M45,'PRODUCT & SERVICES'!$O:$P,2,0),"") -> Sea-Oil | O45: 2 BOXES | P45: GEO SUPREME 1L X 12 | Q45: FULL PAYMENT ON PURCHASED ITEM | R45: OPS | S45: 2026-047 | T45: 46128
A46: 04/13/2026 | B46: 666 | C46: 2026-955 | D46: 4628 | E46: FVC | F46: =IF(E46<>"",VLOOKUP(E46,CODE!$B$2:$C$11,2,0),"") -> FIRST VALLEY -CHECKING | G46: 21016 | H46: =IF(G46<>"",VLOOKUP(G46,COA!$A$3:$G$1048576,2,0),"") -> Unearned Revenue - OPS | I46: Dumingag Bulilit | J46: =IF(I46<>"",VLOOKUP(I46,'CUSTOMER LISTS'!$B$3:$E$1048576,2,0),"") -> K2J2 GAS REFILLING STATION | K46: =IF(I46<>"",VLOOKUP(I46,'CUSTOMER LISTS'!$B$3:$E$1048576,3,0),"") -> JENIE FE BALOGBOG ALINSUG | L46: =IF(I46<>"",VLOOKUP(I46,'CUSTOMER LISTS'!$B$3:$E$1048576,4,0),"") -> BRGY. SAN PEDRO, DUMINGAG, ZAMBOANGA DEL SUR | M46: 712 | N46: =IF(M46<>"",VLOOKUP(M46,'PRODUCT & SERVICES'!$O:$P,2,0),"") -> Sea-Oil | O46: 2 BOXES | P46: COOLANT 1L X 12 | Q46: FULL PAYMENT ON PURCHASED ITEM | R46: OPS | S46: 2026-047 | T46: 46128
A47: 04/13/2026 | B47: 667 | C47: 2026-956 | D47: 1400 | E47: PSC | F47: =IF(E47<>"",VLOOKUP(E47,CODE!$B$2:$C$11,2,0),"") -> PSBC - CHECKING | G47: 21016 | H47: =IF(G47<>"",VLOOKUP(G47,COA!$A$3:$G$1048576,2,0),"") -> Unearned Revenue - OPS | I47: Balagon Siay | J47: =IF(I47<>"",VLOOKUP(I47,'CUSTOMER LISTS'!$B$3:$E$1048576,2,0),"") -> VASH FUEL REFILLING STATION | K47: =IF(I47<>"",VLOOKUP(I47,'CUSTOMER LISTS'!$B$3:$E$1048576,3,0),"") -> JHOANNE SHANE MARIE ESMORES AGLOBO | L47: =IF(I47<>"",VLOOKUP(I47,'CUSTOMER LISTS'!$B$3:$E$1048576,4,0),"") -> BRGY. BALAGON, SIAY, ZAMBOANGA SIBUGAY | M47: 761 | N47: =IF(M47<>"",VLOOKUP(M47,'PRODUCT & SERVICES'!$O:$P,2,0),"") -> Others ( Pls. Specify ) | Q47: RECALIBRATION | R47: OPS
A48: 04/14/2026 | B48: 668 | C48: 2026-957 | D48: 2500 | E48: PSS | F48: =IF(E48<>"",VLOOKUP(E48,CODE!$B$2:$C$11,2,0),"") -> PSBC- SAVINGS | G48: 21016 | H48: =IF(G48<>"",VLOOKUP(G48,COA!$A$3:$G$1048576,2,0),"") -> Unearned Revenue - OPS | I48: Mucas | J48: =IF(I48<>"",VLOOKUP(I48,'CUSTOMER LISTS'!$B$3:$E$1048576,2,0),"") -> RM GASOLINE STATION | K48: =IF(I48<>"",VLOOKUP(I48,'CUSTOMER LISTS'!$B$3:$E$1048576,3,0),"") -> HAMIR GUMANDOL JAAPAL | L48: =IF(I48<>"",VLOOKUP(I48,'CUSTOMER LISTS'!$B$3:$E$1048576,4,0),"") -> BRGY. MUCAS, SALUG, ZAMBONGA DEL NORTE | M48: 2223 | N48: =IF(M48<>"",VLOOKUP(M48,'PRODUCT & SERVICES'!$O:$P,2,0),"") -> Nozzle | O48: 1 PC | Q48: FULL PAYMENT ON PURCHASED ITEM
A49: 04/15/2026 | B49: 669 | C49: 2026-958 | D49: 1400 | E49: FVC | F49: =IF(E49<>"",VLOOKUP(E49,CODE!$B$2:$C$11,2,0),"") -> FIRST VALLEY -CHECKING | G49: 21016 | H49: =IF(G49<>"",VLOOKUP(G49,COA!$A$3:$G$1048576,2,0),"") -> Unearned Revenue - OPS | I49: Lower Landing | J49: =IF(I49<>"",VLOOKUP(I49,'CUSTOMER LISTS'!$B$3:$E$1048576,2,0),"") -> TANAKAMI GAS STATION | K49: =IF(I49<>"",VLOOKUP(I49,'CUSTOMER LISTS'!$B$3:$E$1048576,3,0),"") -> WEDILYN ONRADA ROSALES | L49: =IF(I49<>"",VLOOKUP(I49,'CUSTOMER LISTS'!$B$3:$E$1048576,4,0),"") -> BRGY. LOWER LANDING, DUMINGAG, ZAMBOANGA DEL SUR | M49: 761 | N49: =IF(M49<>"",VLOOKUP(M49,'PRODUCT & SERVICES'!$O:$P,2,0),"") -> Others ( Pls. Specify ) | O49: 1 PC | Q49: RECALIBRATION | R49: OPS
A50: 04/15/2026 | B50: 670 | C50: 2026-959 | D50: 1400 | E50: FVC | F50: =IF(E50<>"",VLOOKUP(E50,CODE!$B$2:$C$11,2,0),"") -> FIRST VALLEY -CHECKING | G50: 21016 | H50: =IF(G50<>"",VLOOKUP(G50,COA!$A$3:$G$1048576,2,0),"") -> Unearned Revenue - OPS | I50: Valencia | J50: =IF(I50<>"",VLOOKUP(I50,'CUSTOMER LISTS'!$B$3:$E$1048576,2,0),"") -> CMT' FUEL STATION | K50: =IF(I50<>"",VLOOKUP(I50,'CUSTOMER LISTS'!$B$3:$E$1048576,3,0),"") -> FEBRA PACALIOGA ENANORIA | L50: =IF(I50<>"",VLOOKUP(I50,'CUSTOMER LISTS'!$B$3:$E$1048576,4,0),"") -> BRGY. VALENCIA, DUMINGAG, ZAMBOANGA DEL SUR | M50: 761 | N50: =IF(M50<>"",VLOOKUP(M50,'PRODUCT & SERVICES'!$O:$P,2,0),"") -> Others ( Pls. Specify ) | O50: 1 PC | Q50: RECALIBRATION | R50: OPS
A51: 04/16/2026 | B51: 671 | C51: 2026-960 | D51: 1400 | E51: PSS | F51: =IF(E51<>"",VLOOKUP(E51,CODE!$B$2:$C$11,2,0),"") -> PSBC- SAVINGS | G51: 21016 | H51: =IF(G51<>"",VLOOKUP(G51,COA!$A$3:$G$1048576,2,0),"") -> Unearned Revenue - OPS | I51: Del Pilar | J51: =IF(I51<>"",VLOOKUP(I51,'CUSTOMER LISTS'!$B$3:$E$1048576,2,0),"") -> ARLEGUI FUEL REFILLING STATION | K51: =IF(I51<>"",VLOOKUP(I51,'CUSTOMER LISTS'!$B$3:$E$1048576,3,0),"") -> SANDY LOU TRANSMIL ARLEGUI | L51: =IF(I51<>"",VLOOKUP(I51,'CUSTOMER LISTS'!$B$3:$E$1048576,4,0),"") -> BRGY. DEL PILAR, PIÑAN, ZAMBOANGA DEL NORTE | M51: 761 | N51: =IF(M51<>"",VLOOKUP(M51,'PRODUCT & SERVICES'!$O:$P,2,0),"") -> Others ( Pls. Specify ) | O51: 1 PC | Q51: RECALIBRATION | R51: OPS | S51: 2026-00106
A52: 04/16/2026 | B52: 672 | C52: 2026-961 | D52: 1400 | E52: PSS | F52: =IF(E52<>"",VLOOKUP(E52,CODE!$B$2:$C$11,2,0),"") -> PSBC- SAVINGS | G52: 21016 | H52: =IF(G52<>"",VLOOKUP(G52,COA!$A$3:$G$1048576,2,0),"") -> Unearned Revenue - OPS | I52: Madalag | J52: =IF(I52<>"",VLOOKUP(I52,'CUSTOMER LISTS'!$B$3:$E$1048576,2,0),"") -> FUELGO GAS REFILLING STATION | K52: =IF(I52<>"",VLOOKUP(I52,'CUSTOMER LISTS'!$B$3:$E$1048576,3,0),"") -> RODMAR VERTUDEZ FUEGO | L52: =IF(I52<>"",VLOOKUP(I52,'CUSTOMER LISTS'!$B$3:$E$1048576,4,0),"") -> BRGY. MADALAG, JOSE DALMAN , ZAMBOANGA DEL NORTE | M52: 761 | N52: =IF(M52<>"",VLOOKUP(M52,'PRODUCT & SERVICES'!$O:$P,2,0),"") -> Others ( Pls. Specify ) | O52: 1 PC | Q52: RECALIBRATION | R52: OPS
A53: 04/17/2026 | B53: 673 | C53: 2026-962 | D53: 5300 | E53: EWC | F53: =IF(E53<>"",VLOOKUP(E53,CODE!$B$2:$C$11,2,0),"") -> EASTWEST-CHECKING | G53: 21023 | H53: =IF(G53<>"",VLOOKUP(G53,COA!$A$3:$G$1048576,2,0),"") -> Unearned Revenue - DMIE | I53: Dicayo | J53: =IF(I53<>"",VLOOKUP(I53,'CUSTOMER LISTS'!$B$3:$E$1048576,2,0),"") -> MJ HABAGAT GAS STATION | K53: =IF(I53<>"",VLOOKUP(I53,'CUSTOMER LISTS'!$B$3:$E$1048576,3,0),"") -> THERESA MEE SARENAS HABAGAT | L53: =IF(I53<>"",VLOOKUP(I53,'CUSTOMER LISTS'!$B$3:$E$1048576,4,0),"") -> BRGY. DAANGLUNGSOD, KATIPUNAN, ZAMBOANGA DEL NORTE | M53: 2313 | N53: =IF(M53<>"",VLOOKUP(M53,'PRODUCT & SERVICES'!$O:$P,2,0),"") -> Other Calibration Buckets | Q53: CALIBRATION BUCKET WITH CERTIFICATE | R53: OPS
A54: 04/20/2026 | B54: 674 | C54: 2026-963 | D54: 1400 | E54: PSS | F54: =IF(E54<>"",VLOOKUP(E54,CODE!$B$2:$C$11,2,0),"") -> PSBC- SAVINGS | G54: 21016 | H54: =IF(G54<>"",VLOOKUP(G54,COA!$A$3:$G$1048576,2,0),"") -> Unearned Revenue - OPS | I54: Siari | J54: =IF(I54<>"",VLOOKUP(I54,'CUSTOMER LISTS'!$B$3:$E$1048576,2,0),"") -> GAZ-N-GO FUEL STATION | K54: =IF(I54<>"",VLOOKUP(I54,'CUSTOMER LISTS'!$B$3:$E$1048576,3,0),"") -> GESELLE GLORIAN BAYAWA | L54: =IF(I54<>"",VLOOKUP(I54,'CUSTOMER LISTS'!$B$3:$E$1048576,4,0),"") -> BRGY. SIARI, SINDANGAN, ZAMBOANGA DEL NORTE | M54: 761 | N54: =IF(M54<>"",VLOOKUP(M54,'PRODUCT & SERVICES'!$O:$P,2,0),"") -> Others ( Pls. Specify ) | O54: 1 PC | Q54: RECALIBRATION | R54: OPS
A55: 04/21/2026 | B55: 675 | C55: 2026-964 | D55: 1400 | E55: PSS | F55: =IF(E55<>"",VLOOKUP(E55,CODE!$B$2:$C$11,2,0),"") -> PSBC- SAVINGS | G55: 21016 | H55: =IF(G55<>"",VLOOKUP(G55,COA!$A$3:$G$1048576,2,0),"") -> Unearned Revenue - OPS | I55: Gampis | J55: =IF(I55<>"",VLOOKUP(I55,'CUSTOMER LISTS'!$B$3:$E$1048576,2,0),"") -> AM-MON FUEL STATION | K55: =IF(I55<>"",VLOOKUP(I55,'CUSTOMER LISTS'!$B$3:$E$1048576,3,0),"") -> LUCILLE MANANQUIL SINARILLOS | L55: =IF(I55<>"",VLOOKUP(I55,'CUSTOMER LISTS'!$B$3:$E$1048576,4,0),"") -> BRGY. SICAYAB, DIPOLOG CITY, ZAMBOANGA DEL NORTE | M55: 761 | N55: =IF(M55<>"",VLOOKUP(M55,'PRODUCT & SERVICES'!$O:$P,2,0),"") -> Others ( Pls. Specify ) | O55: 1 PC | Q55: RECALIBRATION | R55: OPS
A56: 04/23/2026 | B56: 676 | C56: 2026-965 | D56: 150 | E56: PSS | F56: =IF(E56<>"",VLOOKUP(E56,CODE!$B$2:$C$11,2,0),"") -> PSBC- SAVINGS | G56: 43046 | H56: =IF(G56<>"",VLOOKUP(G56,COA!$A$3:$G$1048576,2,0),"") -> Miscellaneous Income - OPS | I56: Dona Josefa | J56: =IF(I56<>"",VLOOKUP(I56,'CUSTOMER LISTS'!$B$3:$E$1048576,2,0),"") -> PATRICK & BRYLE FUEL REFILLING STATION | K56: =IF(I56<>"",VLOOKUP(I56,'CUSTOMER LISTS'!$B$3:$E$1048576,3,0),"") -> BOB DALMAN PAGENTE | L56: =IF(I56<>"",VLOOKUP(I56,'CUSTOMER LISTS'!$B$3:$E$1048576,4,0),"") -> BRGY. DOÑA JOSEFA, SINDANGAN, ZAMBOANGA DEL NORTE | M56: 761 | N56: =IF(M56<>"",VLOOKUP(M56,'PRODUCT & SERVICES'!$O:$P,2,0),"") -> Others ( Pls. Specify ) | O56: 1 SET | Q56: STICKER | R56: OPS | U56: 04/23/2026
A57: 04/23/2026 | B57: 677 | C57: 2026-966 | D57: 322844.5 | E57: EWC | F57: =IF(E57<>"",VLOOKUP(E57,CODE!$B$2:$C$11,2,0),"") -> EASTWEST-CHECKING | G57: 51163 | H57: =IF(G57<>"",VLOOKUP(G57,COA!$A$3:$G$1048576,2,0),"") -> COGS - Other DMIE | I57: KELLY HUNG | J57: =IF(I57<>"",VLOOKUP(I57,'CUSTOMER LISTS'!$B$3:$E$1048576,2,0),"") -> KELLY HUNG | K57: =IF(I57<>"",VLOOKUP(I57,'CUSTOMER LISTS'!$B$3:$E$1048576,3,0),"") -> KELLY HUNG | L57: =IF(I57<>"",VLOOKUP(I57,'CUSTOMER LISTS'!$B$3:$E$1048576,4,0),"") -> BRGY. GALAS, DIPOLOG CITY | M57: 761 | N57: =IF(M57<>"",VLOOKUP(M57,'PRODUCT & SERVICES'!$O:$P,2,0),"") -> Others ( Pls. Specify ) | Q57: 8 AGT EIGHT STP PORTABLE FUEL DISPENSER | S57: #0007 | T57: 46114 | U57: N/A
A58: 04/23/2026 | B58: 678 | C58: 2026-967 | D58: 2500 | E58: PNC | F58: =IF(E58<>"",VLOOKUP(E58,CODE!$B$2:$C$11,2,0),"") -> PNB - CHECKING | G58: 43016 | H58: =IF(G58<>"",VLOOKUP(G58,COA!$A$3:$G$1048576,2,0),"") -> Job Orders | I58: Compra Liloy | J58: =IF(I58<>"",VLOOKUP(I58,'CUSTOMER LISTS'!$B$3:$E$1048576,2,0),"") -> K.M. GAS REFILLING STATION | K58: =IF(I58<>"",VLOOKUP(I58,'CUSTOMER LISTS'!$B$3:$E$1048576,3,0),"") -> MANUEL LUCANAS DELOS SANTOS JR. | L58: =IF(I58<>"",VLOOKUP(I58,'CUSTOMER LISTS'!$B$3:$E$1048576,4,0),"") -> BRGY. COMPRA, LILOY, ZAMBOANGA DEL NORTE | M58: 721 | N58: =IF(M58<>"",VLOOKUP(M58,'PRODUCT & SERVICES'!$O:$P,2,0),"") -> Job Order | Q58: CALIBRATION 3 PUMPS (500 EACH); LABOR & TRANSPORTATION | U58: 04/23/2026
A59: 04/24/2026 | B59: 679 | C59: 2026-968 | D59: 1400 | E59: PSS | F59: =IF(E59<>"",VLOOKUP(E59,CODE!$B$2:$C$11,2,0),"") -> PSBC- SAVINGS | G59: 21016 | H59: =IF(G59<>"",VLOOKUP(G59,COA!$A$3:$G$1048576,2,0),"") -> Unearned Revenue - OPS | I59: Ilaya | J59: =IF(I59<>"",VLOOKUP(I59,'CUSTOMER LISTS'!$B$3:$E$1048576,2,0),"") -> 4J'S MICRO GAS REFILLING STATION | K59: =IF(I59<>"",VLOOKUP(I59,'CUSTOMER LISTS'!$B$3:$E$1048576,3,0),"") -> HEPHER CALASANG BAEL | L59: =IF(I59<>"",VLOOKUP(I59,'CUSTOMER LISTS'!$B$3:$E$1048576,4,0),"") -> BRGY. ILAYA, DAPITAN CITY, ZAMBOANGA DEL NORTE | M59: 761 | N59: =IF(M59<>"",VLOOKUP(M59,'PRODUCT & SERVICES'!$O:$P,2,0),"") -> Others ( Pls. Specify ) | O59: 1 PC | Q59: RECALIBRATION | R59: OPS
A60: 04/25/2026 | B60: 680 | C60: 2026-969 | D60: 500 | E60: RCS | F60: =IF(E60<>"",VLOOKUP(E60,CODE!$B$2:$C$11,2,0),"") -> RCBC -SAVINGS | G60: 43016 | H60: =IF(G60<>"",VLOOKUP(G60,COA!$A$3:$G$1048576,2,0),"") -> Job Orders | I60: VIZPA-BARCELONA | J60: =IF(I60<>"",VLOOKUP(I60,'CUSTOMER LISTS'!$B$3:$E$1048576,2,0),"") -> VIZPA GAS STATION | K60: =IF(I60<>"",VLOOKUP(I60,'CUSTOMER LISTS'!$B$3:$E$1048576,3,0),"") -> 0 | L60: =IF(I60<>"",VLOOKUP(I60,'CUSTOMER LISTS'!$B$3:$E$1048576,4,0),"") -> BRGY. BARCELONA, DAPITAN CITY | M60: 721 | N60: =IF(M60<>"",VLOOKUP(M60,'PRODUCT & SERVICES'!$O:$P,2,0),"") -> Job Order | Q60: MISCELLANEOUS INCOME -OTHER REPAIRS
A61: 04/28/2026 | B61: 681 | C61: 2026-970 | D61: 1400 | E61: PSS | F61: =IF(E61<>"",VLOOKUP(E61,CODE!$B$2:$C$11,2,0),"") -> PSBC- SAVINGS | G61: 21016 | H61: =IF(G61<>"",VLOOKUP(G61,COA!$A$3:$G$1048576,2,0),"") -> Unearned Revenue - OPS | I61: Mucas | J61: =IF(I61<>"",VLOOKUP(I61,'CUSTOMER LISTS'!$B$3:$E$1048576,2,0),"") -> RM GASOLINE STATION | K61: =IF(I61<>"",VLOOKUP(I61,'CUSTOMER LISTS'!$B$3:$E$1048576,3,0),"") -> HAMIR GUMANDOL JAAPAL | L61: =IF(I61<>"",VLOOKUP(I61,'CUSTOMER LISTS'!$B$3:$E$1048576,4,0),"") -> BRGY. MUCAS, SALUG, ZAMBONGA DEL NORTE | M61: 761 | N61: =IF(M61<>"",VLOOKUP(M61,'PRODUCT & SERVICES'!$O:$P,2,0),"") -> Others ( Pls. Specify ) | O61: 1 PC | Q61: RECALIBRATION | R61: OPS
A62: 04/28/2026 | B62: 682 | C62: 2026-971 | D62: 1400 | E62: PSS | F62: =IF(E62<>"",VLOOKUP(E62,CODE!$B$2:$C$11,2,0),"") -> PSBC- SAVINGS | G62: 21016 | H62: =IF(G62<>"",VLOOKUP(G62,COA!$A$3:$G$1048576,2,0),"") -> Unearned Revenue - OPS | I62: Palandok | J62: =IF(I62<>"",VLOOKUP(I62,'CUSTOMER LISTS'!$B$3:$E$1048576,2,0),"") -> KJ FUEL REFILLING STATION | K62: =IF(I62<>"",VLOOKUP(I62,'CUSTOMER LISTS'!$B$3:$E$1048576,3,0),"") -> MARCOS MABANSAG ARAGON | L62: =IF(I62<>"",VLOOKUP(I62,'CUSTOMER LISTS'!$B$3:$E$1048576,4,0),"") -> BRGY. PALANDOK, LEON POSTIGO, ZAMBOANGA DEL NORTE | M62: 761 | N62: =IF(M62<>"",VLOOKUP(M62,'PRODUCT & SERVICES'!$O:$P,2,0),"") -> Others ( Pls. Specify ) | O62: 1 PC | Q62: RECALIBRATION | R62: OPS
A63: 04/30/2026 | B63: 683 | C63: 2026-972 | D63: 1400 | E63: PSS | F63: =IF(E63<>"",VLOOKUP(E63,CODE!$B$2:$C$11,2,0),"") -> PSBC- SAVINGS | G63: 21016 | H63: =IF(G63<>"",VLOOKUP(G63,COA!$A$3:$G$1048576,2,0),"") -> Unearned Revenue - OPS | I63: Villahermosa | J63: =IF(I63<>"",VLOOKUP(I63,'CUSTOMER LISTS'!$B$3:$E$1048576,2,0),"") -> CM-POWER FUEL REFILLING STATION | K63: =IF(I63<>"",VLOOKUP(I63,'CUSTOMER LISTS'!$B$3:$E$1048576,3,0),"") -> CHARLENE ESTRADA MANDANTES | L63: =IF(I63<>"",VLOOKUP(I63,'CUSTOMER LISTS'!$B$3:$E$1048576,4,0),"") -> BRGY. VILLAHERMOSA, POLANCO, ZAMBOANGA DEL NORTE | M63: 761 | N63: =IF(M63<>"",VLOOKUP(M63,'PRODUCT & SERVICES'!$O:$P,2,0),"") -> Others ( Pls. Specify ) | O63: 1 PC | Q63: RECALIBRATION | R63: OPS
A64: 04/30/2026 | B64: 684 | C64: 2026-973 | D64: 9445 | E64: CBS | F64: =IF(E64<>"",VLOOKUP(E64,CODE!$B$2:$C$11,2,0),"") -> CHINA BANK - SAVINGS | G64: 43026 | H64: =IF(G64<>"",VLOOKUP(G64,COA!$A$3:$G$1048576,2,0),"") -> Service Income | I64: Palandok BULILIT | J64: =IF(I64<>"",VLOOKUP(I64,'CUSTOMER LISTS'!$B$3:$E$1048576,2,0),"") -> SR GAS STATION | K64: =IF(I64<>"",VLOOKUP(I64,'CUSTOMER LISTS'!$B$3:$E$1048576,3,0),"") -> RADHATA SALBANI HAMBALI | L64: =IF(I64<>"",VLOOKUP(I64,'CUSTOMER LISTS'!$B$3:$E$1048576,4,0),"") -> BRGY. RIZON, BACUNGAN, ZAMBOANGA DEL NORTE | M64: 751 | N64: =IF(M64<>"",VLOOKUP(M64,'PRODUCT & SERVICES'!$O:$P,2,0),"") -> Other Services ( Pls. Specify ) | Q64: 50 % COC PROCESSING FEE
A65: 04/30/2026 | B65: 685 | C65: 2026-974 | D65: 9445 | E65: CBS | F65: =IF(E65<>"",VLOOKUP(E65,CODE!$B$2:$C$11,2,0),"") -> CHINA BANK - SAVINGS | G65: 43026 | H65: =IF(G65<>"",VLOOKUP(G65,COA!$A$3:$G$1048576,2,0),"") -> Service Income | I65: Caracol Salug | J65: =IF(I65<>"",VLOOKUP(I65,'CUSTOMER LISTS'!$B$3:$E$1048576,2,0),"") -> AZ FUEL REFILLING STATION | K65: =IF(I65<>"",VLOOKUP(I65,'CUSTOMER LISTS'!$B$3:$E$1048576,3,0),"") -> SALAHUDDIN AKIL HAMBALI | L65: =IF(I65<>"",VLOOKUP(I65,'CUSTOMER LISTS'!$B$3:$E$1048576,4,0),"") -> BRGY. CARACOL, SALUG, ZAMBOANGA DEL NORTE | M65: 751 | N65: =IF(M65<>"",VLOOKUP(M65,'PRODUCT & SERVICES'!$O:$P,2,0),"") -> Other Services ( Pls. Specify ) | Q65: 50 % COC PROCESSING FEE
A66: 04/30/2026 | B66: 686 | C66: 2026-975 | D66: 1400 | E66: PNC | F66: =IF(E66<>"",VLOOKUP(E66,CODE!$B$2:$C$11,2,0),"") -> PNB - CHECKING | G66: 21016 | H66: =IF(G66<>"",VLOOKUP(G66,COA!$A$3:$G$1048576,2,0),"") -> Unearned Revenue - OPS | I66: Suertes-Guitran | J66: =IF(I66<>"",VLOOKUP(I66,'CUSTOMER LISTS'!$B$3:$E$1048576,2,0),"") -> SUERTE GAS STATION | K66: =IF(I66<>"",VLOOKUP(I66,'CUSTOMER LISTS'!$B$3:$E$1048576,3,0),"") -> ALJUN LATA SUERTE | L66: =IF(I66<>"",VLOOKUP(I66,'CUSTOMER LISTS'!$B$3:$E$1048576,4,0),"") -> BRGY. GUITRAN, DUMINGAG, ZAMBOANGA DEL SUR | M66: 761 | N66: =IF(M66<>"",VLOOKUP(M66,'PRODUCT & SERVICES'!$O:$P,2,0),"") -> Others ( Pls. Specify ) | O66: 1 PC | Q66: RECALIBRATION
A67: 05/04/2026 | B67: 687 | C67: 2026-976 | D67: 450000 | E67: EWC | F67: =IF(E67<>"",VLOOKUP(E67,CODE!$B$2:$C$11,2,0),"") -> EASTWEST-CHECKING | G67: 21023 | H67: =IF(G67<>"",VLOOKUP(G67,COA!$A$3:$G$1048576,2,0),"") -> Unearned Revenue - DMIE | I67: SAPANGDALAGA | J67: =IF(I67<>"",VLOOKUP(I67,'CUSTOMER LISTS'!$B$3:$E$1048576,2,0),"") -> PHIL GAMZ GAS REFILLING STATION | K67: =IF(I67<>"",VLOOKUP(I67,'CUSTOMER LISTS'!$B$3:$E$1048576,3,0),"") -> CRYSTALL MAE PAUNDOG | L67: =IF(I67<>"",VLOOKUP(I67,'CUSTOMER LISTS'!$B$3:$E$1048576,4,0),"") -> BRGY. GUINABUT, SAPANGDALAGA, MISAMIS OCCIDENTAL | M67: 2217 | N67: =IF(M67<>"",VLOOKUP(M67,'PRODUCT & SERVICES'!$O:$P,2,0),"") -> 5.0 KL TSRO Standard Machine | Q67: FULL PAYMENT ON PURCHASED ITEM - 5KL MACHINE | R67: DMIE | S67: #000008 | T67: 46198
A68: 05/04/2026 | B68: 687 | C68: 2026-976 | D68: 35210 | E68: EWC | F68: =IF(E68<>"",VLOOKUP(E68,CODE!$B$2:$C$11,2,0),"") -> EASTWEST-CHECKING | G68: 21023 | H68: =IF(G68<>"",VLOOKUP(G68,COA!$A$3:$G$1048576,2,0),"") -> Unearned Revenue - DMIE | I68: SAPANGDALAGA | J68: =IF(I68<>"",VLOOKUP(I68,'CUSTOMER LISTS'!$B$3:$E$1048576,2,0),"") -> PHIL GAMZ GAS REFILLING STATION | K68: =IF(I68<>"",VLOOKUP(I68,'CUSTOMER LISTS'!$B$3:$E$1048576,3,0),"") -> CRYSTALL MAE PAUNDOG | L68: =IF(I68<>"",VLOOKUP(I68,'CUSTOMER LISTS'!$B$3:$E$1048576,4,0),"") -> BRGY. GUINABUT, SAPANGDALAGA, MISAMIS OCCIDENTAL | M68: 761 | N68: =IF(M68<>"",VLOOKUP(M68,'PRODUCT & SERVICES'!$O:$P,2,0),"") -> Others ( Pls. Specify ) | Q68: SHIPPING PARTICIPATION | R68: DMIE
A69: 05/04/2026 | B69: 688 | C69: 2026-977 | D69: 7485 | E69: KBS | F69: =IF(E69<>"",VLOOKUP(E69,CODE!$B$2:$C$11,2,0),"") -> KATIPUNAN BANK-SAVINGS | G69: 43026 | H69: =IF(G69<>"",VLOOKUP(G69,COA!$A$3:$G$1048576,2,0),"") -> Service Income | I69: Bajo Oroqueita | J69: =IF(I69<>"",VLOOKUP(I69,'CUSTOMER LISTS'!$B$3:$E$1048576,2,0),"") -> NONON'S FUEL STATION | K69: =IF(I69<>"",VLOOKUP(I69,'CUSTOMER LISTS'!$B$3:$E$1048576,3,0),"") -> CRISAN SABIJON HERNANE | L69: =IF(I69<>"",VLOOKUP(I69,'CUSTOMER LISTS'!$B$3:$E$1048576,4,0),"") -> BRGY. SAN VICENTE BAJO, OROQUIETA CITY, MISAMIS OCCIDENTAL | M69: 761 | N69: =IF(M69<>"",VLOOKUP(M69,'PRODUCT & SERVICES'!$O:$P,2,0),"") -> Others ( Pls. Specify ) | Q69: 50 % COC PROCESSING FEE | R69: OPS | U69: 05/04/2026
A70: 05/04/2026 | B70: 689 | C70: 2026-978 | D70: 7485 | E70: CBS | F70: =IF(E70<>"",VLOOKUP(E70,CODE!$B$2:$C$11,2,0),"") -> CHINA BANK - SAVINGS | G70: 43026 | H70: =IF(G70<>"",VLOOKUP(G70,COA!$A$3:$G$1048576,2,0),"") -> Service Income | I70: New Sicayab | J70: =IF(I70<>"",VLOOKUP(I70,'CUSTOMER LISTS'!$B$3:$E$1048576,2,0),"") -> FAME GAS REFILLING STATION | K70: =IF(I70<>"",VLOOKUP(I70,'CUSTOMER LISTS'!$B$3:$E$1048576,3,0),"") -> FERNANDO DELA ROSA PARAN | L70: =IF(I70<>"",VLOOKUP(I70,'CUSTOMER LISTS'!$B$3:$E$1048576,4,0),"") -> BRGY. NEW SICAYAB, POLANCO, ZAMBOANGA DEL NORTE | M70: 761 | N70: =IF(M70<>"",VLOOKUP(M70,'PRODUCT & SERVICES'!$O:$P,2,0),"") -> Others ( Pls. Specify ) | Q70: 50 % COC PROCESSING FEE | R70: OPS | U70: 05/04/2026
A71: 05/04/2026 | B71: 690 | C71: 2026-979 | D71: 7485 | E71: KBS | F71: =IF(E71<>"",VLOOKUP(E71,CODE!$B$2:$C$11,2,0),"") -> KATIPUNAN BANK-SAVINGS | G71: 43026 | H71: =IF(G71<>"",VLOOKUP(G71,COA!$A$3:$G$1048576,2,0),"") -> Service Income | I71: Villaflor-Len | J71: =IF(I71<>"",VLOOKUP(I71,'CUSTOMER LISTS'!$B$3:$E$1048576,2,0),"") -> LEN GASOLINE STATION | K71: =IF(I71<>"",VLOOKUP(I71,'CUSTOMER LISTS'!$B$3:$E$1048576,3,0),"") -> ARLENE EDIOS UBA | L71: =IF(I71<>"",VLOOKUP(I71,'CUSTOMER LISTS'!$B$3:$E$1048576,4,0),"") -> BRGY. VILLAFLOR, OROQUIETA CITY, MISAMIS OCCIDENTAL | M71: 761 | N71: =IF(M71<>"",VLOOKUP(M71,'PRODUCT & SERVICES'!$O:$P,2,0),"") -> Others ( Pls. Specify ) | Q71: 50 % COC PROCESSING FEE | R71: OPS | U71: 05/04/2026
A72: 05/04/2026 | B72: 691 | C72: 2026-980 | D72: 7485 | E72: CBS | F72: =IF(E72<>"",VLOOKUP(E72,CODE!$B$2:$C$11,2,0),"") -> CHINA BANK - SAVINGS | G72: 43026 | H72: =IF(G72<>"",VLOOKUP(G72,COA!$A$3:$G$1048576,2,0),"") -> Service Income | I72: Gampis | J72: =IF(I72<>"",VLOOKUP(I72,'CUSTOMER LISTS'!$B$3:$E$1048576,2,0),"") -> AM-MON FUEL STATION | K72: =IF(I72<>"",VLOOKUP(I72,'CUSTOMER LISTS'!$B$3:$E$1048576,3,0),"") -> LUCILLE MANANQUIL SINARILLOS | L72: =IF(I72<>"",VLOOKUP(I72,'CUSTOMER LISTS'!$B$3:$E$1048576,4,0),"") -> BRGY. SICAYAB, DIPOLOG CITY, ZAMBOANGA DEL NORTE | M72: 761 | N72: =IF(M72<>"",VLOOKUP(M72,'PRODUCT & SERVICES'!$O:$P,2,0),"") -> Others ( Pls. Specify ) | Q72: 50 % COC PROCESSING FEE | R72: OPS | U72: 05/04/2026
A73: 05/04/2026 | B73: 692 | C73: 2026-981 | D73: 7485 | E73: CBS | F73: =IF(E73<>"",VLOOKUP(E73,CODE!$B$2:$C$11,2,0),"") -> CHINA BANK - SAVINGS | G73: 43026 | H73: =IF(G73<>"",VLOOKUP(G73,COA!$A$3:$G$1048576,2,0),"") -> Service Income | I73: MUTIA-OROQUIETA | J73: =IF(I73<>"",VLOOKUP(I73,'CUSTOMER LISTS'!$B$3:$E$1048576,2,0),"") -> MUTIA RANGERS FUEL RETAILING | K73: =IF(I73<>"",VLOOKUP(I73,'CUSTOMER LISTS'!$B$3:$E$1048576,3,0),"") -> JULIE ANN CONING MUTIA | L73: =IF(I73<>"",VLOOKUP(I73,'CUSTOMER LISTS'!$B$3:$E$1048576,4,0),"") -> BRGY. DOLIPOS, BAJO, OROQUIETA CITY | M73: 761 | N73: =IF(M73<>"",VLOOKUP(M73,'PRODUCT & SERVICES'!$O:$P,2,0),"") -> Others ( Pls. Specify ) | Q73: 50 % COC PROCESSING FEE | R73: OPS | U73: 05/04/2026
A74: 05/04/2026 | B74: 693 | C74: 2026-982 | D74: 7485 | E74: CBS | F74: =IF(E74<>"",VLOOKUP(E74,CODE!$B$2:$C$11,2,0),"") -> CHINA BANK - SAVINGS | G74: 43026 | H74: =IF(G74<>"",VLOOKUP(G74,COA!$A$3:$G$1048576,2,0),"") -> Service Income | I74: Maralag | J74: =IF(I74<>"",VLOOKUP(I74,'CUSTOMER LISTS'!$B$3:$E$1048576,2,0),"") -> GUNIX GAS STATION | K74: =IF(I74<>"",VLOOKUP(I74,'CUSTOMER LISTS'!$B$3:$E$1048576,3,0),"") -> SEM UDTOHAN PANGASIAN | L74: =IF(I74<>"",VLOOKUP(I74,'CUSTOMER LISTS'!$B$3:$E$1048576,4,0),"") -> BRGY. MARALAG, DUMINGAG, ZAMBOANGA DEL SUR | M74: 761 | N74: =IF(M74<>"",VLOOKUP(M74,'PRODUCT & SERVICES'!$O:$P,2,0),"") -> Others ( Pls. Specify ) | Q74: 50 % COC PROCESSING FEE | R74: OPS | U74: 05/04/2026
A75: 05/04/2026 | B75: 694 | C75: 2026-983 | D75: 7485 | E75: CBS | F75: =IF(E75<>"",VLOOKUP(E75,CODE!$B$2:$C$11,2,0),"") -> CHINA BANK - SAVINGS | G75: 43026 | H75: =IF(G75<>"",VLOOKUP(G75,COA!$A$3:$G$1048576,2,0),"") -> Service Income | I75: San Antonio Titay | J75: =IF(I75<>"",VLOOKUP(I75,'CUSTOMER LISTS'!$B$3:$E$1048576,2,0),"") -> JMS FUEL REFILLING STATION | K75: =IF(I75<>"",VLOOKUP(I75,'CUSTOMER LISTS'!$B$3:$E$1048576,3,0),"") -> JESSA CAMAC ACAYLAR | L75: =IF(I75<>"",VLOOKUP(I75,'CUSTOMER LISTS'!$B$3:$E$1048576,4,0),"") -> BRGY. SAN ANTONIO, TITAY, ZAMBOANGA SIBUGAY | M75: 761 | N75: =IF(M75<>"",VLOOKUP(M75,'PRODUCT & SERVICES'!$O:$P,2,0),"") -> Others ( Pls. Specify ) | Q75: 50 % COC PROCESSING FEE | R75: OPS | U75: 05/04/2026
A76: 03/26/2026 | B76: 695 | C76: 2026-984 | D76: 150000 | E76: EWC | F76: =IF(E76<>"",VLOOKUP(E76,CODE!$B$2:$C$11,2,0),"") -> EASTWEST-CHECKING | G76: 21000 | H76: =IF(G76<>"",VLOOKUP(G76,COA!$A$3:$G$1048576,2,0),"") -> Unearned Revenue - DHPP | I76: Tamil Jrm | J76: =IF(I76<>"",VLOOKUP(I76,'CUSTOMER LISTS'!$B$3:$E$1048576,2,0),"") -> JRM FUEL REFILLING STATION | K76: =IF(I76<>"",VLOOKUP(I76,'CUSTOMER LISTS'!$B$3:$E$1048576,3,0),"") -> MELVA MACAPAZ NICOLAS | L76: =IF(I76<>"",VLOOKUP(I76,'CUSTOMER LISTS'!$B$3:$E$1048576,4,0),"") -> BRGY. TAMIL, JOSE DALMAN, ZAMBOANGA DEL NORTE | M76: 761 | N76: =IF(M76<>"",VLOOKUP(M76,'PRODUCT & SERVICES'!$O:$P,2,0),"") -> Others ( Pls. Specify ) | Q76: TANKER RELATED REPAIRS AND CONSTRUCTION | R76: OPS
A77: 05/04/2026 | B77: 696 | C77: 2026-985 | D77: 7485 | E77: CBS | F77: =IF(E77<>"",VLOOKUP(E77,CODE!$B$2:$C$11,2,0),"") -> CHINA BANK - SAVINGS | G77: 43026 | H77: =IF(G77<>"",VLOOKUP(G77,COA!$A$3:$G$1048576,2,0),"") -> Service Income | I77: Napo Dapitan | J77: =IF(I77<>"",VLOOKUP(I77,'CUSTOMER LISTS'!$B$3:$E$1048576,2,0),"") -> GIAN'S FUEL STATION | K77: =IF(I77<>"",VLOOKUP(I77,'CUSTOMER LISTS'!$B$3:$E$1048576,3,0),"") -> HELGREG LINGO TINNAE | L77: =IF(I77<>"",VLOOKUP(I77,'CUSTOMER LISTS'!$B$3:$E$1048576,4,0),"") -> BRGY. NAPO, DAPITAN CITY, ZAMBONGA DEL NORTE | M77: 761 | N77: =IF(M77<>"",VLOOKUP(M77,'PRODUCT & SERVICES'!$O:$P,2,0),"") -> Others ( Pls. Specify ) | Q77: 50 % COC PROCESSING FEE | R77: OPS | U77: 05/04/2026
A78: 05/07/2026 | B78: 697 | C78: 2026-986 | D78: 7485 | E78: CBS | F78: =IF(E78<>"",VLOOKUP(E78,CODE!$B$2:$C$11,2,0),"") -> CHINA BANK - SAVINGS | G78: 43026 | H78: =IF(G78<>"",VLOOKUP(G78,COA!$A$3:$G$1048576,2,0),"") -> Service Income | I78: San Pablo Sur | J78: =IF(I78<>"",VLOOKUP(I78,'CUSTOMER LISTS'!$B$3:$E$1048576,2,0),"") -> RHOIE GAS STATION | K78: =IF(I78<>"",VLOOKUP(I78,'CUSTOMER LISTS'!$B$3:$E$1048576,3,0),"") -> LEROY CAYASAN EGONIA | L78: =IF(I78<>"",VLOOKUP(I78,'CUSTOMER LISTS'!$B$3:$E$1048576,4,0),"") -> BRGY. SAGASAN, SAN PABLO, ZAMBOANGA DEL SUR | M78: 761 | N78: =IF(M78<>"",VLOOKUP(M78,'PRODUCT & SERVICES'!$O:$P,2,0),"") -> Others ( Pls. Specify ) | Q78: 50 % COC PROCESSING FEE | R78: OPS | U78: 05/04/2026
A79: 05/09/2026 | B79: 698 | C79: 2026-987 | D79: 1400 | E79: PSS | F79: =IF(E79<>"",VLOOKUP(E79,CODE!$B$2:$C$11,2,0),"") -> PSBC- SAVINGS | G79: 21016 | H79: =IF(G79<>"",VLOOKUP(G79,COA!$A$3:$G$1048576,2,0),"") -> Unearned Revenue - OPS | I79: CALAMBA | J79: =IF(I79<>"",VLOOKUP(I79,'CUSTOMER LISTS'!$B$3:$E$1048576,2,0),"") -> CALAMBA FUEL REFILLING STATION | K79: =IF(I79<>"",VLOOKUP(I79,'CUSTOMER LISTS'!$B$3:$E$1048576,3,0),"") -> RONAN CASTILLON | L79: =IF(I79<>"",VLOOKUP(I79,'CUSTOMER LISTS'!$B$3:$E$1048576,4,0),"") -> BRGY. MAGCAMIGUING, CALAMBA, ZAMBOANGA DEL NORTE | M79: 761 | N79: =IF(M79<>"",VLOOKUP(M79,'PRODUCT & SERVICES'!$O:$P,2,0),"") -> Others ( Pls. Specify ) | O79: 1 PC | Q79: RECALIBRATION | R79: OPS | S79: 2026-00104 | U79: 05/04/2026
A80: 05/09/2026 | B80: 699 | C80: 2026-988 | D80: 2500 | E80: RCS | F80: =IF(E80<>"",VLOOKUP(E80,CODE!$B$2:$C$11,2,0),"") -> RCBC -SAVINGS | G80: 21016 | H80: =IF(G80<>"",VLOOKUP(G80,COA!$A$3:$G$1048576,2,0),"") -> Unearned Revenue - OPS | I80: Sinuyak | J80: =IF(I80<>"",VLOOKUP(I80,'CUSTOMER LISTS'!$B$3:$E$1048576,2,0),"") -> GAS DISTRIBUTION SERVICES D-BROTHERS GASOLINAHAN | K80: =IF(I80<>"",VLOOKUP(I80,'CUSTOMER LISTS'!$B$3:$E$1048576,3,0),"") -> DEMOSTHENES SIARON CASTILLON SR. | L80: =IF(I80<>"",VLOOKUP(I80,'CUSTOMER LISTS'!$B$3:$E$1048576,4,0),"") -> BRGY. SINUYAK, KATIPUNAN, ZAMBOANGA DEL NORTE | M80: 2223 | N80: =IF(M80<>"",VLOOKUP(M80,'PRODUCT & SERVICES'!$O:$P,2,0),"") -> Nozzle | O80: 1 PC | Q80: FULL PAYMENT ON PURCHASED ITEM - NOZZLE | R80: OPS | S80: 2026-0049 | T80: 05/09/2026
A81: 05/09/2026 | B81: 699 | C81: 2026-988 | D81: 1500 | E81: RCS | F81: =IF(E81<>"",VLOOKUP(E81,CODE!$B$2:$C$11,2,0),"") -> RCBC -SAVINGS | G81: 43016 | H81: =IF(G81<>"",VLOOKUP(G81,COA!$A$3:$G$1048576,2,0),"") -> Job Orders | I81: Sinuyak | J81: =IF(I81<>"",VLOOKUP(I81,'CUSTOMER LISTS'!$B$3:$E$1048576,2,0),"") -> GAS DISTRIBUTION SERVICES D-BROTHERS GASOLINAHAN | L81: =IF(I81<>"",VLOOKUP(I81,'CUSTOMER LISTS'!$B$3:$E$1048576,4,0),"") -> BRGY. SINUYAK, KATIPUNAN, ZAMBOANGA DEL NORTE | M81: 721 | N81: =IF(M81<>"",VLOOKUP(M81,'PRODUCT & SERVICES'!$O:$P,2,0),"") -> Job Order | Q81: NOZZLE REPLACEMENT | R81: OPS | U81: 05/09/2026
A82: 05/12/2026 | B82: 700 | C82: 2026-989 | D82: 9445 | E82: CBS | F82: =IF(E82<>"",VLOOKUP(E82,CODE!$B$2:$C$11,2,0),"") -> CHINA BANK - SAVINGS | G82: 43026 | H82: =IF(G82<>"",VLOOKUP(G82,COA!$A$3:$G$1048576,2,0),"") -> Service Income | I82: Mandih | J82: =IF(I82<>"",VLOOKUP(I82,'CUSTOMER LISTS'!$B$3:$E$1048576,2,0),"") -> JANUAORYZA MICRO GAS STATION | K82: =IF(I82<>"",VLOOKUP(I82,'CUSTOMER LISTS'!$B$3:$E$1048576,3,0),"") -> RUFINO ANDUS MUKOD | L82: =IF(I82<>"",VLOOKUP(I82,'CUSTOMER LISTS'!$B$3:$E$1048576,4,0),"") -> BRGY. MANDIH, SINDANGAN, ZAMBOANGA DEL NORTE | M82: 761 | N82: =IF(M82<>"",VLOOKUP(M82,'PRODUCT & SERVICES'!$O:$P,2,0),"") -> Others ( Pls. Specify ) | Q82: 50 % COC PROCESSING FEE- LFRO | R82: OPS | U82: 05/12/2026
A83: 05/12/2026 | B83: 701 | C83: 2026-990 | D83: 5000 | E83: PNC | F83: =IF(E83<>"",VLOOKUP(E83,CODE!$B$2:$C$11,2,0),"") -> PNB - CHECKING | G83: 15000 | H83: =IF(G83<>"",VLOOKUP(G83,COA!$A$3:$G$1048576,2,0),"") -> Due from STPC - DHPP | I83: San Pedro bulilit | J83: SEVEN-TRENT PETROLEUM CORP. | K83: =IF(I83<>"",VLOOKUP(I83,'CUSTOMER LISTS'!$B$3:$E$1048576,3,0),"") -> TOM JERRY TIMBOL SAGARIO | L83: =IF(I83<>"",VLOOKUP(I83,'CUSTOMER LISTS'!$B$3:$E$1048576,4,0),"") -> BRGY. SAN PEDRO, DAPITAN, ZAMBOANGA DEL NORTE | M83: 761 | N83: =IF(M83<>"",VLOOKUP(M83,'PRODUCT & SERVICES'!$O:$P,2,0),"") -> Others ( Pls. Specify ) | Q83: PAYMENT FOR BILLING DTD 5/9/2026 - (FINANCIAL ASSISTANT TO THE BEREAVED FAMILY | R83: DHPP
A84: 05/12/2026 | B84: 702 | C84: 2026-991 | D84: 9445 | E84: CBS | F84: =IF(E84<>"",VLOOKUP(E84,CODE!$B$2:$C$11,2,0),"") -> CHINA BANK - SAVINGS | G84: 43026 | H84: =IF(G84<>"",VLOOKUP(G84,COA!$A$3:$G$1048576,2,0),"") -> Service Income | I84: Timan | J84: =IF(I84<>"",VLOOKUP(I84,'CUSTOMER LISTS'!$B$3:$E$1048576,2,0),"") -> CHUCK GAS REFILLING STATION | K84: =IF(I84<>"",VLOOKUP(I84,'CUSTOMER LISTS'!$B$3:$E$1048576,3,0),"") -> MAREBEL VILLACURA HICALDE | L84: =IF(I84<>"",VLOOKUP(I84,'CUSTOMER LISTS'!$B$3:$E$1048576,4,0),"") -> BRGY. TIMAN, LILOY, ZAMBOANGA DEL NORTE | M84: 761 | N84: =IF(M84<>"",VLOOKUP(M84,'PRODUCT & SERVICES'!$O:$P,2,0),"") -> Others ( Pls. Specify ) | Q84: 50 % COC PROCESSING FEE | R84: OPS | U84: 05/12/2026
A85: 05/13/2026 | B85: 703 | C85: 2026-992 | D85: 1400 | E85: PSS | F85: =IF(E85<>"",VLOOKUP(E85,CODE!$B$2:$C$11,2,0),"") -> PSBC- SAVINGS | G85: 21016 | H85: =IF(G85<>"",VLOOKUP(G85,COA!$A$3:$G$1048576,2,0),"") -> Unearned Revenue - OPS | I85: Dampalan DAPITAN | J85: =IF(I85<>"",VLOOKUP(I85,'CUSTOMER LISTS'!$B$3:$E$1048576,2,0),"") -> RAMAD FUEL REFILLING STATION | K85: =IF(I85<>"",VLOOKUP(I85,'CUSTOMER LISTS'!$B$3:$E$1048576,3,0),"") -> RAMIL QUIGUING ADANTE | L85: =IF(I85<>"",VLOOKUP(I85,'CUSTOMER LISTS'!$B$3:$E$1048576,4,0),"") -> BRGY. DAMPALAN, DAPITAN CITY, ZAMBOANGA DEL NORTE | M85: 761 | N85: =IF(M85<>"",VLOOKUP(M85,'PRODUCT & SERVICES'!$O:$P,2,0),"") -> Others ( Pls. Specify ) | O85: 1 PC | Q85: RECALIBRATION | R85: OPS | S85: 2026-00105
A86: 05/13/2026 | B86: 704 | C86: 2026-993 | D86: 2500 | E86: PSS | F86: =IF(E86<>"",VLOOKUP(E86,CODE!$B$2:$C$11,2,0),"") -> PSBC- SAVINGS | G86: 21016 | H86: =IF(G86<>"",VLOOKUP(G86,COA!$A$3:$G$1048576,2,0),"") -> Unearned Revenue - OPS | I86: Bato Plaridel | J86: =IF(I86<>"",VLOOKUP(I86,'CUSTOMER LISTS'!$B$3:$E$1048576,2,0),"") -> MARCUS FUEL STATION | K86: =IF(I86<>"",VLOOKUP(I86,'CUSTOMER LISTS'!$B$3:$E$1048576,3,0),"") -> MARICRIS FE MAGHINAY ARANDID | L86: =IF(I86<>"",VLOOKUP(I86,'CUSTOMER LISTS'!$B$3:$E$1048576,4,0),"") -> BRGY. BATO, PLARIDEL, MISAMIS OCCIDENTAL | M86: 761 | N86: =IF(M86<>"",VLOOKUP(M86,'PRODUCT & SERVICES'!$O:$P,2,0),"") -> Others ( Pls. Specify ) | O86: 1 PC | Q86: PAYMENT FOR RELAY | R86: OPS | S86: 2026-053 | T86: 46155
A87: 05/13/2026 | B87: 705 | C87: 2026-994 | D87: 165000 | E87: MBC | F87: =IF(E87<>"",VLOOKUP(E87,CODE!$B$2:$C$11,2,0),"") -> METROBANK-CHECKING | G87: 25500 | H87: =IF(G87<>"",VLOOKUP(G87,COA!$A$3:$G$1048576,2,0),"") -> Other Payables_Current - DHPP | I87: STPC-San Pedro | J87: =IF(I87<>"",VLOOKUP(I87,'CUSTOMER LISTS'!$B$3:$E$1048576,2,0),"") -> SEVEN-TRENT PETROLEUM CORP. | K87: =IF(I87<>"",VLOOKUP(I87,'CUSTOMER LISTS'!$B$3:$E$1048576,3,0),"") -> SEVEN-TRENT PETROLEUM CORP. | L87: =IF(I87<>"",VLOOKUP(I87,'CUSTOMER LISTS'!$B$3:$E$1048576,4,0),"") -> BRGY. SAN PEDRO, DAPITAN, ZAMBOANGA DEL NORTE | M87: 761 | N87: =IF(M87<>"",VLOOKUP(M87,'PRODUCT & SERVICES'!$O:$P,2,0),"") -> Others ( Pls. Specify ) | Q87: SHORT TERM LOAN | R87: DHPP | S87: NA | T87: NA | U87: NA
A88: 05/13/2026 | B88: 706 | C88: 2026-995 | D88: 7485 | E88: CBS | F88: =IF(E88<>"",VLOOKUP(E88,CODE!$B$2:$C$11,2,0),"") -> CHINA BANK - SAVINGS | G88: 43026 | H88: =IF(G88<>"",VLOOKUP(G88,COA!$A$3:$G$1048576,2,0),"") -> Service Income | I88: Lapuyan KLJ | J88: =IF(I88<>"",VLOOKUP(I88,'CUSTOMER LISTS'!$B$3:$E$1048576,2,0),"") -> ZAHRA'S GAS REFILLING STATION | K88: =IF(I88<>"",VLOOKUP(I88,'CUSTOMER LISTS'!$B$3:$E$1048576,3,0),"") -> ZAHRA KATE MENDIOLA | L88: =IF(I88<>"",VLOOKUP(I88,'CUSTOMER LISTS'!$B$3:$E$1048576,4,0),"") -> BRGY. POBLACION, LAPUYAN, ZAMBOANGA DEL SUR | M88: 761 | N88: =IF(M88<>"",VLOOKUP(M88,'PRODUCT & SERVICES'!$O:$P,2,0),"") -> Others ( Pls. Specify ) | Q88: 50 % COC PROCESSING FEE | R88: OPS | U88: 05/13/2026
A89: 05/15/2026 | B89: 707 | C89: 2026-996 | D89: 1200 | E89: EWC | F89: =IF(E89<>"",VLOOKUP(E89,CODE!$B$2:$C$11,2,0),"") -> EASTWEST-CHECKING | G89: 21023 | H89: =IF(G89<>"",VLOOKUP(G89,COA!$A$3:$G$1048576,2,0),"") -> Unearned Revenue - DMIE | I89: Palandok | J89: =IF(I89<>"",VLOOKUP(I89,'CUSTOMER LISTS'!$B$3:$E$1048576,2,0),"") -> KJ FUEL REFILLING STATION | K89: =IF(I89<>"",VLOOKUP(I89,'CUSTOMER LISTS'!$B$3:$E$1048576,3,0),"") -> MARCOS MABANSAG ARAGON | L89: =IF(I89<>"",VLOOKUP(I89,'CUSTOMER LISTS'!$B$3:$E$1048576,4,0),"") -> BRGY. PALANDOK, LEON POSTIGO, ZAMBOANGA DEL NORTE | M89: 311 | N89: =IF(M89<>"",VLOOKUP(M89,'PRODUCT & SERVICES'!$O:$P,2,0),"") -> Fuel Filter | O89: 1 PC | Q89: FULL PAYMENT ON PURCHASED ITEM | R89: DMIE | S89: 2026-054 | T89: 46157
A90: 05/15/2026 | B90: 708 | C90: 2026-997 | D90: 990 | E90: PSS | F90: =IF(E90<>"",VLOOKUP(E90,CODE!$B$2:$C$11,2,0),"") -> PSBC- SAVINGS | G90: 21016 | H90: =IF(G90<>"",VLOOKUP(G90,COA!$A$3:$G$1048576,2,0),"") -> Unearned Revenue - OPS | I90: Palandok | J90: =IF(I90<>"",VLOOKUP(I90,'CUSTOMER LISTS'!$B$3:$E$1048576,2,0),"") -> KJ FUEL REFILLING STATION | K90: =IF(I90<>"",VLOOKUP(I90,'CUSTOMER LISTS'!$B$3:$E$1048576,3,0),"") -> MARCOS MABANSAG ARAGON | L90: =IF(I90<>"",VLOOKUP(I90,'CUSTOMER LISTS'!$B$3:$E$1048576,4,0),"") -> BRGY. PALANDOK, LEON POSTIGO, ZAMBOANGA DEL NORTE | M90: 761 | N90: =IF(M90<>"",VLOOKUP(M90,'PRODUCT & SERVICES'!$O:$P,2,0),"") -> Others ( Pls. Specify ) | O90: 1 PC | Q90: CARBON BRASS | R90: OPS | S90: 2026-052 | T90: 46157
A91: 05/15/2026 | B91: 709 | C91: 2026-998 | D91: 1400 | E91: PSS | F91: =IF(E91<>"",VLOOKUP(E91,CODE!$B$2:$C$11,2,0),"") -> PSBC- SAVINGS | G91: 21016 | H91: =IF(G91<>"",VLOOKUP(G91,COA!$A$3:$G$1048576,2,0),"") -> Unearned Revenue - OPS | I91: Sitio Sapa Indian | J91: =IF(I91<>"",VLOOKUP(I91,'CUSTOMER LISTS'!$B$3:$E$1048576,2,0),"") -> R & R FUEL STATION | K91: =IF(I91<>"",VLOOKUP(I91,'CUSTOMER LISTS'!$B$3:$E$1048576,3,0),"") -> RUBEN SARAJENA YURONG JR. | L91: =IF(I91<>"",VLOOKUP(I91,'CUSTOMER LISTS'!$B$3:$E$1048576,4,0),"") -> BRGY. SUGUILON, SIAYAN, ZAMBOANGA DEL NORTE | M91: 761 | N91: =IF(M91<>"",VLOOKUP(M91,'PRODUCT & SERVICES'!$O:$P,2,0),"") -> Others ( Pls. Specify ) | O91: 1 PC | Q91: RECALIBRATION | R91: OPS
A92: 05/15/2026 | B92: 710 | C92: 2026-999 | D92: 7485 | E92: CBS | F92: =IF(E92<>"",VLOOKUP(E92,CODE!$B$2:$C$11,2,0),"") -> CHINA BANK - SAVINGS | G92: 43026 | H92: =IF(G92<>"",VLOOKUP(G92,COA!$A$3:$G$1048576,2,0),"") -> Service Income | I92: Bajo Oroqueita | J92: =IF(I92<>"",VLOOKUP(I92,'CUSTOMER LISTS'!$B$3:$E$1048576,2,0),"") -> NONON'S FUEL STATION | K92: =IF(I92<>"",VLOOKUP(I92,'CUSTOMER LISTS'!$B$3:$E$1048576,3,0),"") -> CRISAN SABIJON HERNANE | L92: =IF(I92<>"",VLOOKUP(I92,'CUSTOMER LISTS'!$B$3:$E$1048576,4,0),"") -> BRGY. SAN VICENTE BAJO, OROQUIETA CITY, MISAMIS OCCIDENTAL | M92: 761 | N92: =IF(M92<>"",VLOOKUP(M92,'PRODUCT & SERVICES'!$O:$P,2,0),"") -> Others ( Pls. Specify ) | Q92: FULL PAYMENT ON COC PROCESSING | R92: OPS | U92: 05/15/2026
A93: 05/15/2026 | B93: 711 | C93: 2026-1000 | D93: 1400 | E93: BNC | F93: =IF(E93<>"",VLOOKUP(E93,CODE!$B$2:$C$11,2,0),"") -> BDO NETWORK - CHECKING | G93: 21016 | H93: =IF(G93<>"",VLOOKUP(G93,COA!$A$3:$G$1048576,2,0),"") -> Unearned Revenue - OPS | I93: Malintubuan (Bustillos) | J93: =IF(I93<>"",VLOOKUP(I93,'CUSTOMER LISTS'!$B$3:$E$1048576,2,0),"") -> B-PRO GASOLINE STATION | K93: =IF(I93<>"",VLOOKUP(I93,'CUSTOMER LISTS'!$B$3:$E$1048576,3,0),"") -> DIVINE MAY SALAZAR BUSTILLOS | L93: =IF(I93<>"",VLOOKUP(I93,'CUSTOMER LISTS'!$B$3:$E$1048576,4,0),"") -> BRGY. MALINTUBOAN, LABASON, ZAMBOANGA DEL NORTE | M93: 761 | N93: =IF(M93<>"",VLOOKUP(M93,'PRODUCT & SERVICES'!$O:$P,2,0),"") -> Others ( Pls. Specify ) | Q93: RECALIBRATION | R93: OPS
A94: 05/15/2026 | B94: 712 | C94: 2026-1001 | D94: 60000 | F94: =IF(E94<>"",VLOOKUP(E94,CODE!$B$2:$C$12,2,0),"") | G94: 25500 | H94: =IF(G94<>"",VLOOKUP(G94,COA!$A$3:$G$1048576,2,0),"") -> Other Payables_Current - DHPP | I94: CNR | J94: =IF(I94<>"",VLOOKUP(I94,'CUSTOMER LISTS'!$B$3:$E$1048576,2,0),"") -> CLYDE N. REBOLLOS | K94: =IF(I94<>"",VLOOKUP(I94,'CUSTOMER LISTS'!$B$3:$E$1048576,3,0),"") -> CLYDE N. REBOLLOS | L94: =IF(I94<>"",VLOOKUP(I94,'CUSTOMER LISTS'!$B$3:$E$1048576,4,0),"") -> BRGY. STA.ISABEL, DIPOLOG CITY | M94: 761 | N94: =IF(M94<>"",VLOOKUP(M94,'PRODUCT & SERVICES'!$O:$P,2,0),"") -> Others ( Pls. Specify ) | Q94: SHORT TERM LOAN
A95: 05/15/2026 | B95: 713 | C95: 2026-1002 | D95: 9400 | E95: FVC | F95: =IF(E95<>"",VLOOKUP(E95,CODE!$B$2:$C$12,2,0),"") -> FIRST VALLEY -CHECKING | G95: 21016 | H95: =IF(G95<>"",VLOOKUP(G95,COA!$A$3:$G$1048576,2,0),"") -> Unearned Revenue - OPS | I95: Dumingag Bulilit | J95: =IF(I95<>"",VLOOKUP(I95,'CUSTOMER LISTS'!$B$3:$E$1048576,2,0),"") -> K2J2 GAS REFILLING STATION | K95: =IF(I95<>"",VLOOKUP(I95,'CUSTOMER LISTS'!$B$3:$E$1048576,3,0),"") -> JENIE FE BALOGBOG ALINSUG | L95: =IF(I95<>"",VLOOKUP(I95,'CUSTOMER LISTS'!$B$3:$E$1048576,4,0),"") -> BRGY. SAN PEDRO, DUMINGAG, ZAMBOANGA DEL SUR | M95: 712 | N95: =IF(M95<>"",VLOOKUP(M95,'PRODUCT & SERVICES'!$O:$P,2,0),"") -> Sea-Oil | O95: 4 BOXES | P95: 2T 200ML X 60 | Q95: FULL PAYMENT ON PURCHASED ITEM - 2T 200 ML X 60 | R95: OPS | S95: 2026-0050 | T95: 46169
A96: 05/15/2026 | B96: 714 | C96: 2026-1003 | D96: 234800 | F96: =IF(E96<>"",VLOOKUP(E96,CODE!$B$2:$C$12,2,0),"") | G96: 25500 | H96: =IF(G96<>"",VLOOKUP(G96,COA!$A$3:$G$1048576,2,0),"") -> Other Payables_Current - DHPP | I96: STPC-San Pedro | J96: =IF(I96<>"",VLOOKUP(I96,'CUSTOMER LISTS'!$B$3:$E$1048576,2,0),"") -> SEVEN-TRENT PETROLEUM CORP. | K96: =IF(I96<>"",VLOOKUP(I96,'CUSTOMER LISTS'!$B$3:$E$1048576,3,0),"") -> SEVEN-TRENT PETROLEUM CORP. | L96: =IF(I96<>"",VLOOKUP(I96,'CUSTOMER LISTS'!$B$3:$E$1048576,4,0),"") -> BRGY. SAN PEDRO, DAPITAN, ZAMBOANGA DEL NORTE | M96: 761 | N96: =IF(M96<>"",VLOOKUP(M96,'PRODUCT & SERVICES'!$O:$P,2,0),"") -> Others ( Pls. Specify ) | Q96: SHORT TERM LOAN; ADDITIONAL PAYMENT ON 8 PCS. MS PLATE (SOMINOT)
A97: 05/06/2026 | B97: 715 | C97: 2026-1004 | D97: 9445 | E97: CBS | F97: =IF(E97<>"",VLOOKUP(E97,CODE!$B$2:$C$12,2,0),"") -> CHINA BANK - SAVINGS | G97: 43026 | H97: =IF(G97<>"",VLOOKUP(G97,COA!$A$3:$G$1048576,2,0),"") -> Service Income | I97: Bayog Bulilit | J97: =IF(I97<>"",VLOOKUP(I97,'CUSTOMER LISTS'!$B$3:$E$1048576,2,0),"") -> JDM-6 FUEL STATION | K97: =IF(I97<>"",VLOOKUP(I97,'CUSTOMER LISTS'!$B$3:$E$1048576,3,0),"") -> DELIA SAJULGA BACO | L97: =IF(I97<>"",VLOOKUP(I97,'CUSTOMER LISTS'!$B$3:$E$1048576,4,0),"") -> BRGY. KAHAYAGAN, BAYOG, ZAMBOANGA DEL SUR | M97: 761 | N97: =IF(M97<>"",VLOOKUP(M97,'PRODUCT & SERVICES'!$O:$P,2,0),"") -> Others ( Pls. Specify ) | Q97: 50 % COC PROCESSING FEE | U97: 05/06/2026
A98: 05/21/2026 | B98: 716 | C98: 2026-1005 | D98: 7485 | E98: KBS | F98: =IF(E98<>"",VLOOKUP(E98,CODE!$B$2:$C$12,2,0),"") -> KATIPUNAN BANK-SAVINGS | G98: 43026 | H98: =IF(G98<>"",VLOOKUP(G98,COA!$A$3:$G$1048576,2,0),"") -> Service Income | I98: Villaflor-Len | J98: =IF(I98<>"",VLOOKUP(I98,'CUSTOMER LISTS'!$B$3:$E$1048576,2,0),"") -> LEN GASOLINE STATION | K98: =IF(I98<>"",VLOOKUP(I98,'CUSTOMER LISTS'!$B$3:$E$1048576,3,0),"") -> ARLENE EDIOS UBA | L98: =IF(I98<>"",VLOOKUP(I98,'CUSTOMER LISTS'!$B$3:$E$1048576,4,0),"") -> BRGY. VILLAFLOR, OROQUIETA CITY, MISAMIS OCCIDENTAL | M98: 761 | N98: =IF(M98<>"",VLOOKUP(M98,'PRODUCT & SERVICES'!$O:$P,2,0),"") -> Others ( Pls. Specify ) | Q98: FULL PAYMENT ON COC PROCESSING | U98: 05/21/2026
A99: 05/22/2026 | B99: 717 | C99: 2026-1006 | D99: 2350 | E99: PSS | F99: =IF(E99<>"",VLOOKUP(E99,CODE!$B$2:$C$12,2,0),"") -> PSBC- SAVINGS | G99: 21016 | H99: =IF(G99<>"",VLOOKUP(G99,COA!$A$3:$G$1048576,2,0),"") -> Unearned Revenue - OPS | I99: Dicayo | J99: =IF(I99<>"",VLOOKUP(I99,'CUSTOMER LISTS'!$B$3:$E$1048576,2,0),"") -> MJ HABAGAT GAS STATION | K99: =IF(I99<>"",VLOOKUP(I99,'CUSTOMER LISTS'!$B$3:$E$1048576,3,0),"") -> THERESA MEE SARENAS HABAGAT | L99: =IF(I99<>"",VLOOKUP(I99,'CUSTOMER LISTS'!$B$3:$E$1048576,4,0),"") -> BRGY. DAANGLUNGSOD, KATIPUNAN, ZAMBOANGA DEL NORTE | M99: 712 | N99: =IF(M99<>"",VLOOKUP(M99,'PRODUCT & SERVICES'!$O:$P,2,0),"") -> Sea-Oil | O99: 1 BOX | P99: 2T 200ML X 60 | Q99: FULL PAYMENT ON PURCHASED ITEM-SEA OIL | S99: 2026-081 | T99: 05/22/2026
A100: 05/23/2026 | B100: 718 | C100: 2026-1007 | D100: 1200 | E100: RCS | F100: =IF(E100<>"",VLOOKUP(E100,CODE!$B$2:$C$12,2,0),"") -> RCBC -SAVINGS | G100: 43016 | H100: =IF(G100<>"",VLOOKUP(G100,COA!$A$3:$G$1048576,2,0),"") -> Job Orders | I100: Bato Plaridel | J100: =IF(I100<>"",VLOOKUP(I100,'CUSTOMER LISTS'!$B$3:$E$1048576,2,0),"") -> MARCUS FUEL STATION | K100: =IF(I100<>"",VLOOKUP(I100,'CUSTOMER LISTS'!$B$3:$E$1048576,3,0),"") -> MARICRIS FE MAGHINAY ARANDID | L100: =IF(I100<>"",VLOOKUP(I100,'CUSTOMER LISTS'!$B$3:$E$1048576,4,0),"") -> BRGY. BATO, PLARIDEL, MISAMIS OCCIDENTAL | M100: 761 | N100: =IF(M100<>"",VLOOKUP(M100,'PRODUCT & SERVICES'!$O:$P,2,0),"") -> Others ( Pls. Specify ) | Q100: RELAY REPLACEMENT | U100: 05/23/2026
A101: 05/26/2026 | B101: 719 | C101: 2026-1008 | D101: 27000 | E101: EWC | F101: =IF(E101<>"",VLOOKUP(E101,CODE!$B$2:$C$12,2,0),"") -> EASTWEST-CHECKING | H101: =IF(G101<>"",VLOOKUP(G101,COA!$A$3:$G$1048576,2,0),"") | I101: San Pedro bulilit | J101: =IF(I101<>"",VLOOKUP(I101,'CUSTOMER LISTS'!$B$3:$E$1048576,2,0),"") -> JANA'S FUEL STATION | K101: =IF(I101<>"",VLOOKUP(I101,'CUSTOMER LISTS'!$B$3:$E$1048576,3,0),"") -> TOM JERRY TIMBOL SAGARIO | L101: =IF(I101<>"",VLOOKUP(I101,'CUSTOMER LISTS'!$B$3:$E$1048576,4,0),"") -> BRGY. SAN PEDRO, DAPITAN, ZAMBOANGA DEL NORTE | M101: 761 | N101: =IF(M101<>"",VLOOKUP(M101,'PRODUCT & SERVICES'!$O:$P,2,0),"") -> Others ( Pls. Specify ) | Q101: PAYMENT FOR COMPRESSOR
...

Sheet CUSTOMER LISTS
B2: CODING (FROM OPERATIONS) | C2: REGISTERED BUSINESS NAME | D2: SUPPLIER'S NAME | E2: BUSINESS ADDRESS
B3: Bacong bulilit | C3: HI-LAND FUEL REFILLING STATION | D3: SITTI MAIRA LANGAN ANDAL | E3: BRGY. BACONG, SALUG, ZAMBONGA DEL NORTE
B4: Aseniero | C4: IAP'S GASOLINE STATION | D4: ALLAN FEROLINO OBAS | E4: BRGY. ASENIERO, DAPITAN, ZAMBOANGA DEL NORTE
B5: Bacong Pamil | C5: MJ FUEL REFILLING STATION | D5: MERCEDARIO NUGAS PAMIL | E5: BRGY. BACONG, SALUG, ZAMBONGA DEL NORTE
B6: Bago
B7: Bagumbang palomar
B8: Bajo Oroqueita | C8: NONON'S FUEL STATION | D8: CRISAN SABIJON HERNANE | E8: BRGY. SAN VICENTE BAJO, OROQUIETA CITY, MISAMIS OCCIDENTAL
B9: Balagon Siay | C9: VASH FUEL REFILLING STATION | D9: JHOANNE SHANE MARIE ESMORES AGLOBO | E9: BRGY. BALAGON, SIAY, ZAMBOANGA SIBUGAY
B10: Balamban Mahayag | C10: MMN GAS STATION | D10: MARY JANE RESILOSA PAUSANOS | E10: BRGY. BAG-ONG BALAMBAN, MAHAYAG, ZAMBOANGA DEL SUR
B11: Barcelona
B12: Basagan | C12: RJM GASOLINAHAN PETROCHEMICAL PRODUCTS TRADING | D12: FELICISIMA PANTORILLA ORILLAN | E12: BRGY. BASAGAN, KATIPUNAN, ZAMBOANGA DEL NORTE
B13: Bato Plaridel | C13: MARCUS FUEL STATION | D13: MARICRIS FE MAGHINAY ARANDID | E13: BRGY. BATO, PLARIDEL, MISAMIS OCCIDENTAL
B14: Baylimango | C14: MORTE FUEL REFILLING STATION | D14: PRIMITIVO ALICMAN MORTE | E14: BRGY. BAYLIMANGO, DAPITAN CITY, ZAMBOANGA DEL NORTE
B15: Bayog (BACO) | C15: JD-MACS GAS REFILLING STATION | D15: DELIA S. BACO | E15: BRGY. KAHAYAGAN, BAYOG, ZAMBOANGA DEL SUR
B16: Bayog buboan | C16: REDBAR GAS REFILLING STATION | D16: ARNEL GAJO ENTAG | E16: BRGY. BOBUAN, BAYOG, ZAMBOANGA DEL SUR
B17: Bayog Bulilit | C17: JDM-6 FUEL STATION | D17: DELIA SAJULGA BACO | E17: BRGY. KAHAYAGAN, BAYOG, ZAMBOANGA DEL SUR
B18: Binoni | C18: BOY G FUEL REFILLING STATION | D18: EPIFRAS RUDAS GALLEPOSO | E18: BRGY. BINONI, SALUG, ZAMBOANGA DEL NORTE
B19: Bucana Siocon | C19: NAUFAR FUEL REFILLING STATION | D19: JULCARIM ALVAREZ CASALIN | E19: BRGY. BUCANA, SIOCON, ZAMBOANGA DEL NORTE
B20: Buug
B21: Calican | C21: FOUR ANGELS FUEL REFILLING STATION | D21: FREMIE ALFON PALCONAYO | E21: BRGY. CALICAN, PIÑAN, ZAMBOANGA DEL NORTE
B22: Caracol Salug | C22: AZ FUEL REFILLING STATION | D22: SALAHUDDIN AKIL HAMBALI | E22: BRGY. CARACOL, SALUG, ZAMBOANGA DEL NORTE
B23: Clarin Settlement | C23: COUNTRYROAD FUEL REFILLING STATION | D23: ASHLEY NICOLE REAMBONANZA LLERIN | E23: BRGY. CLARIN SETTLEMENT, OROQUIETA CITY, MISAMIS OCCIDENTAL
B24: Cogon | C24: DJ FUEL REFILLING STATION | D24: DAPHNE CLAIRE ABARCA MARQUINA | E24: BRGY. COGON, DIPOLOG CITY, ZAMBOANGA DEL NORTE
B25: Coloran Siay | C25: LIA-FRAN-LILY FUEL STATION | D25: LILIA CAMBE UNITO | E25: BRGY. COLORAN, SIAY, ZAMBOANGA DEL SUR
B26: Dampalan (Osmena)
B27: Dampalan DAPITAN | C27: RAMAD FUEL REFILLING STATION | D27: RAMIL QUIGUING ADANTE | E27: BRGY. DAMPALAN, DAPITAN CITY, ZAMBOANGA DEL NORTE
B28: Dansulyan | C28: GD FUEL REFILLING STATION | D28: DOUET PEPITO AMARILLE | E28: BRGY. DANSULLAN, POLANCO, ZAMBOANGA DEL NORTE
B29: Del Pilar | C29: ARLEGUI FUEL REFILLING STATION | D29: SANDY LOU TRANSMIL ARLEGUI | E29: BRGY. DEL PILAR, PIÑAN, ZAMBOANGA DEL NORTE
B30: Dona Josefa | C30: PATRICK & BRYLE FUEL REFILLING STATION | D30: BOB DALMAN PAGENTE | E30: BRGY. DOÑA JOSEFA, SINDANGAN, ZAMBOANGA DEL NORTE
B31: Denuyan siayan
B32: Detulan | C32: B & J GAS REFILLING STATION | D32: ISAGANI BARAZON LEDESMA | E32: BRGY. DITULAN, DUMINGAG, ZAMBOANGA DEL SUR
B33: Dicayo | C33: MJ HABAGAT GAS STATION | D33: THERESA MEE SARENAS HABAGAT | E33: BRGY. DAANGLUNGSOD, KATIPUNAN, ZAMBOANGA DEL NORTE
B34: Dicoyong | C34: PIPZ GAS REFILLING STATION | D34: JEMWEL TAMAN ZAMORA | E34: BRGY. DICOYONG, SINDANGAN, ZAMBOANGA DEL NORTE
B35: Dilawa | C35: G-P GAS REFILLING STATION | D35: JAYNALYN GUIO PACAÑA | E35: BRGY. DILAWA, PIÑAN, ZAMBOANGA DEL NORTE
B36: Dinasan | C36: JRG GAS REFILLING STATION | D36: JUDY ASISTER GONDULA | E36: BRGY. DINASAN, JOSE DALMAN, ZAMBOANGA DEL NORTE
B37: Dohinob | C37: LJ GAS REFILLING STATION | D37: LEONARDO BAYBAY UGNIT III | E37: BRGY. DOHINOB, PRES. MANUEL A. ROXAS, ZAMBOANGA DEL NORTE
B38: Don Vic Dennis | C38: 3DS & B GAS REFILLING STATION | D38: DENNIS RAMIREZ DELOS SANTOS | E38: BRGY. TUNO, DON VICTORIANO, MISAMIS OCCIDENTAL
B39: Dumingag Bulilit | C39: K2J2 GAS REFILLING STATION | D39: JENIE FE BALOGBOG ALINSUG | E39: BRGY. SAN PEDRO, DUMINGAG, ZAMBOANGA DEL SUR
B40: Eunice
B41: Fatima Liloy | C41: ENCAR GASOLINE STATION | D41: REY ENRICO ORIOLA EROY | E41: BRGY. FATIMA, LILOY, ZAMBOANGA DEL NORTE
B42: Gampis | C42: AM-MON FUEL STATION | D42: LUCILLE MANANQUIL SINARILLOS | E42: BRGY. SICAYAB, DIPOLOG CITY, ZAMBOANGA DEL NORTE
B43: Guisokan | C43: JK GAS REFILLING STATION | D43: REZA ZAMORAS BATION | E43: BRGY. DOÑA JOSEFA, SINDANGAN, ZAMBOANGA DEL NORTE
B44: Guitran | C44: QUADRU FUEL REFILLING STATION | D44: ALJUN LATA SUERTE | E44: BRGY. GUITRAN, DUMINGAG, ZAMBOANGA DEL SUR
B45: Ilaya | C45: 4J'S MICRO GAS REFILLING STATION | D45: HEPHER CALASANG BAEL | E45: BRGY. ILAYA, DAPITAN CITY, ZAMBOANGA DEL NORTE
B46: Ilihan | C46: RIA FRITZ GAS REFILLING STATION | D46: CHATERINE VILLARIN SULIMAN | E46: BRGY. ILIHAN, JOSE DALMAN, ZAMBOANGA DEL NORTE
B47: Imelda Sibugay | C47: JICKA GAS STATION | D47: JEFFREY SONZA DELA CRUZ | E47: BRGY. GANDIANGAN, IMELDA, ZAMBOANGA SIBUGAY
B48: Josefina (Helen) | C48: LENLEN GASOLINE STATION | D48: HELEN ESTORIOSO | E48: BRGY.MORADJE, JOSEFINA ZAMBOANGA DEL SUR
B49: Josefina (Malindang) | C49: MT. MALINDANG GAS REFILLING STATION | D49: GILBERTH DANDOY LAURE | E49: BRGY. LEONARDO, JOSEFINA, ZAMBOANGA DEL SUR
B50: Josefina Dlime | C50: DLIME GASOLINE STATION | D50: LEX IVOR MANGOMPIT ETAC | E50: BRGY. UPPER BAGONG TUDELA, JOSEFINA, ZAMBOANGA DEL SUR
B51: Josefina FT | C51: ADEV GAS STATION | D51: GLORIA PERATER CUARTO | E51: BRGY. UPPER BAGONG TUDELA, JOSEFINA, ZAMBOANGA DEL SUR
B52: Kalawit | C52: MACDROF FUEL REFILLING STATION | D52: BIDULITA TELMO AGUILAR
B53: La libertad | C53: 3J'S GASOLINE STATION | D53: JUNNEL JUMALON JUMAWAN | E53: BRGY. POBLACION, LA LIBERTAD, ZAMBOANGA DEL NORTE
B54: Labakid | C54: M & J GAS STATION | D54: IVY MAESTRE OMOS | E54: BRGY. LABAKID, SINDANGAN, ZAMBOANGA DEL NORTE
B55: Labason (Daguplo) | C55: DJ FUEL REFILLING STATION | D55: DANIEL DAGUPLO | E55: BRGY. MALINTUBOAN, LABASON, ZAMBOANGA DEL NORTE
B56: Labason Panos (Ubay) | C56: PANOS GAS REFILLING STATION | D56: HEROINAE JOY DIGAMOS PANOS | E56: BRGY. UBAY, LABASON, ZAMBOANGA DEL NORTE
B57: LABASON BULILIT | C57: S/R GASOLINE STATION | D57: DAVID ALAIN ORTEGA MORGIA | E57: BRGY. IMELDA, LABASON, ZAMBOANGA DEL NORTE
B58: Liba Bayog | C58: KELTEX GAS REFILLING STATION | D58: LOVELY BERNARDO FABIANTES | E58: BRGY. LIBA, BAYOG, ZAMBOANGA DEL SUR
B59: Libertad D. | C59: PUMP-N-GO LIBERTAD GAS REFILLING STATION | D59: WARLY BACLAY DELA RAIZ | E59: BRGY. LIBERTAD, DUMINGAG, ZAMBOANGA DEL SUR
B60: Liloan | C60: BUD'S GAS REFILLING STATION | D60: DOREEN KAAMIÑO FRIGILLANO | E60: BRGY. LILOAN, BONIFACIO, MISAMIS OCCIDENTAL
B61: Lingasad | C61: ARQUIZA FUEL REFILLING STATION | D61: ANTONIO MANINGO ARQUIZA | E61: BRGY. LINGASAD, POLANCO, ZAMBOANGA DEL NORTE
B62: Lipakan | C62: JGCJ FUEL REFILLING STATION | D62: JOSEPH ALBON MAATA | E62: BRGY. LIPAKAN, ROXAS, ZAMBOANGA DEL NORTE
B63: Lituban Siocon | C63: AM GAS REFILLING STATION | D63: ANGELITO ORNATES CAMION | E63: BRGY. NEW LITUBAN, SIOCON, ZAMBOANGA DEL NORTE
B64: Lower Landing | C64: TANAKAMI GAS STATION | D64: WEDILYN ONRADA ROSALES | E64: BRGY. LOWER LANDING, DUMINGAG, ZAMBOANGA DEL SUR
B65: Lutiman Alicia
B66: Malintubuan (Bustillos) | C66: B-PRO GASOLINE STATION | D66: DIVINE MAY SALAZAR BUSTILLOS | E66: BRGY. MALINTUBOAN, LABASON, ZAMBOANGA DEL NORTE
B67: MAHAYAG BULILIT | C67: E & R GAS REFILLING STATION | D67: ELVIE TALOCOD SALADAGA | E67: BRGY. POBLACION, MAHAYAG, ZAMBOANGA DEL SUR
B68: Madalag | C68: FUELGO GAS REFILLING STATION | D68: RODMAR VERTUDEZ FUEGO | E68: BRGY. MADALAG, JOSE DALMAN , ZAMBOANGA DEL NORTE
B69: Malala (San pedro) | C69: KL GAS REFILLING STATION | D69: MIKE JAPHET FERNANDEZ BARBASO | E69: BRGY. SAN PEDRO, POLANCO, ZAMBOANGA DEL NORTE
B70: Mandih | C70: JANUAORYZA MICRO GAS STATION | D70: RUFINO ANDUS MUKOD | E70: BRGY. MANDIH, SINDANGAN, ZAMBOANGA DEL NORTE
B71: Maralag | C71: GUNIX GAS STATION | D71: SEM UDTOHAN PANGASIAN | E71: BRGY. MARALAG, DUMINGAG, ZAMBOANGA DEL SUR
B72: MBB Siayan | C72: MBB FUEL REFILLING STATION | D72: BRENDO BIASCA MALAHAY | E72: BRGY. POBLACION, SIAYAN, ZAMBONGA DEL NORTE
B73: Midsalip | C73: AA'S GAS REFILLING STATION | D73: ARNEL DELA CERNA CALEXTERIO | E73: BRGY. BIBILOP, MIDSALIP, ZAMBOANGA DEL SUR
B74: Milanid Talinga
B75: Misom Baliangao
B76: Motibot | C76: RIVAS GAS REFILLING STATION | D76: RIEL MONTEFALCON RIVAS | E76: BRGY. MOTIBOT, SINDANGAN, ZAMBOANGA DEL NORTE
B77: Mucas | C77: RM GASOLINE STATION | D77: HAMIR GUMANDOL JAAPAL | E77: BRGY. MUCAS, SALUG, ZAMBONGA DEL NORTE
B78: Mutia | C78: FREECOPE FUEL REFILLING STATION | D78: LERNIE SAMSON FREJOLEZ | E78: BRGY. POBLACION, MUTIA, ZAMBOANGA DEL NORTE
B79: New Sicayab | C79: FAME GAS REFILLING STATION | D79: FERNANDO DELA ROSA PARAN | E79: BRGY. NEW SICAYAB, POLANCO, ZAMBOANGA DEL NORTE
B80: Olingan | C80: ENZO'S GAS REFILLING STATION | D80: CLEMENTE COPE GUIO | E80: BRGY. OLINGAN, DIPOLOG CITY, ZAMBOANGA DEL NORTE
B81: Villaflor Oroquieta | C81: AYA G MICRO GAS STATION | D81: ARTIUS TALADUA GALINDO | E81: BRGY. VILLAFLOR, OROQUIETA CITY, MISAMIS OCCIDENTAL
B82: Osukan Labason | C82: GD GASOLINE STATION | D82: DAVID ALAIN ORTEGA MORGIA | E82: BRGY. OSUKAN, LABASON, ZAMBOANGA DEL NORTE
B83: Palandok | C83: KJ FUEL REFILLING STATION | D83: MARCOS MABANSAG ARAGON | E83: BRGY. PALANDOK, LEON POSTIGO, ZAMBOANGA DEL NORTE
B84: Pangalalan | C84: C & N GAS REFILLING STATION | D84: WILSON ENOJARDO PLANTERAS | E84: BRGY. PANGALALAN, SINDANGAN, ZAMBOANGA DEL NORTE
B85: Paruk Siay | C85: CRILOUR FUEL REFILLING STATION | D85: ELSON ENRIQUEZ BASCO | E85: BRGY. PARUK, SIAY, ZAMBOANGA SIBUGAY
B86: Queenex B. | C86: QUEENEX M GAS STATION | D86: MYLO OLIDIANA QUINTO | E86: BRGY. BAGUMBANG, BONIFACIO, MISAMIS OCCIDENTAL
B87: Timan | C87: CHUCK GAS REFILLING STATION | D87: MAREBEL VILLACURA HICALDE | E87: BRGY. TIMAN, LILOY, ZAMBOANGA DEL NORTE
... B123: Dansulyan-Awa | C123: MJ FUEL REFILLING STATION | D123: JERELYN MONTEZA AWA | E123: BRGY. DANSULLAN, POLANCO, ZAMBOANGA DEL NORTE
B124: CNR-Gcash | C124: CLYDE N. REBOLLOS | D124: CLYDE N. REBOLLOS
B125: Dinas Sur | C125: KRD MICRO GAS STATION | D125: KELVIN ENOT DULA | E125: BRGY. LEGARDA 1, DINAS, ZAMBOANGA DEL SUR
B126: Mandih Bulilit | C126: JANUA-ORYZA GAS REFILLING STATION | D126: RUFINO ANDUS MUKOD | E126: BRGY. MANDIH, SINDANGAN, ZAMBOANGA DEL NORTE
B127: Napo Dapitan | C127: GIAN'S FUEL STATION | D127: HELGREG LINGO TINNAE | E127: BRGY. NAPO, DAPITAN CITY, ZAMBONGA DEL NORTE
B128: Sitio Sapa Indian | C128: R & R FUEL STATION | D128: RUBEN SARAJENA YURONG JR. | E128: BRGY. SUGUILON, SIAYAN, ZAMBOANGA DEL NORTE
B129: Tipolo-Claritas | C129: CLARITA'S FUEL STATION | D129: HEINZ BERNHARD YUMOL MANREZ | E129: BRGY. TIPOLO, PLARIDEL, MISAMIS OCCIDENTAL
B130: Suertes-Guitran | C130: SUERTE GAS STATION | D130: ALJUN LATA SUERTE | E130: BRGY. GUITRAN, DUMINGAG, ZAMBOANGA DEL SUR
B131: SLP-Rizal | C131: LARMINN & COASTAL GAS REFILLING STATION | D131: SANA ANDUS BAJAMUNDE | E131: BRGY. NANGCAAN, RIZAL, ZAMBOANGA DEL NORTE
B132: Villaflor-Len | C132: LEN GASOLINE STATION | D132: ARLENE EDIOS UBA | E132: BRGY. VILLAFLOR, OROQUIETA CITY, MISAMIS OCCIDENTAL
B133: San Miguel Aishi | C133: AISHI'S FUEL STATION | D133: NOELAINE SALAGUSTE BATINGAL | E133: BRGY. POBLACION, SAN MIGUEL, ZAMBOANGA DEL SUR
B134: Tudela G-max | C134: G-MAX GASOLINE STATION | D134: RUFINO MAINE III OCAPAN GONZALEZ | E134: BRGY. BASIRANG, TUDELA, MISAMIS OCCIDENTAL
B135: Bongon Sirawai | D135: MIRAN MADDA | E135: BRGY. BONGON, SIRAWAI, ZAMBOANGA DEL NORTE
B136: Bogabongan | C136: O'S FUEL REFILLING STATION | D136: OGIE S. SAGBED | E136: BRGY. BOGABONGAN, LEON B. POSTIGO
...

Sheet PRODUCT & SERVICES
B1: DIRECTORY | O1: CODING
B4: 1. Fuel Products | G4: Fuel
B5: 1.1 | C5: Gasoline
C6: 111 | D6: Premium (RON95) | O6: =C6 -> 111 | P6: =D6 -> Premium (RON95) | Q6: DHPP
C7: 112 | D7: Regular (RON 91) | O7: =C7 -> 112 | P7: =D7 -> Regular (RON 91) | Q7: DHPP
B8: 1.2 | C8: Diesel
C9: 121 | D9: Diesel ( Krudo ) | O9: =C9 -> 121 | P9: =D9 -> Diesel ( Krudo ) | Q9: DHPP
B10: 1.3 | C10: Jet Fuel
C11: 131 | D11: Jet Fuel | O11: =C11 -> 131 | P11: =D11 -> Jet Fuel | Q11: DHPP
B12: 1.4 | C12: LPG
C13: 141 | O13: =C13 -> 141 | Q13: DHPP
C14: 142 | O14: =C14 -> 142 | Q14: DHPP
C15: 143 | O15: =C15 -> 143 | Q15: DHPP
C16: 144 | O16: =C16 -> 144 | Q16: DHPP
B17: 1.5 | C17: Kerosene
C18: 151 | O18: =C18 -> 151 | Q18: DHPP
B20: 2. Storage & Handling Equipment | J20: CATEGORY
C21: 2.1 | D21: Tanks & Containers
D22: 211 | E22: Storage tanks | O22: =D22 -> 211 | P22: =E22 -> Storage tanks | Q22: DMIE
D23: 212 | E23: Barrels / Drums | O23: =D23 -> 212 | P23: =E23 -> Barrels / Drums | Q23: DMIE
C24: 2.2 | D24: Dispensing Equipment
D25: 2.2.1 | E25: Fuel Dispensers
E26: 2211 | F26: 1.5 KL TSRO Standard Machine | J26: MFS | O26: =E26 -> 2211 | P26: =F26 -> 1.5 KL TSRO Standard Machine | Q26: DMIE
E27: 2212 | F27: 1.5 KL TSRO Standing Machine | J27: MFS | O27: =E27 -> 2212 | P27: =F27 -> 1.5 KL TSRO Standing Machine | Q27: DMIE
E28: 2213 | F28: 2.0 KL TSRO Standard Machine | J28: MFS | O28: =E28 -> 2213 | P28: =F28 -> 2.0 KL TSRO Standard Machine | Q28: DMIE
E29: 2214 | F29: 2.0 KL TSRO Standing Machine | J29: MFS | O29: =E29 -> 2214 | P29: =F29 -> 2.0 KL TSRO Standing Machine | Q29: DMIE
E30: 2215 | F30: 3.0 KL TSRO Standard Machine | J30: MFS | O30: =E30 -> 2215 | P30: =F30 -> 3.0 KL TSRO Standard Machine | Q30: DMIE
E31: 2216 | F31: 3.0 KL TSRO Standing Machine | J31: MFS | O31: =E31 -> 2216 | P31: =F31 -> 3.0 KL TSRO Standing Machine | Q31: DMIE
E32: 2217 | F32: 5.0 KL TSRO Standard Machine | J32: MFS | O32: =E32 -> 2217 | P32: =F32 -> 5.0 KL TSRO Standard Machine | Q32: DMIE
E33: 2218 | F33: 5.0 KL TSRO Standing Machine | J33: MFS | O33: =E33 -> 2218 | P33: =F33 -> 5.0 KL TSRO Standing Machine | Q33: DMIE
E34: 2219 | F34: 6.0 KL TSRO Standard Machine | J34: MFS | O34: =E34 -> 2219 | P34: =F34 -> 6.0 KL TSRO Standard Machine | Q34: DMIE
E35: 2220 | F35: 6.0 KL TSRO Standing Machine | J35: MFS | O35: =E35 -> 2220 | P35: =F35 -> 6.0 KL TSRO Standing Machine | Q35: DMIE
D37: 2.2.2 | E37: Fuel Dispenser Parts
E38: 2221 | F38: Transfer Pump | O38: =E38 -> 2221 | P38: =F38 -> Transfer Pump | Q38: DMIE
E39: 2222 | F39: Hose | O39: =E39 -> 2222 | P39: =F39 -> Hose | Q39: DMIE
E40: 2223 | F40: Nozzle | O40: =E40 -> 2223 | P40: =F40 -> Nozzle | Q40: DMIE
E41: 2224 | F41: Keypad | O41: =E41 -> 2224 | P41: =F41 -> Keypad | Q41: DMIE
E42: 2225 | F42: Display | O42: =E42 -> 2225 | P42: =F42 -> Display | Q42: DMIE
E43: 2226 | F43: Pulser | O43: =E43 -> 2226 | P43: =F43 -> Pulser | Q43: DMIE
E44: 2227 | F44: Encoder | O44: =E44 -> 2227 | P44: =F44 -> Encoder | Q44: DMIE
E45: 2228 | F45: Solenoid Valves | O45: =E45 -> 2228 | P45: =F45 -> Solenoid Valves | Q45: DMIE
E46: 2229 | F46: CPU | O46: =E46 -> 2229 | P46: =F46 -> CPU | Q46: DMIE
D48: 2.2.3 | E48: Underground Tank (UGT)
E49: 2231 | F49: UGT | O49: 2231 | P49: =F49 -> UGT | Q49: DMIE
B51: 2.3 | C51: Calibration & Measurement | G51: IES
C52: 2.3.1 | D52: Fuel Calibration buckets
D53: 2311 | E53: Stainless Calibration Bucket | O53: =D53 -> 2311 | P53: =E53 -> Stainless Calibration Bucket | Q53: DMIE
D54: 2312 | E54: Galvanize Calibration Bucket | O54: =D54 -> 2312 | P54: =E54 -> Galvanize Calibration Bucket | Q54: DMIE
D55: 2313 | E55: Other Calibration Buckets | O55: =D55 -> 2313 | P55: =E55 -> Other Calibration Buckets | Q55: DMIE
C56: 2.3.2 | D56: Fuel dipsticks
D57: 2321 | E57: Dipstick ( Foldable ) | O57: =D57 -> 2321 | P57: =E57 -> Dipstick ( Foldable ) | Q57: DMIE
D58: 2322 | E58: Dipstick ( Others ) | O58: =D58 -> 2322 | P58: =E58 -> Dipstick ( Others ) | Q58: DMIE
C59: 2.3.3 | D59: Flow meters / gauges
D60: 2331 | E60: Flow Meter | O60: =D60 -> 2331 | P60: =E60 -> Flow Meter | Q60: DMIE
B62: 3. Fuel Maintenance & Additives | G62: IES
C63: 3.1 | D63: Fuel filters
D64: 311 | E64: Fuel Filter | O64: =D64 -> 311 | P64: =E64 -> Fuel Filter | Q64: DMIE
C65: 3.2 | D65: Fuel stabilizers
D66: 321 | E66: Stabilizer | O66: =D66 -> 321 | P66: =E66 -> Stabilizer | Q66: DMIE
C67: 3.3 | D67: Tank cleaning chemicals
D68: 331 | E68: Tank Cleaning Chemicals | O68: =D68 -> 331 | P68: =E68 -> Tank Cleaning Chemicals | Q68: DMIE
B70: 4. Safety & PPE
C71: 4.1 | D71: Gloves
D72: 411 | E72: Gloves | O72: =D72 -> 411 | P72: =E72 -> Gloves | Q72: DMIE
C73: 4.2 | D73: Goggles
D74: 421 | E74: Goggles | O74: =D74 -> 421 | P74: =E74 -> Goggles | Q74: DMIE
C75: 4.3 | D75: Suits
D76: 421 | E76: Suits | O76: =D76 -> 421 | P76: =E76 -> Suits | Q76: DMIE
C77: 4.4 | D77: Fire extinguishers
D78: 441 | E78: Fire Extinguisher 5 lbs | O78: =D78 -> 441 | P78: =E78 -> Fire Extinguisher 5 lbs | Q78: DMIE
D79: 442 | E79: Fire Extinguisher 10 lbs | O79: =D79 -> 442 | P79: =E79 -> Fire Extinguisher 10 lbs | Q79: DMIE
D80: 443 | E80: Fire Extinguisher 15 lbs | O80: =D80 -> 443 | P80: =E80 -> Fire Extinguisher 15 lbs | Q80: DMIE
D81: 444 | E81: Fire Extinguisher 20 lbs | O81: =D81 -> 444 | P81: =E81 -> Fire Extinguisher 20 lbs | Q81: DMIE
D82: 445 | E82: Fire Extinguisher 25 lbs | O82: =D82 -> 445 | P82: =E82 -> Fire Extinguisher 25 lbs | Q82: DMIE
C83: 4.5 | D83: Spill kits
D84: 451 | E84: Spill Kits | O84: =D84 -> 451 | P84: =E84 -> Spill Kits | Q84: DMIE
C85: 4.6 | D85: Thermal Papers
D86: 452 | E86: Thermal Paper | O86: =D86 -> 452 | P86: =E86 -> Thermal Paper | Q86: DMIE
B88: 5. Tools & Accessories
C89: 5.1 | D89: Funnels
D90: 511 | E90: Funnels | O90: =D90 -> 511 | P90: =E90 -> Funnels | Q90: DMIE
C91: 5.2 | D91: Clamps
D92: 521 | E92: Clamps | O92: =D92 -> 521 | P92: =E92 -> Clamps | Q92: DMIE
C93: 5.3 | D93: Hand tools for fuel systems
D94: 531 | E94: Tools | O94: =D94 -> 531 | P94: =E94 -> Tools | Q94: DMIE
B96: 6. Electrical & Power Backup Equipment
C97: 6.1 Batteries
C98: - Lead-acid batteries
D99: 611 | E99: Lead - Acid Batteries | O99: =D99 -> 611 | P99: =E99 -> Lead - Acid Batteries | Q99: DMIE
C100: - Lithium-ion batteries
D101: 611 | E101: Lithium -ion Batteries | O101: =D101 -> 611 | P101: =E101 -> Lithium -ion Batteries | Q101: DMIE
C102: 6.2 Inverters / UPS
C103: - Standalone inverters
D104: 621 | E104: Inverter 12 V | O104: =D104 -> 621 | P104: =E104 -> Inverter 12 V | Q104: DMIE
C105: - Combined inverter/charger systems
C106: 6.3 Generators (if you have backup fuel generators)
C107: - Diesel generators
C108: - Gasoline generators
B110: 7. OPS and Other Services
C112: 7.1 | D112: Lubricants
...

Sheet CODE
B1: CODING | C1: BANKS | F1: SEGMENT
B2: BNC | C2: BDO NETWORK - CHECKING | F2: DHPP
B3: CBS | C3: CHINA BANK - SAVINGS | F3: DMIE
B4: EWC | C4: EASTWEST-CHECKING | F4: OPS
B5: FVC | C5: FIRST VALLEY -CHECKING
B6: KBS | C6: KATIPUNAN BANK-SAVINGS
B7: MBC | C7: METROBANK-CHECKING
B8: PNC | C8: PNB - CHECKING
B9: PSC | C9: PSBC - CHECKING
B10: PSS | C10: PSBC- SAVINGS
B11: RCS | C11: RCBC -SAVINGS
B12: COH | C12: CASH/CHECK ON HAND
B13: PNO | C13: PNB - OPEX
B14: ARC | C14: A/Receivables - CNR

Sheet COA
A3: COA | B3: ACCOUNT TITLES | C3: SEGMENT | D3: CLASSIFICATION | E3: CATEGORY | F3: Sub-Accounts | G3: Major Accounts
A4: 10000 | B4: Petty Cash Fund | C4: DHPP | D4: Cash & Cash in Bank | E4: Petty Cash | F4: Current Assets | G4: Asset
A5: 10010 | B5: Cash on Hand-DHPP | C5: DHPP | D5: Cash & Cash in Bank | E5: Cash on Hand | F5: Current Assets | G5: Asset
A6: 10013 | B6: Cash on Hand-DMIE | C6: DMIE | D6: Cash & Cash in Bank | E6: Cash on Hand | F6: Current Assets | G6: Asset
A7: 10016 | B7: Cash on Hand-OPS | C7: OPS | D7: Cash & Cash in Bank | E7: Cash on Hand | F7: Current Assets | G7: Asset
A8: 10020 | B8: Due from Other Bank_EW-DHPP | C8: DHPP | D8: Due From Other Bank | E8: Due from Banks | F8: Current Assets | G8: Asset
A9: 10023 | B9: Due from Other Bank_EW-DMIE | C9: DMIE | D9: Due From Other Bank | E9: Due from Banks | F9: Current Assets | G9: Asset
A10: 10026 | B10: Due from Other Bank_EW-OPS | C10: OPS | D10: Due From Other Bank | E10: Due from Banks | F10: Current Assets | G10: Asset
A11: 10030 | B11: Cash in Bank_1VB-DHPP | C11: DHPP | D11: Cash & Cash in Bank | E11: Cash in Bank | F11: Current Assets | G11: Asset
A12: 10033 | B12: Cash in Bank_1VB-DMIE | C12: DMIE | D12: Cash & Cash in Bank | E12: Cash in Bank | F12: Current Assets | G12: Asset
A13: 10036 | B13: Cash in Bank_1VB-OPS | C13: OPS | D13: Cash & Cash in Bank | E13: Cash in Bank | F13: Current Assets | G13: Asset
A14: 10040 | B14: Cash in Bank_PNB-DHPP | C14: DHPP | D14: Cash & Cash in Bank | E14: Cash in Bank | F14: Current Assets | G14: Asset
A15: 10043 | B15: Cash in Bank_PNB-DMIE | C15: DMIE | D15: Cash & Cash in Bank | E15: Cash in Bank | F15: Current Assets | G15: Asset
... A374: 66006 | B374: Other Gen. and Admin. Expenses_OPS | C374: OPS | D374: Non-Trade Expense | E374: Gen. and Admin. Expenses | F374: Non-Operating Expense | G374: Equity
