Workbook
Name ChartofAccountsTable: '[1]Chart of Accounts'!$B$7:$C$115

Sheet CF
B2: SEVEN-TRENT MACHINERIES INDUSTRIAL EQUIPMENT TRADING
B3: Summary of Cash Flows
B4: For the period cycle June 23 - June 29, 2026
H5: Amounts in pesos
B6: CASH FLOWS ARISING FROM OPERATING ACTIVITIES
B7: Collections from Distribution and Hauling of Petroleum (+) [ Net of inter-account transfer] | H7: ='CASH, END'!R17 -> 0
B8: Other Cash Collections relating to operating activities (+) | H8: ='CASH, END'!Q18 -> 0 | K8: =H6+H8 -> 0
B9: Payments to Supplier of Petroleum Products (-) | H9: =-'CASH, END'!Q20 -> 0 | K9: =H7+H9 -> 0
B10: RFP of Accounts Payable [ i.e other suppliers, 3rd parties] (-) | H10: =-'CASH, END'!Q21 -> 0 | K10: =H10 -> 0
B11: Cash Withdrawn for PCF Replenishment (-) | H11: =-'CASH, END'!Q22 -> 0 | K11: =H11 -> 0
B12: Other Cash payments relating to operating activities(-) | H12: =-'CASH, END'!$Q$25 -> 0 | K12: =H12 -> 0
B13: Net cash flows provided by operating activities (+/-) | H13: =H7+H8+H9+H10+H11+H12 -> 0 | K13: =K9+K10+K11+K12+K8 -> 0 | L13: =H13-K13 -> 0
B14: CASH FLOWS FROM INVESTING ACTIVITIES
H15: 0
H16: 0
B17: Net cash flows used in investing activities | H17: =H15+H16 -> 0
B18: CASH FLOWS ARISING FROM FINANCING ACTIVITIES
B19: Funds Borrowed from other account (+) | H19: ='CASH, END'!Q19 -> 0
B20: Checks Cleared for Loan / Fund Repayments (-) | H20: =-'CASH, END'!Q26 -> 0
B21: Net cash flows used in financing activities (+/-) | H21: =H20+H19 -> 0
B22: NET INCREASE / (DECREASE) IN CASH | H22: =H21+H17+H13 -> 0
B23: Add: CASH AT THE BEGINNING OF THE CYCLE | H23: ='CASH, END'!Q3 -> 0
B24: Less: ADB, Maintaining Balance | H24: =-'CASH, END'!Q4 -> 0
B25: CASH AVAILABLE AT THE END OF THE CYCLE | H25: =H22+H23+H24 -> 0 | J25: ='CASH, END'!Q8 -> 0 | K25: =H25-J25 -> 0
J26: =H25-H24 -> 0
J27: =J25-J26 -> 0

Sheet COLLECTIBLES
C1: DISTRIBUTION AND HAULING DEPARTMENT | F1: FINANCE AND ACCOUNTING DEPARTMENT
C2: PERIOD: AUG 19-AUG 25, 2025 | D2: AMOUNT | F2: PERIOD: AUG 19-AUG 25, 2025 | G2: AMOUNT
C3: PARTICULARS | F3: PARTICULARS | L3: CASHIER:
C4: TOTAL NET AMOUNT CLIENT PAID CURRENT | D4: =D9 -> 6615525 | F4: TOTAL AMOUNT CLIENT PAID | G4: ='CASH, END'!Q17+'CASH, END'!Q18-'CASH, END'!Q24 -> 0 | I4: =D12-G4 -> 6512925 | M4: RECONCILIATION
C5: TOTAL DEPOT AMOUNT PAID | D5: 6315100 | F5: BORROWINGS FROM OTHER ACCOUNT (EW) | G5: 0 | M5: PASSBOOKS | N5: =G4 -> 0
C6: GROSS MARK - UP | D6: =D4-D5 -> 300425 | F6: TOTAL DEPOT AMOUNT PAID | G6: ='CASH, END'!Q20 -> 0 | I6: =D5-G6 -> 6315100 | M6: GCASH | N6: 5050
F7: EXCESS CASH REMAINING FROM COLLECTIONS | G7: =G4-G6 -> 0 | M7: OTHER BANK CREDITS | N7: -292.55 | P7: =N5+N6+N7+N8+N9+N10+N11 -> -39042.55
F8: Add: Ending, Available Balance Aug 12, 2025 | G8: =CF!H23+CF!H24 -> 0 | M8: COLLECTED LAST CYCLE | N8: =-43800 -> -43800
C9: TOTAL AMOUNT CLIENT PAID | D9: 6615525 | F9: TOTAL EXCESS CASH AFTER PAYMENTS TO DEPOT | G9: =SUM(G7:G8) -> 0
C10: LESS: TUBIL-OFFICE | D10: 0 | F10: LESS: OTHER PAYMENTS / OUTFLOW ( AUG 05 - AUG 11, 2025) | G10: =SUM(G11:G14) -> 0
C11: LESS : PREVIOUS ORDERS | D11: 102600 | F11: RFP of Accounts Payable [ i.e other suppliers, 3rd parties] (-) | G11: =-'CASH, END'!$Q$21 -> 0 | P11: =N12-P7 -> 7724522.5
C12: TOTAL NET AMOUNT CLIENT PAID CURRENT | D12: =D9-D10-D11 -> 6512925 | F12: Cash Withdrawn for PCF Replenishment (-) | G12: =-'CASH, END'!$Q$22 -> 0 | M12: CASHIER | N12: 7685480
F13: Checks Cleared for Loan / Fund Repayments (-) | G13: =-'CASH, END'!$Q$26 -> 0
F14: Other Cash payments / transfer relating to operating activities to EW (-) | G14: =-'CASH, END'!$Q$25 -> 0
F15: ENDING BALANCE, CASH AVAILABLE AUG 11, 2025 | G15: =G9+G10 -> 0 | I15: =CF!H25 -> 0 | J15: 0
F16: LESS: ADVANCE PAYMENTS FOR NEXT CYCLE* | G16: =-349405 -> -349405 | I16: *Cashier
F17: ="ACTUAL CASH " & IF(G17<0, "DEFICIT", IF(G17>0, "EXCESS", "BREAKEVEN")) & " FOR THE CYCLE" -> ACTUAL CASH DEFICIT FOR THE CYCLE | G17: =G15+G16 -> -349405
F19: TOTAL AMOUNT CLIENT PAID | G19: =G4 -> 0
F20: LESS: PAYMENTS FROM NON-DHPP / PREVIOUS CYCLES / ADVANCES / ETC | G20: =SUM(G21:G24) -> -597827.55
F21: PAYMENTS COLLECTED FOR NEXT CYCLE (ADVANCES) [ Data from Cashier] | G21: =G16 -> -349405 | H21: OK
B22: 7c1334 | C22: 700000 | F22: PAYMENTS COLLECTED FROM PREVIOUS CYCLES [Data from Cashier] | G22: =-232750 -> -232750
C23: 300000 | F23: PAYMENTS COLLECTED FROM (DMIE / OPS) [ Data from Cashier ] | G23: =-15380 -> -15380
C24: =C23/C22 -> 0.42857143 | F24: OTHER COLLECTIONS [ Bank data ] | G24: =-292.55 -> -292.55 | I24: 8574420
C25: 0.25 | F25: EQUALS: NET AMOUNT PAID FOR FUEL CURRENT CYCLE (ACCOUNTING) | G25: =G19+G20 -> -597827.55 | I25: 8670950 | J25: cashier
F26: LESS: TOTAL AMOUNT CLIENT PAID CURRENT CYCLE (HAULING) | G26: =D12 -> 6512925 | I26: 96530 | J26: COH
F27: ADD: ADVANCE PAYMENTS LAST CYCLE ( AUG 5-11, 2025 ) | G27: 968125 | I27: 5000 | J27: EW
F28: VARIANCE: REMAINING COLLECTIBLES FOR THE CURRENT CYCLE | G28: =G25-G26+G27 -> -6142627.5 | I28: 15000 | J28: CALICAN | K28: 78900
I29: 51500 | J29: ILAYA | K29: 17630
I30: 7400 | J30: GCASH

Sheet CASH SHORT
C1: DISTRIBUTION AND HAULING DEPARTMENT | F1: FINANCE AND ACCOUNTING DEPARTMENT
C2: PERIOD: NOV 11-NOV 17, 2025 | D2: AMOUNT | F2: PERIOD: NOV 11 - NOV 17, 2025 | G2: AMOUNT
C3: PARTICULARS | F3: PARTICULARS | L3: CASHIER:
C4: TOTAL NET AMOUNT CLIENT PAID CURRENT | D4: =D12 -> 9398277 | F4: TOTAL AMOUNT DEPOSITED ( From Nov 11- Nov 17, 2025) | G4: ='CASH, END'!Q17+'CASH, END'!Q18-'CASH, END'!Q24 -> 0 | I4: =D12-G4 -> 9398277 | M4: RECONCILIATION
C5: TOTAL PAYABLE TO DEPOT | D5: 9068800 | F5: BORROWINGS FROM OTHER ACCOUNT (EW) | G5: ='CASH, END'!$Q$19 -> 0 | M5: PASSBOOKS | N5: =G4 -> 0
C6: GROSS MARK - UP | D6: =D4-D5 -> 329477 | F6: TOTAL PAYABLES TO DEPOT ( Cycle Nov 11 - Nov 17, 2025) | G6: ='CASH, END'!Q20 -> 0 | I6: =D5-G6 -> 9068800 | M6: GCASH | N6: 17450
F7: TOTAL CASH EXCESS FROM COLLECTIONS | G7: =G4+G5-G6 -> 0 | M7: OTHER BANK CREDITS | N7: =-105.19 -> -105.19 | P7: =N5+N6+N7+N8+N9+N10+N11 -> 17344.81
F8: Add: Ending, Available Balance Nov 10, 2025 | G8: =CF!H23+CF!H24 -> 0 | M8: COLLECTED LAST CYCLE | N8: 0
C9: TOTAL AMOUNT CLIENT PAID | D9: 9424327 | F9: NET CASH EXCESS AFTER PAYMENTS TO DEPOT | G9: =SUM(G7:G8) -> 0 | M9: EW | N9: 0
C10: LESS: TUBIL-OFFICE | D10: 26050 | F10: LESS: OTHER PAYMENTS / OUTFLOW ( NOV 11 - NOV 17, 2025) | G10: =SUM(G11:G14) -> 0
C11: LESS : PREVIOUS ORDERS | D11: 0 | F11: RFP of Accounts Payable [ i.e other suppliers, 3rd parties] (-) | G11: =-'CASH, END'!$Q$21 -> 0 | M11: PCF | P11: =N12-P7 -> 7056400.2
C12: TOTAL NET AMOUNT CLIENT PAID CURRENT | D12: =D9-D10-D11 -> 9398277 | F12: Cash Withdrawn for PCF Replenishment (-) | G12: =-'CASH, END'!$Q$22 -> 0 | M12: CASHIER | N12: 7073745
F13: Checks Cleared for Loan / Fund Repayments (-) | G13: =-'CASH, END'!$Q$26 -> 0
F14: Other Cash payments / transfer relating to operating activities to EW (-) | G14: =-'CASH, END'!$Q$25 -> 0
C15: NET MARK-UP | D15: =D6 -> 329477 | F15: TOTAL CASH AVAILABLE, AS OF NOV 17, 2025 | G15: =G9+G10 -> 0 | I15: =CF!H25 -> 0 | J15: 0
C16: CASH OUTFLOW | D16: =G11+G12+G14 -> 0 | F16: LESS: ADVANCE PAYMENTS COLLECTED FOR THE CYCLE | G16: =-53100 -> -53100 | I16: *Cashier
C17: EXCESS FUNDS / NET PROFIT | D17: =D15+D16 -> 329477 | F17: ="ACTUAL CASH " & IF(G17<0, "DEFICIT", IF(G17>0, "EXCESS", "BREAKEVEN")) & " AS OF THE END THE CYCLE" & J17 -> ACTUAL CASH DEFICIT AS OF THE END THE CYCLE NOV. 17, 2025 | G17: =G15+G16 -> -53100 | J17: NOV. 17, 2025
G18: 0
F19: CASH SHORT ACTUAL | G19: =G18-G17 -> 53100
F24: 150000
F25: 4
D26: 150 | F26: =F24*F25 -> 600000
D27: 150 | F27: 300000
F28: =F27/F26 -> 0.5

Sheet CASH, END
C2: CASH FOR THE CYCLE | D2: PNB-OPEX | E2: PNB - CHECKING | F2: PSBC-S | G2: PSBC-C | H2: KB - C | I2: KB - S | J2: 1VB | K2: BDO | L2: MBTC | M2: RCBC | N2: CHINA BANK | O2: E.TAN/STPC | P2: PCF & COH | Q2: GRAND TOTAL
C3: Beg. Balances, June 23, 2026
C4: Less: ADB /Maintaining Balance / PCF
C5: Available Cash in Bank
C6: Add: Deposits | Y6: 49000
C7: Less: Checks Issued/ Withdrawals | Y7: 51900
C8: Available Cash, End. June 29, 2026 | Y8: 1300
C9: Add: ADB/Maintaining Balance/ PCF
C10: TOTAL CASH
D11: =D8/$Q$8 -> #DIV/0! | E11: =E8/$Q$8 -> #DIV/0! | F11: =F8/$Q$8 -> #DIV/0! | G11: =G8/$Q$8 -> #DIV/0! | H11: =H8/$Q$8 -> #DIV/0! | I11: =I8/$Q$8 -> #DIV/0! | J11: =J8/$Q$8 -> #DIV/0! | K11: =K8/$Q$8 -> #DIV/0! | ... N11: =N8/$Q$8 -> #DIV/0!
H12: =H5+H4 -> 0 | I12: =I5+I4 -> 0 | J12: =J5+J4 -> 0 | K12: =K5+K4 -> 0 | L12: =L5+L4 -> 0
C13: T-ENDING
C14: variance
C17: Collections from Distribution and Hauling of Petroleum (+) | R17: =Q17-Q24-Q23 -> 0
C18: Other Cash Collections relating to operating activities (+)
C19: Funds Borrowed from other account (+)
C20: Payments to Supplier of Petroleum Products (-)
C21: RFP of Accounts Payable [ i.e other suppliers, 3rd parties] (-)
C22: Cash Withdrawn for PCF Replenishment (-)
C23: Inter-account fund transfer / EW (-)
C24: Inter-account fund transfer / SA to CA (-)
C25: Other Cash payments / transfer relating to operating activities (-)
C26: Checks Cleared for Loan / Funds Repayments(-)
C27: TOTAL | D27: =D17+D18+D19-D20-D21-D22-D23-D24-D25-D26 -> 0 | E27: =E17-E20-E21-E24 -> 0 | F27: =F17+F18+F19-F20-F21-F22-F23-F24-F25-F26 -> 0 | G27: =G17+G18+G19-G20-G21-G22-G23-G24-G25-G26 -> 0 | H27: =H17+H18+H19-H20-H21-H22-H23-H24-H25-H26 -> 0 | I27: =I17+I18+I19-I20-I21-I22-I23-I24-I25-I26 -> 0 | J27: =J17+J18+J19-J20-J21-J22-J23-J24-J25-J26 -> 0 | K27: =K17+K18+K19-K20-K21-K22-K23-K24-K25-K26 -> 0 | L27: =L17+L18+L19-L20-L21-L22-L23-L24-L25-L26 -> 0 | M27: =M17+M18+M19-M20-M21-M22-M23-M24-M25-M26 -> 0 | ... Q27: =Q17+Q18+Q19-Q20-Q21-Q22-Q23-Q24-Q25-Q26 -> 0
C28: BEGINNING | D28: =D3 -> 0 | E28: =E3 -> 0 | F28: =F3 -> 0 | G28: =G3 -> 0 | H28: =H3 -> 0 | I28: =I3 -> 0 | J28: =J3 -> 0 | K28: =K3 -> 0 | ... Q28: =Q3 -> 0
C29: ENDING | D29: =D10 -> 0 | E29: =E10 -> 0 | F29: =F10 -> 0 | G29: =G10 -> 0 | H29: =H10 -> 0 | I29: =I10 -> 0 | J29: =J10 -> 0 | K29: =K10 -> 0 | ... Q29: =Q10 -> 0
C30: VARIANCE | D30: =D27+D28-D29 -> 0 | E30: =E27+E28-E29 -> 0 | F30: =F27+F28-F29 -> 0 | G30: =G27+G28-G29 -> 0 | H30: =H27+H28-H29 -> 0 | I30: =I27+I28-I29 -> 0 | J30: =J27+J28-J29 -> 0 | K30: =K27+K28-K29 -> 0 | ... Q30: =Q27+Q28-Q29 -> 0
D32: =D6-SUM(D17:D19) -> 0 | E32: =E6-SUM(E17:E19) -> 0 | F32: =F6-SUM(F17:F19) -> 0 | G32: =G6-SUM(G17:G19) -> 0 | H32: =H6-SUM(H17:H19) -> 0 | I32: =I6-SUM(I17:I19) -> 0 | J32: =J6-SUM(J17:J19) -> 0 | K32: =K6-SUM(K17:K19) -> 0 | ... Q32: =Q6-SUM(Q17:Q19) -> 0
D33: =D7-SUM(D20:D26) -> 0 | E33: =E7-SUM(E20:E26) -> 0 | F33: =F7-SUM(F20:F26) -> 0 | G33: =G7-SUM(G20:G26) -> 0 | H33: =H7-SUM(H20:H26) -> 0 | I33: =I7-SUM(I20:I26) -> 0 | J33: =J7-SUM(J20:J26) -> 0 | K33: =K7-SUM(K20:K26) -> 0 | ... Q33: =Q7-SUM(Q20:Q26) -> 0

Sheet trial;
D1: OK | E1: OK | F1: OK | G1: OK | H1: OK | I1: OK | J1: OK | K1: OK | L1: OK | M1: OK | N1: OK
C2: CASH FOR THE CYCLE | D2: PNB | E2: PSBC-S | F2: PSBC-C | G2: KB | H2: 1VB | I2: BDO | J2: MBTC | K2: RCBC | L2: CHINA BANK | M2: E.TAN/STPC | N2: PCF & COH | O2: GRAND TOTAL
C3: Beg. Balances, Jan 06, 2026 | D3: 168787.02 | E3: 18981.36 | F3: 127742.74 | G3: 59030.43 | H3: 8838.88 | I3: 408733.08 | J3: 139004.14 | K3: 11097.11 | L3: 5000 | N3: 192075 | O3: =SUM(D3:N3) -> 1139289.8
C4: Less: ADB /Maintaining Balance / PCF | D4: 50000 | E4: 5000 | F4: 5000 | G4: 5000 | H4: 5000 | I4: 5000 | J4: 50000 | K4: 5000 | L4: 5000 | M4: 0 | N4: 20000 | O4: =SUM(D4:N4) -> 155000
C5: Available Cash in Bank | D5: =D3-D4 -> 118787.02 | E5: =E3-E4 -> 13981.36 | F5: =F3-F4 -> 122742.74 | G5: =G3-G4 -> 54030.43 | H5: =H3-H4 -> 3838.88 | I5: =I3-I4 -> 403733.08 | J5: =J3-J4 -> 89004.14 | K5: =K3-K4 -> 6097.11 | ... N5: =N3-N4 -> 172075 | O5: =SUM(D5:N5) -> 984289.76
C6: Add: Deposits | D6: 3487525 | E6: 6850 | F6: 432650 | G6: 476400 | H6: 3209050 | I6: 156006.27 | J6: 2204550 | K6: 14470 | L6: 0 | M6: 150000 | N6: =108350+471600 -> 579950 | O6: =SUM(D6:N6) -> 10717451 | P6: =O17+O18+O19 -> 10717451 | Q6: =O6-P6 -> 0 | W6: 49000
C7: Less: Checks Issued/ Withdrawals | D7: 3410382.6 | E7: 17435 | F7: 552575.75 | G7: 526400 | H7: 3209350 | I7: 558001.25 | J7: 2171164 | K7: 0 | L7: 0 | M7: 150000 | N7: =172075+471600 -> 643675 | O7: =SUM(D7:N7) -> 11238984 | P7: =O20+O21+O22+O24+O25+O26+O23 -> 11238984 | Q7: =O7-P7 -> 0 | W7: 51900
C8: Available Cash, End. Jan. 12, 2026 | D8: =D5+D6-D7 -> 195929.41 | E8: =E5+E6-E7 -> 3396.36 | F8: =F5+F6-F7 -> 2816.99 | G8: =G5+G6-G7 -> 4030.43 | H8: =H5+H6-H7 -> 3538.88 | I8: =I5+I6-I7 -> 1738.1 | J8: =J5+J6-J7 -> 122390.19 | K8: =K5+K6-K7 -> 20567.11 | ... N8: =N5+N6-N7 -> 108350 | O8: =SUM(D8:N8) -> 462757.47 | Q8: =O3-O4+O6-O7 -> 462757.47 | R8: =O8-Q8 -> -6.9849193e-10 | W8: 1300
C9: Add: ADB/Maintaining Balance/ PCF | D9: =D4 -> 50000 | E9: =E4 -> 5000 | F9: =F4 -> 5000 | G9: =G4 -> 5000 | H9: =H4 -> 5000 | I9: =I4 -> 5000 | J9: =J4 -> 50000 | K9: =K4 -> 5000 | ... N9: =N4 -> 20000 | O9: =SUM(D9:N9) -> 155000
C10: TOTAL CASH | D10: =D8+D9 -> 245929.41 | E10: =E8+E9 -> 8396.36 | F10: =F8+F9 -> 7816.99 | G10: =G8+G9 -> 9030.43 | H10: =H8+H9 -> 8538.88 | I10: =I8+I9 -> 6738.1 | J10: =J8+J9 -> 172390.19 | K10: =K8+K9 -> 25567.11 | ... N10: =N8+N9 -> 128350 | O10: =SUM(D10:N10) -> 617757.47 | P10: =O8+O9 -> 617757.47 | Q10: =O10-P10 -> 0
D11: =D8/$O$8 -> 0.42339546 | E11: =E8/$O$8 -> 0.0073393953 | F11: =F8/$O$8 -> 0.0060874004 | G11: =G8/$O$8 -> 0.0087095947 | H11: =H8/$O$8 -> 0.0076473752 | I11: =I8/$O$8 -> 0.0037559631 | J11: =J8/$O$8 -> 0.2644802 | K11: =K8/$O$8 -> 0.044444685 | L11: =L8/$O$8 -> 0
G12: =G5+G4 -> 59030.43 | H12: =H5+H4 -> 8838.88 | I12: =I5+I4 -> 408733.08 | J12: =J5+J4 -> 139004.14
C13: T-ENDING | D13: 245929.41 | E13: 8396.36 | F13: 7816.99 | G13: 9030.43 | H13: 8538.88 | I13: 6738.1 | J13: 172390.19 | K13: 25567.11 | L13: 5000 | M13: 0 | N13: =108350+20000 -> 128350 | O13: =SUM(D13:N13) -> 617757.47
C14: variance | D14: =D10-D13 -> 0 | E14: =E10-E13 -> 0 | F14: =F10-F13 -> -9.094947e-12 | G14: =G10-G13 -> 5.0931703e-11 | H14: =H10-H13 -> -1.1095835e-10 | I14: =I10-I13 -> -2.3646862e-11 | J14: =J10-J13 -> 0 | K14: =K10-K13 -> 0 | ... O14: =O10-O13 -> 0
C17: Collections from Distribution and Hauling of Petroleum (+) | D17: 3437525 | F17: 422650 | G17: 476400 | H17: 3209050 | I17: 156000 | J17: 1840030 | M17: 150000 | N17: 108350 | O17: =SUM(D17:N17) -> 9800005 | P17: =O17-O24-O23 -> 9041530 | Q17: =O17+O18+O19-O20-O21-O22-O23-O24-O25-O26 -> -521532.29
C18: Other Cash Collections relating to operating activities (+) | D18: 50000 | E18: 6850 | F18: 10000 | I18: 6.27 | J18: 364520 | K18: 14470 | O18: =SUM(D18:N18) -> 445846.27 | Q18: =O17+O18-O23-O24 -> 9487376.3
C19: Funds Borrowed from other account (+) | N19: 471600 | O19: =SUM(D19:N19) -> 471600
C20: Payments to Supplier of Petroleum Products (-) | D20: 2926700 | F20: 412300 | H20: =135900+83600+500000+680000+381050+356000+530000+336800+106000 -> 3109350 | I20: =155000+103000 -> 258000 | J20: 1676750 | M20: 150000 | N20: 471600 | O20: =SUM(D20:N20) -> 9004700
C21: RFP of Accounts Payable [ i.e other suppliers, 3rd parties] (-) | D21: =93740.13+57242.28+2100+25576.74+45000+5923.46+100 -> 229682.61 | F21: =120000+11772 -> 131772 | H21: 100000 | I21: =300000+1.25 -> 300001.25 | J21: =12725+80000+63227.78+63225.87+42695.07 -> 261873.72 | O21: =SUM(D21:N21) -> 1023329.6
C22: Cash Withdrawn for PCF Replenishment (-) | E22: 7435 | F22: 8503.75 | J22: =8987.6+7840.63 -> 16828.23 | O22: =SUM(D22:N22) -> 32766.98
C23: Inter-account fund transfer / EW (-) | O23: =SUM(D23:N23) -> 0
C24: Inter-account fund transfer / SA to CA (-) | D24: =50000 -> 50000 | E24: 10000 | G24: =51450+15000+320200+53750+36000+50000 -> 526400 | N24: 172075 | O24: =SUM(D24:N24) -> 758475
C25: Other Cash payments / transfer relating to operating activities (-) | D25: =29000+175000 -> 204000 | J25: 115712 | O25: =SUM(D25:N25) -> 319712
C26: Checks Cleared for Loan / Funds Repayments(-) | J26: =100000 -> 100000 | O26: =SUM(D26:N26) -> 100000 | P26: =O17+O18-O20-O21-O22-O25-O26 -> -234657.29
C27: TOTAL | D27: =D17+D18+D19-D20-D21-D22-D23-D24-D25-D26 -> 77142.39 | E27: =E17+E18+E19-E20-E21-E22-E23-E24-E25-E26 -> -10585 | F27: =F17+F18+F19-F20-F21-F22-F23-F24-F25-F26 -> -119925.75 | G27: =G17+G18+G19-G20-G21-G22-G23-G24-G25-G26 -> -50000 | H27: =H17+H18+H19-H20-H21-H22-H23-H24-H25-H26 -> -300 | I27: =I17+I18+I19-I20-I21-I22-I23-I24-I25-I26 -> -401994.98 | J27: =J17+J18+J19-J20-J21-J22-J23-J24-J25-J26 -> 33386.05 | K27: =K17+K18+K19-K20-K21-K22-K23-K24-K25-K26 -> 14470 | ... O27: =O17+O18+O19-O20-O21-O22-O23-O24-O25-O26 -> -521532.29
C28: BEGINNING | D28: =D3 -> 168787.02 | E28: =E3 -> 18981.36 | F28: =F3 -> 127742.74 | G28: =G3 -> 59030.43 | H28: =H3 -> 8838.88 | I28: =I3 -> 408733.08 | J28: =J3 -> 139004.14 | K28: =K3 -> 11097.11 | ... O28: =O3 -> 1139289.8
C29: ENDING | D29: =D10 -> 245929.41 | E29: =E10 -> 8396.36 | F29: =F10 -> 7816.99 | G29: =G10 -> 9030.43 | H29: =H10 -> 8538.88 | I29: =I10 -> 6738.1 | J29: =J10 -> 172390.19 | K29: =K10 -> 25567.11 | ... O29: =O10 -> 617757.47
C30: VARIANCE | D30: =D27+D28-D29 -> 0 | E30: =E27+E28-E29 -> 0 | F30: =F27+F28-F29 -> 1.4551915e-11 | G30: =G27+G28-G29 -> -5.0931703e-11 | H30: =H27+H28-H29 -> 1.1095835e-10 | I30: =I27+I28-I29 -> 5.8207661e-11 | J30: =J27+J28-J29 -> 0 | K30: =K27+K28-K29 -> 0 | ... O30: =O27+O28-O29 -> 0
D32: =D6-SUM(D17:D19) -> 0 | E32: =E6-SUM(E17:E19) -> 0 | F32: =F6-SUM(F17:F19) -> 0 | G32: =G6-SUM(G17:G19) -> 0 | H32: =H6-SUM(H17:H19) -> 0 | I32: =I6-SUM(I17:I19) -> 0 | J32: =J6-SUM(J17:J19) -> 0 | K32: =K6-SUM(K17:K19) -> 0 | ... O32: =O6-SUM(O17:O19) -> 0
D33: =D7-SUM(D20:D26) -> 0 | E33: =E7-SUM(E20:E26) -> 0 | F33: =F7-SUM(F20:F26) -> 0 | G33: =G7-SUM(G20:G26) -> 0 | H33: =H7-SUM(H20:H26) -> 0 | I33: =I7-SUM(I20:I26) -> 0 | J33: =J7-SUM(J20:J26) -> 0 | K33: =K7-SUM(K20:K26) -> 0 | ... O33: =O7-SUM(O20:O26) -> 0
